Workbook
Name Slicer_smoker2: #N/A
Name Slicer_Weight_status: #N/A

Sheet Customer
A1: Customer ID | B1: Title | C1: First | D1: Last
A2: Id1 | B2: Ms | C2: Kelly | D2: Hawks
A3: Id2 | B3: Mr | C3: Matthew | D3: Lehner
A4: Id3 | B4: Mr | C4: Phil | D4: Lu
A5: Id4 | B5: Ms | C5: Kelsey | D5: Osborne
A6: Id5 | B6: Ms | C6: Kristyn | D6: Kadala
A7: Id6 | B7: Mr | C7: Russell | D7: Baker
A8: Id7 | B8: Mr | C8: Scott | D8: Macpherson
A9: Id8 | B9: Mr | C9: Stephen | D9: Hallman
A10: Id9 | B10: Mr | C10: Patrick | D10: Moran
A11: Id10 | B11: Ms | C11: Brooke | D11: Benner
A12: Id11 | B12: Ms | C12: Andrea Paola | D12: Fierro Vargas
... A2336: Id2335 | B2336: Mr | C2336: Aaron | D2336: German

Sheet Hospitalisation
A1: Customer ID | B1: children | C1: charges | D1: Hospital tier | E1: State ID | F1: Hospital tier2 | G1: City tier | H1: Yea | I1: Hsp Tier | J1: Cty Tier | K1: StateID | L1: Age | M1: Date of Birth2
A2: Id1 | B2: 0 | C2: 63770.43 | D2: tier - 1 | E2: R1013 | F2: tier - 1 | G2: tier - 3 | H2: 1968 | I2: {=IF(D2="", INDEX($D$2:$D$2345, MODE(MATCH(IF($D$2:$D$2345<>"",$D$2:$D$2345), IF($D$2:$D$2345<>"",$D$2:$D$2345),0))), D2)} -> tier - 1 | J2: {=IF(G2="", INDEX($G$2:$G$2345, MODE(MATCH(IF($G$2:$G$2345<>"",$G$2:$G$2345), IF($G$2:$G$2345<>"",$G$2:$G$2345),0))), G2)} -> tier - 3 | K2: {=IF(E2="", INDEX($E$2:$E$2345, MODE(MATCH(IF($E$2:$E$2345<>"",$E$2:$E$2345), IF($E$2:$E$2345<>"",$E$2:$E$2345),0))), E2)} -> R1013 | L2: =INT(YEARFRAC(M2,DATE(2023,6,8))) -> 39 | M2: 30601
A3: Id10 | B3: 0 | C3: 48885.14 | D3: tier - 1 | E3: R1013 | F3: tier - 1 | G3: tier - 2 | H3: 1978 | I3: {=IF(D3="", INDEX($D$2:$D$2345, MODE(MATCH(IF($D$2:$D$2345<>"",$D$2:$D$2345), IF($D$2:$D$2345<>"",$D$2:$D$2345),0))), D3)} -> tier - 1 | J3: {=IF(G3="", INDEX($G$2:$G$2345, MODE(MATCH(IF($G$2:$G$2345<>"",$G$2:$G$2345), IF($G$2:$G$2345<>"",$G$2:$G$2345),0))), G3)} -> tier - 2 | K3: {=IF(E3="", INDEX($E$2:$E$2345, MODE(MATCH(IF($E$2:$E$2345<>"",$E$2:$E$2345), IF($E$2:$E$2345<>"",$E$2:$E$2345),0))), E3)} -> R1013 | L3: =INT(YEARFRAC(M3,DATE(2023,6,8))) -> 59 | M3: 23374
A4: Id100 | B4: 2 | C4: 40284.38 | D4: tier - 1 | E4: R1012 | F4: tier - 1 | G4: tier - 3 | H4: 1977 | I4: {=IF(D4="", INDEX($D$2:$D$2345, MODE(MATCH(IF($D$2:$D$2345<>"",$D$2:$D$2345), IF($D$2:$D$2345<>"",$D$2:$D$2345),0))), D4)} -> tier - 1 | J4: {=IF(G4="", INDEX($G$2:$G$2345, MODE(MATCH(IF($G$2:$G$2345<>"",$G$2:$G$2345), IF($G$2:$G$2345<>"",$G$2:$G$2345),0))), G4)} -> tier - 3 | K4: {=IF(E4="", INDEX($E$2:$E$2345, MODE(MATCH(IF($E$2:$E$2345<>"",$E$2:$E$2345), IF($E$2:$E$2345<>"",$E$2:$E$2345),0))), E4)} -> R1012 | L4: =INT(YEARFRAC(M4,DATE(2023,6,8))) -> 60 | M4: 22824
A5: Id1000 | B5: 3 | C5: 11250.43 | D5: tier - 3 | E5: R1026 | F5: tier - 3 | G5: tier - 2 | H5: 1989 | I5: {=IF(D5="", INDEX($D$2:$D$2345, MODE(MATCH(IF($D$2:$D$2345<>"",$D$2:$D$2345), IF($D$2:$D$2345<>"",$D$2:$D$2345),0))), D5)} -> tier - 3 | J5: {=IF(G5="", INDEX($G$2:$G$2345, MODE(MATCH(IF($G$2:$G$2345<>"",$G$2:$G$2345), IF($G$2:$G$2345<>"",$G$2:$G$2345),0))), G5)} -> tier - 2 | K5: {=IF(E5="", INDEX($E$2:$E$2345, MODE(MATCH(IF($E$2:$E$2345<>"",$E$2:$E$2345), IF($E$2:$E$2345<>"",$E$2:$E$2345),0))), E5)} -> R1026 | L5: =INT(YEARFRAC(M5,DATE(2023,6,8))) -> 53 | M5: 25554
A6: Id1001 | B6: 2 | C6: 11244.38 | D6: tier - 3 | E6: R1016 | F6: tier - 3 | G6: tier - 1 | H6: 1969 | I6: {=IF(D6="", INDEX($D$2:$D$2345, MODE(MATCH(IF($D$2:$D$2345<>"",$D$2:$D$2345), IF($D$2:$D$2345<>"",$D$2:$D$2345),0))), D6)} -> tier - 3 | J6: {=IF(G6="", INDEX($G$2:$G$2345, MODE(MATCH(IF($G$2:$G$2345<>"",$G$2:$G$2345), IF($G$2:$G$2345<>"",$G$2:$G$2345),0))), G6)} -> tier - 1 | K6: {=IF(E6="", INDEX($E$2:$E$2345, MODE(MATCH(IF($E$2:$E$2345<>"",$E$2:$E$2345), IF($E$2:$E$2345<>"",$E$2:$E$2345),0))), E6)} -> R1016 | L6: =INT(YEARFRAC(M6,DATE(2023,6,8))) -> 33 | M6: 32872
A7: Id1002 | B7: 2 | C7: 11217.35 | D7: tier - 3 | E7: R1025 | F7: tier - 3 | G7: tier - 2 | H7: 1976 | I7: {=IF(D7="", INDEX($D$2:$D$2345, MODE(MATCH(IF($D$2:$D$2345<>"",$D$2:$D$2345), IF($D$2:$D$2345<>"",$D$2:$D$2345),0))), D7)} -> tier - 3 | J7: {=IF(G7="", INDEX($G$2:$G$2345, MODE(MATCH(IF($G$2:$G$2345<>"",$G$2:$G$2345), IF($G$2:$G$2345<>"",$G$2:$G$2345),0))), G7)} -> tier - 2 | K7: {=IF(E7="", INDEX($E$2:$E$2345, MODE(MATCH(IF($E$2:$E$2345<>"",$E$2:$E$2345), IF($E$2:$E$2345<>"",$E$2:$E$2345),0))), E7)} -> R1025 | L7: =INT(YEARFRAC(M7,DATE(2023,6,8))) -> 53 | M7: 25382
A8: Id1003 | B8: 2 | C8: 11187.66 | D8: tier - 3 | E8: R1012 | F8: tier - 3 | G8: tier - 2 | H8: 1970 | I8: {=IF(D8="", INDEX($D$2:$D$2345, MODE(MATCH(IF($D$2:$D$2345<>"",$D$2:$D$2345), IF($D$2:$D$2345<>"",$D$2:$D$2345),0))), D8)} -> tier - 3 | J8: {=IF(G8="", INDEX($G$2:$G$2345, MODE(MATCH(IF($G$2:$G$2345<>"",$G$2:$G$2345), IF($G$2:$G$2345<>"",$G$2:$G$2345),0))), G8)} -> tier - 2 | K8: {=IF(E8="", INDEX($E$2:$E$2345, MODE(MATCH(IF($E$2:$E$2345<>"",$E$2:$E$2345), IF($E$2:$E$2345<>"",$E$2:$E$2345),0))), E8)} -> R1012 | L8: =INT(YEARFRAC(M8,DATE(2023,6,8))) -> 46 | M8: 27925
A9: Id1004 | B9: 0 | C9: 11186.2 | D9: tier - 3 | E9: R1021 | F9: tier - 3 | G9: tier - 2 | H9: 1972 | I9: {=IF(D9="", INDEX($D$2:$D$2345, MODE(MATCH(IF($D$2:$D$2345<>"",$D$2:$D$2345), IF($D$2:$D$2345<>"",$D$2:$D$2345),0))), D9)} -> tier - 3 | J9: {=IF(G9="", INDEX($G$2:$G$2345, MODE(MATCH(IF($G$2:$G$2345<>"",$G$2:$G$2345), IF($G$2:$G$2345<>"",$G$2:$G$2345),0))), G9)} -> tier - 2 | K9: {=IF(E9="", INDEX($E$2:$E$2345, MODE(MATCH(IF($E$2:$E$2345<>"",$E$2:$E$2345), IF($E$2:$E$2345<>"",$E$2:$E$2345),0))), E9)} -> R1021 | L9: =INT(YEARFRAC(M9,DATE(2023,6,8))) -> 52 | M9: 25814
A10: Id1005 | B10: 0 | C10: 11165.42 | D10: tier - 3 | E10: R1016 | F10: tier - 3 | G10: tier - 1 | H10: 1966 | I10: {=IF(D10="", INDEX($D$2:$D$2345, MODE(MATCH(IF($D$2:$D$2345<>"",$D$2:$D$2345), IF($D$2:$D$2345<>"",$D$2:$D$2345),0))), D10)} -> tier - 3 | J10: {=IF(G10="", INDEX($G$2:$G$2345, MODE(MATCH(IF($G$2:$G$2345<>"",$G$2:$G$2345), IF($G$2:$G$2345<>"",$G$2:$G$2345),0))), G10)} -> tier - 1 | K10: {=IF(E10="", INDEX($E$2:$E$2345, MODE(MATCH(IF($E$2:$E$2345<>"",$E$2:$E$2345), IF($E$2:$E$2345<>"",$E$2:$E$2345),0))), E10)} -> R1016 | L10: =INT(YEARFRAC(M10,DATE(2023,6,8))) -> 50 | M10: 26517
A11: Id1006 | B11: 2 | C11: 11163.57 | D11: tier - 3 | E11: R1011 | F11: tier - 3 | G11: tier - 2 | H11: 1969 | I11: {=IF(D11="", INDEX($D$2:$D$2345, MODE(MATCH(IF($D$2:$D$2345<>"",$D$2:$D$2345), IF($D$2:$D$2345<>"",$D$2:$D$2345),0))), D11)} -> tier - 3 | J11: {=IF(G11="", INDEX($G$2:$G$2345, MODE(MATCH(IF($G$2:$G$2345<>"",$G$2:$G$2345), IF($G$2:$G$2345<>"",$G$2:$G$2345),0))), G11)} -> tier - 2 | K11: {=IF(E11="", INDEX($E$2:$E$2345, MODE(MATCH(IF($E$2:$E$2345<>"",$E$2:$E$2345), IF($E$2:$E$2345<>"",$E$2:$E$2345),0))), E11)} -> R1011 | L11: =INT(YEARFRAC(M11,DATE(2023,6,8))) -> 56 | M11: 24283
A12: Id1007 | B12: 2 | C12: 11150.78 | D12: tier - 3 | E12: R1011 | F12: tier - 3 | G12: tier - 2 | H12: 1969 | I12: {=IF(D12="", INDEX($D$2:$D$2345, MODE(MATCH(IF($D$2:$D$2345<>"",$D$2:$D$2345), IF($D$2:$D$2345<>"",$D$2:$D$2345),0))), D12)} -> tier - 3 | J12: {=IF(G12="", INDEX($G$2:$G$2345, MODE(MATCH(IF($G$2:$G$2345<>"",$G$2:$G$2345), IF($G$2:$G$2345<>"",$G$2:$G$2345),0))), G12)} -> tier - 2 | K12: {=IF(E12="", INDEX($E$2:$E$2345, MODE(MATCH(IF($E$2:$E$2345<>"",$E$2:$E$2345), IF($E$2:$E$2345<>"",$E$2:$E$2345),0))), E12)} -> R1011 | L12: =INT(YEARFRAC(M12,DATE(2023,6,8))) -> 53 | M12: 25537
A13: Id1008 | B13: 2 | C13: 11103.33 | D13: tier - 3 | E13: R1021 | F13: tier - 3 | G13: tier - 1 | H13: 1980 | I13: {=IF(D13="", INDEX($D$2:$D$2345, MODE(MATCH(IF($D$2:$D$2345<>"",$D$2:$D$2345), IF($D$2:$D$2345<>"",$D$2:$D$2345),0))), D13)} -> tier - 3 | J13: {=IF(G13="", INDEX($G$2:$G$2345, MODE(MATCH(IF($G$2:$G$2345<>"",$G$2:$G$2345), IF($G$2:$G$2345<>"",$G$2:$G$2345),0))), G13)} -> tier - 1 | K13: {=IF(E13="", INDEX($E$2:$E$2345, MODE(MATCH(IF($E$2:$E$2345<>"",$E$2:$E$2345), IF($E$2:$E$2345<>"",$E$2:$E$2345),0))), E13)} -> R1021 | L13: =INT(YEARFRAC(M13,DATE(2023,6,8))) -> 53 | M13: 25435
... A320: Id1285 | B320: 1 | C320: 8551.35 | D320: tier - 2 | E320: R1011 | F320: tier - 2 | G320: tier - 2 | H320: 1975 | I320: {=IF(D320="", INDEX($D$2:$D$2345, MODE(MATCH(IF($D$2:$D$2345<>"",$D$2:$D$2345), IF($D$2:$D$2345<>"",$D$2:$D$2345),0))), D320)} -> tier - 2 | J320: {=IF(G320="", INDEX($G$2:$G$2345, MODE(MATCH(IF($G$2:$G$2345<>"",$G$2:$G$2345), IF($G$2:$G$2345<>"",$G$2:$G$2345),0))), G320)} -> tier - 2 | K320: {=IF(E320="", INDEX($E$2:$E$2345, MODE(MATCH(IF($E$2:$E$2345<>"",$E$2:$E$2345), IF($E$2:$E$2345<>"",$E$2:$E$2345),0))), E320)} -> R1011 | L320: =INT(YEARFRAC(M320,DATE(2023,6,8))) -> 47 | M320: 27612
A321: Id1286 | B321: 1 | C321: 8547.69 | D321: tier - 2 | E321: R1013 | F321: tier - 2 | G321: tier - 1 | I321: {=IF(D321="", INDEX($D$2:$D$2345, MODE(MATCH(IF($D$2:$D$2345<>"",$D$2:$D$2345), IF($D$2:$D$2345<>"",$D$2:$D$2345),0))), D321)} -> tier - 2 | J321: {=IF(G321="", INDEX($G$2:$G$2345, MODE(MATCH(IF($G$2:$G$2345<>"",$G$2:$G$2345), IF($G$2:$G$2345<>"",$G$2:$G$2345),0))), G321)} -> tier - 1 | K321: {=IF(E321="", INDEX($E$2:$E$2345, MODE(MATCH(IF($E$2:$E$2345<>"",$E$2:$E$2345), IF($E$2:$E$2345<>"",$E$2:$E$2345),0))), E321)} -> R1013 | L321: =INT(YEARFRAC(M321,DATE(2023,6,8))) -> 47 | M321: 27740
A322: Id1287 | B322: 1 | C322: 8539.67 | D322: tier - 2 | E322: R1011 | F322: tier - 2 | G322: tier - 3 | H322: 1975 | I322: {=IF(D322="", INDEX($D$2:$D$2345, MODE(MATCH(IF($D$2:$D$2345<>"",$D$2:$D$2345), IF($D$2:$D$2345<>"",$D$2:$D$2345),0))), D322)} -> tier - 2 | J322: {=IF(G322="", INDEX($G$2:$G$2345, MODE(MATCH(IF($G$2:$G$2345<>"",$G$2:$G$2345), IF($G$2:$G$2345<>"",$G$2:$G$2345),0))), G322)} -> tier - 3 | K322: {=IF(E322="", INDEX($E$2:$E$2345, MODE(MATCH(IF($E$2:$E$2345<>"",$E$2:$E$2345), IF($E$2:$E$2345<>"",$E$2:$E$2345),0))), E322)} -> R1011 | L322: =INT(YEARFRAC(M322,DATE(2023,6,8))) -> 39 | M322: 30626
A323: Id1288 | B323: 3 | C323: 8538.29 | D323: tier - 2 | E323: R1024 | F323: tier - 2 | G323: tier - 3 | H323: 1981 | I323: {=IF(D323="", INDEX($D$2:$D$2345, MODE(MATCH(IF($D$2:$D$2345<>"",$D$2:$D$2345), IF($D$2:$D$2345<>"",$D$2:$D$2345),0))), D323)} -> tier - 2 | J323: {=IF(G323="", INDEX($G$2:$G$2345, MODE(MATCH(IF($G$2:$G$2345<>"",$G$2:$G$2345), IF($G$2:$G$2345<>"",$G$2:$G$2345),0))), G323)} -> tier - 3 | K323: {=IF(E323="", INDEX($E$2:$E$2345, MODE(MATCH(IF($E$2:$E$2345<>"",$E$2:$E$2345), IF($E$2:$E$2345<>"",$E$2:$E$2345),0))), E323)} -> R1024 | L323: =INT(YEARFRAC(M323,DATE(2023,6,8))) -> 47 | M323: 27755
A324: Id1289 | B324: 0 | C324: 8534.67 | D324: tier - 2 | E324: R1024 | F324: tier - 2 | G324: tier - 3 | I324: {=IF(D324="", INDEX($D$2:$D$2345, MODE(MATCH(IF($D$2:$D$2345<>"",$D$2:$D$2345), IF($D$2:$D$2345<>"",$D$2:$D$2345),0))), D324)} -> tier - 2 | J324: {=IF(G324="", INDEX($G$2:$G$2345, MODE(MATCH(IF($G$2:$G$2345<>"",$G$2:$G$2345), IF($G$2:$G$2345<>"",$G$2:$G$2345),0))), G324)} -> tier - 3 | K324: {=IF(E324="", INDEX($E$2:$E$2345, MODE(MATCH(IF($E$2:$E$2345<>"",$E$2:$E$2345), IF($E$2:$E$2345<>"",$E$2:$E$2345),0))), E324)} -> R1024 | L324: =INT(YEARFRAC(M324,DATE(2023,6,8))) -> 41 | M324: 29791
A325: Id129 | B325: 1 | C325: 39047.29 | D325: tier - 1 | E325: R1017 | F325: tier - 1 | G325: tier - 3 | H325: 1985 | I325: {=IF(D325="", INDEX($D$2:$D$2345, MODE(MATCH(IF($D$2:$D$2345<>"",$D$2:$D$2345), IF($D$2:$D$2345<>"",$D$2:$D$2345),0))), D325)} -> tier - 1 | J325: {=IF(G325="", INDEX($G$2:$G$2345, MODE(MATCH(IF($G$2:$G$2345<>"",$G$2:$G$2345), IF($G$2:$G$2345<>"",$G$2:$G$2345),0))), G325)} -> tier - 3 | K325: {=IF(E325="", INDEX($E$2:$E$2345, MODE(MATCH(IF($E$2:$E$2345<>"",$E$2:$E$2345), IF($E$2:$E$2345<>"",$E$2:$E$2345),0))), E325)} -> R1017 | L325: =INT(YEARFRAC(M325,DATE(2023,6,8))) -> 40 | M325: 30214
A326: Id1290 | B326: 2 | C326: 8527.53 | D326: tier - 2 | E326: R1013 | F326: tier - 2 | G326: tier - 2 | H326: 1977 | I326: {=IF(D326="", INDEX($D$2:$D$2345, MODE(MATCH(IF($D$2:$D$2345<>"",$D$2:$D$2345), IF($D$2:$D$2345<>"",$D$2:$D$2345),0))), D326)} -> tier - 2 | J326: {=IF(G326="", INDEX($G$2:$G$2345, MODE(MATCH(IF($G$2:$G$2345<>"",$G$2:$G$2345), IF($G$2:$G$2345<>"",$G$2:$G$2345),0))), G326)} -> tier - 2 | K326: {=IF(E326="", INDEX($E$2:$E$2345, MODE(MATCH(IF($E$2:$E$2345<>"",$E$2:$E$2345), IF($E$2:$E$2345<>"",$E$2:$E$2345),0))), E326)} -> R1013 | L326: =INT(YEARFRAC(M326,DATE(2023,6,8))) -> 39 | M326: 30523
A327: Id1291 | B327: 3 | C327: 8522 | D327: tier - 2 | E327: R1011 | F327: tier - 2 | G327: tier - 2 | H327: 1979 | I327: {=IF(D327="", INDEX($D$2:$D$2345, MODE(MATCH(IF($D$2:$D$2345<>"",$D$2:$D$2345), IF($D$2:$D$2345<>"",$D$2:$D$2345),0))), D327)} -> tier - 2 | J327: {=IF(G327="", INDEX($G$2:$G$2345, MODE(MATCH(IF($G$2:$G$2345<>"",$G$2:$G$2345), IF($G$2:$G$2345<>"",$G$2:$G$2345),0))), G327)} -> tier - 2 | K327: {=IF(E327="", INDEX($E$2:$E$2345, MODE(MATCH(IF($E$2:$E$2345<>"",$E$2:$E$2345), IF($E$2:$E$2345<>"",$E$2:$E$2345),0))), E327)} -> R1011 | L327: =INT(YEARFRAC(M327,DATE(2023,6,8))) -> 45 | M327: 28350
A328: Id1292 | B328: 2 | C328: 8520.03 | D328: tier - 2 | E328: R1011 | F328: tier - 2 | G328: tier - 3 | H328: 1977 | I328: {=IF(D328="", INDEX($D$2:$D$2345, MODE(MATCH(IF($D$2:$D$2345<>"",$D$2:$D$2345), IF($D$2:$D$2345<>"",$D$2:$D$2345),0))), D328)} -> tier - 2 | J328: {=IF(G328="", INDEX($G$2:$G$2345, MODE(MATCH(IF($G$2:$G$2345<>"",$G$2:$G$2345), IF($G$2:$G$2345<>"",$G$2:$G$2345),0))), G328)} -> tier - 3 | K328: {=IF(E328="", INDEX($E$2:$E$2345, MODE(MATCH(IF($E$2:$E$2345<>"",$E$2:$E$2345), IF($E$2:$E$2345<>"",$E$2:$E$2345),0))), E328)} -> R1011 | L328: =INT(YEARFRAC(M328,DATE(2023,6,8))) -> 43 | M328: 29218
A329: Id1293 | B329: 2 | C329: 8516.83 | D329: tier - 2 | E329: R1013 | F329: tier - 2 | G329: tier - 1 | H329: 1977 | I329: {=IF(D329="", INDEX($D$2:$D$2345, MODE(MATCH(IF($D$2:$D$2345<>"",$D$2:$D$2345), IF($D$2:$D$2345<>"",$D$2:$D$2345),0))), D329)} -> tier - 2 | J329: {=IF(G329="", INDEX($G$2:$G$2345, MODE(MATCH(IF($G$2:$G$2345<>"",$G$2:$G$2345), IF($G$2:$G$2345<>"",$G$2:$G$2345),0))), G329)} -> tier - 1 | K329: {=IF(E329="", INDEX($E$2:$E$2345, MODE(MATCH(IF($E$2:$E$2345<>"",$E$2:$E$2345), IF($E$2:$E$2345<>"",$E$2:$E$2345),0))), E329)} -> R1013 | L329: =INT(YEARFRAC(M329,DATE(2023,6,8))) -> 45 | M329: 28297
A330: Id1294 | B330: 2 | C330: 8515.76 | D330: tier - 2 | E330: R1013 | F330: tier - 2 | G330: tier - 2 | H330: 1977 | I330: {=IF(D330="", INDEX($D$2:$D$2345, MODE(MATCH(IF($D$2:$D$2345<>"",$D$2:$D$2345), IF($D$2:$D$2345<>"",$D$2:$D$2345),0))), D330)} -> tier - 2 | J330: {=IF(G330="", INDEX($G$2:$G$2345, MODE(MATCH(IF($G$2:$G$2345<>"",$G$2:$G$2345), IF($G$2:$G$2345<>"",$G$2:$G$2345),0))), G330)} -> tier - 2 | K330: {=IF(E330="", INDEX($E$2:$E$2345, MODE(MATCH(IF($E$2:$E$2345<>"",$E$2:$E$2345), IF($E$2:$E$2345<>"",$E$2:$E$2345),0))), E330)} -> R1013 | L330: =INT(YEARFRAC(M330,DATE(2023,6,8))) -> 45 | M330: 28485
A331: Id1295 | B331: 0 | C331: 8471.65 | D331: tier - 2 | E331: R1012 | F331: tier - 2 | G331: tier - 1 | H331: 1993 | I331: {=IF(D331="", INDEX($D$2:$D$2345, MODE(MATCH(IF($D$2:$D$2345<>"",$D$2:$D$2345), IF($D$2:$D$2345<>"",$D$2:$D$2345),0))), D331)} -> tier - 2 | J331: {=IF(G331="", INDEX($G$2:$G$2345, MODE(MATCH(IF($G$2:$G$2345<>"",$G$2:$G$2345), IF($G$2:$G$2345<>"",$G$2:$G$2345),0))), G331)} -> tier - 1 | K331: {=IF(E331="", INDEX($E$2:$E$2345, MODE(MATCH(IF($E$2:$E$2345<>"",$E$2:$E$2345), IF($E$2:$E$2345<>"",$E$2:$E$2345),0))), E331)} -> R1012 | L331: =INT(YEARFRAC(M331,DATE(2023,6,8))) -> 45 | M331: 28439
A332: Id1296 | B332: 0 | C332: 8466.35 | D332: tier - 2 | E332: R1012 | F332: tier - 2 | G332: tier - 2 | H332: 1992 | I332: {=IF(D332="", INDEX($D$2:$D$2345, MODE(MATCH(IF($D$2:$D$2345<>"",$D$2:$D$2345), IF($D$2:$D$2345<>"",$D$2:$D$2345),0))), D332)} -> tier - 2 | J332: {=IF(G332="", INDEX($G$2:$G$2345, MODE(MATCH(IF($G$2:$G$2345<>"",$G$2:$G$2345), IF($G$2:$G$2345<>"",$G$2:$G$2345),0))), G332)} -> tier - 2 | K332: {=IF(E332="", INDEX($E$2:$E$2345, MODE(MATCH(IF($E$2:$E$2345<>"",$E$2:$E$2345), IF($E$2:$E$2345<>"",$E$2:$E$2345),0))), E332)} -> R1012 | L332: =INT(YEARFRAC(M332,DATE(2023,6,8))) -> 29 | M332: 34221
A333: Id1297 | B333: 0 | C333: 8457.82 | D333: tier - 2 | E333: R1011 | F333: tier - 2 | G333: tier - 3 | H333: 1972 | I333: {=IF(D333="", INDEX($D$2:$D$2345, MODE(MATCH(IF($D$2:$D$2345<>"",$D$2:$D$2345), IF($D$2:$D$2345<>"",$D$2:$D$2345),0))), D333)} -> tier - 2 | J333: {=IF(G333="", INDEX($G$2:$G$2345, MODE(MATCH(IF($G$2:$G$2345<>"",$G$2:$G$2345), IF($G$2:$G$2345<>"",$G$2:$G$2345),0))), G333)} -> tier - 3 | K333: {=IF(E333="", INDEX($E$2:$E$2345, MODE(MATCH(IF($E$2:$E$2345<>"",$E$2:$E$2345), IF($E$2:$E$2345<>"",$E$2:$E$2345),0))), E333)} -> R1011 | L333: =INT(YEARFRAC(M333,DATE(2023,6,8))) -> 30 | M333: 33964
A334: Id1298 | B334: 3 | C334: 8450.82 | D334: tier - 2 | E334: R1025 | F334: tier - 2 | G334: tier - 2 | H334: 1984 | I334: {=IF(D334="", INDEX($D$2:$D$2345, MODE(MATCH(IF($D$2:$D$2345<>"",$D$2:$D$2345), IF($D$2:$D$2345<>"",$D$2:$D$2345),0))), D334)} -> tier - 2 | J334: {=IF(G334="", INDEX($G$2:$G$2345, MODE(MATCH(IF($G$2:$G$2345<>"",$G$2:$G$2345), IF($G$2:$G$2345<>"",$G$2:$G$2345),0))), G334)} -> tier - 2 | K334: {=IF(E334="", INDEX($E$2:$E$2345, MODE(MATCH(IF($E$2:$E$2345<>"",$E$2:$E$2345), IF($E$2:$E$2345<>"",$E$2:$E$2345),0))), E334)} -> R1025 | L334: =INT(YEARFRAC(M334,DATE(2023,6,8))) -> 50 | M334: 26469
A335: Id1299 | B335: 0 | C335: 8448.66 | D335: tier - 3 | E335: R1013 | F335: tier - 3 | G335: tier - 1 | H335: 1966 | I335: {=IF(D335="", INDEX($D$2:$D$2345, MODE(MATCH(IF($D$2:$D$2345<>"",$D$2:$D$2345), IF($D$2:$D$2345<>"",$D$2:$D$2345),0))), D335)} -> tier - 3 | J335: {=IF(G335="", INDEX($G$2:$G$2345, MODE(MATCH(IF($G$2:$G$2345<>"",$G$2:$G$2345), IF($G$2:$G$2345<>"",$G$2:$G$2345),0))), G335)} -> tier - 1 | K335: {=IF(E335="", INDEX($E$2:$E$2345, MODE(MATCH(IF($E$2:$E$2345<>"",$E$2:$E$2345), IF($E$2:$E$2345<>"",$E$2:$E$2345),0))), E335)} -> R1013 | L335: =INT(YEARFRAC(M335,DATE(2023,6,8))) -> 38 | M335: 30845
A336: Id13 | B336: 0 | C336: 48673.56 | D336: tier - 1 | E336: R1013 | F336: tier - 1 | G336: tier - 2 | H336: 1962 | I336: {=IF(D336="", INDEX($D$2:$D$2345, MODE(MATCH(IF($D$2:$D$2345<>"",$D$2:$D$2345), IF($D$2:$D$2345<>"",$D$2:$D$2345),0))), D336)} -> tier - 1 | J336: {=IF(G336="", INDEX($G$2:$G$2345, MODE(MATCH(IF($G$2:$G$2345<>"",$G$2:$G$2345), IF($G$2:$G$2345<>"",$G$2:$G$2345),0))), G336)} -> tier - 2 | K336: {=IF(E336="", INDEX($E$2:$E$2345, MODE(MATCH(IF($E$2:$E$2345<>"",$E$2:$E$2345), IF($E$2:$E$2345<>"",$E$2:$E$2345),0))), E336)} -> R1013 | L336: =INT(YEARFRAC(M336,DATE(2023,6,8))) -> 57 | M336: 24026
... A780: Id17 | B780: 1 | C780: 47928.03 | D780: tier - 2 | E780: R1011 | F780: tier - 2 | G780: tier - 3 | H780: 1958 | I780: {=IF(D780="", INDEX($D$2:$D$2345, MODE(MATCH(IF($D$2:$D$2345<>"",$D$2:$D$2345), IF($D$2:$D$2345<>"",$D$2:$D$2345),0))), D780)} -> tier - 2 | J780: {=IF(G780="", INDEX($G$2:$G$2345, MODE(MATCH(IF($G$2:$G$2345<>"",$G$2:$G$2345), IF($G$2:$G$2345<>"",$G$2:$G$2345),0))), G780)} -> tier - 3 | K780: {=IF(E780="", INDEX($E$2:$E$2345, MODE(MATCH(IF($E$2:$E$2345<>"",$E$2:$E$2345), IF($E$2:$E$2345<>"",$E$2:$E$2345),0))), E780)} -> R1011 | L780: =INT(YEARFRAC(M780,DATE(2023,6,8))) -> 60 | M780: 22966
A781: Id170 | B781: 1 | C781: 37165.16 | D781: tier - 1 | F781: tier - 1 | G781: tier - 3 | H781: 2000 | I781: {=IF(D781="", INDEX($D$2:$D$2345, MODE(MATCH(IF($D$2:$D$2345<>"",$D$2:$D$2345), IF($D$2:$D$2345<>"",$D$2:$D$2345),0))), D781)} -> tier - 1 | J781: {=IF(G781="", INDEX($G$2:$G$2345, MODE(MATCH(IF($G$2:$G$2345<>"",$G$2:$G$2345), IF($G$2:$G$2345<>"",$G$2:$G$2345),0))), G781)} -> tier - 3 | K781: {=IF(E781="", INDEX($E$2:$E$2345, MODE(MATCH(IF($E$2:$E$2345<>"",$E$2:$E$2345), IF($E$2:$E$2345<>"",$E$2:$E$2345),0))), E781)} -> R1013 | L781: =INT(YEARFRAC(M781,DATE(2023,6,8))) -> 32 | M781: 33121
A782: Id1700 | B782: 2 | C782: 5428.98 | D782: tier - 2 | E782: R1012 | F782: tier - 2 | G782: tier - 2 | H782: 1978 | I782: {=IF(D782="", INDEX($D$2:$D$2345, MODE(MATCH(IF($D$2:$D$2345<>"",$D$2:$D$2345), IF($D$2:$D$2345<>"",$D$2:$D$2345),0))), D782)} -> tier - 2 | J782: {=IF(G782="", INDEX($G$2:$G$2345, MODE(MATCH(IF($G$2:$G$2345<>"",$G$2:$G$2345), IF($G$2:$G$2345<>"",$G$2:$G$2345),0))), G782)} -> tier - 2 | K782: {=IF(E782="", INDEX($E$2:$E$2345, MODE(MATCH(IF($E$2:$E$2345<>"",$E$2:$E$2345), IF($E$2:$E$2345<>"",$E$2:$E$2345),0))), E782)} -> R1012 | L782: =INT(YEARFRAC(M782,DATE(2023,6,8))) -> 41 | M782: 30110
A783: Id1701 | B783: 3 | C783: 5428.73 | D783: tier - 3 | E783: R1017 | F783: tier - 3 | G783: tier - 1 | H783: 1992 | I783: {=IF(D783="", INDEX($D$2:$D$2345, MODE(MATCH(IF($D$2:$D$2345<>"",$D$2:$D$2345), IF($D$2:$D$2345<>"",$D$2:$D$2345),0))), D783)} -> tier - 3 | J783: {=IF(G783="", INDEX($G$2:$G$2345, MODE(MATCH(IF($G$2:$G$2345<>"",$G$2:$G$2345), IF($G$2:$G$2345<>"",$G$2:$G$2345),0))), G783)} -> tier - 1 | K783: {=IF(E783="", INDEX($E$2:$E$2345, MODE(MATCH(IF($E$2:$E$2345<>"",$E$2:$E$2345), IF($E$2:$E$2345<>"",$E$2:$E$2345),0))), E783)} -> R1017 | L783: =INT(YEARFRAC(M783,DATE(2023,6,8))) -> 44 | M783: 28750
A784: Id1702 | B784: 3 | C784: 5425.02 | D784: tier - 2 | E784: R1012 | F784: tier - 2 | G784: tier - 1 | H784: 1991 | I784: {=IF(D784="", INDEX($D$2:$D$2345, MODE(MATCH(IF($D$2:$D$2345<>"",$D$2:$D$2345), IF($D$2:$D$2345<>"",$D$2:$D$2345),0))), D784)} -> tier - 2 | J784: {=IF(G784="", INDEX($G$2:$G$2345, MODE(MATCH(IF($G$2:$G$2345<>"",$G$2:$G$2345), IF($G$2:$G$2345<>"",$G$2:$G$2345),0))), G784)} -> tier - 1 | K784: {=IF(E784="", INDEX($E$2:$E$2345, MODE(MATCH(IF($E$2:$E$2345<>"",$E$2:$E$2345), IF($E$2:$E$2345<>"",$E$2:$E$2345),0))), E784)} -> R1012 | L784: =INT(YEARFRAC(M784,DATE(2023,6,8))) -> 30 | M784: 33791
A785: Id1703 | B785: 0 | C785: 5415.66 | D785: tier - 2 | E785: R1013 | F785: tier - 2 | G785: tier - 3 | H785: 1982 | I785: {=IF(D785="", INDEX($D$2:$D$2345, MODE(MATCH(IF($D$2:$D$2345<>"",$D$2:$D$2345), IF($D$2:$D$2345<>"",$D$2:$D$2345),0))), D785)} -> tier - 2 | J785: {=IF(G785="", INDEX($G$2:$G$2345, MODE(MATCH(IF($G$2:$G$2345<>"",$G$2:$G$2345), IF($G$2:$G$2345<>"",$G$2:$G$2345),0))), G785)} -> tier - 3 | K785: {=IF(E785="", INDEX($E$2:$E$2345, MODE(MATCH(IF($E$2:$E$2345<>"",$E$2:$E$2345), IF($E$2:$E$2345<>"",$E$2:$E$2345),0))), E785)} -> R1013 | L785: =INT(YEARFRAC(M785,DATE(2023,6,8))) -> 31 | M785: 33508
A786: Id1704 | B786: 1 | C786: 5411.99 | D786: tier - 2 | E786: R1012 | F786: tier - 2 | G786: tier - 3 | H786: 1975 | I786: {=IF(D786="", INDEX($D$2:$D$2345, MODE(MATCH(IF($D$2:$D$2345<>"",$D$2:$D$2345), IF($D$2:$D$2345<>"",$D$2:$D$2345),0))), D786)} -> tier - 2 | J786: {=IF(G786="", INDEX($G$2:$G$2345, MODE(MATCH(IF($G$2:$G$2345<>"",$G$2:$G$2345), IF($G$2:$G$2345<>"",$G$2:$G$2345),0))), G786)} -> tier - 3 | K786: {=IF(E786="", INDEX($E$2:$E$2345, MODE(MATCH(IF($E$2:$E$2345<>"",$E$2:$E$2345), IF($E$2:$E$2345<>"",$E$2:$E$2345),0))), E786)} -> R1012 | L786: =INT(YEARFRAC(M786,DATE(2023,6,8))) -> 40 | M786: 30221
A787: Id1705 | B787: 3 | C787: 5402.89 | D787: tier - 2 | E787: R1013 | F787: tier - 2 | G787: tier - 1 | H787: 1985 | I787: {=IF(D787="", INDEX($D$2:$D$2345, MODE(MATCH(IF($D$2:$D$2345<>"",$D$2:$D$2345), IF($D$2:$D$2345<>"",$D$2:$D$2345),0))), D787)} -> tier - 2 | J787: {=IF(G787="", INDEX($G$2:$G$2345, MODE(MATCH(IF($G$2:$G$2345<>"",$G$2:$G$2345), IF($G$2:$G$2345<>"",$G$2:$G$2345),0))), G787)} -> tier - 1 | K787: {=IF(E787="", INDEX($E$2:$E$2345, MODE(MATCH(IF($E$2:$E$2345<>"",$E$2:$E$2345), IF($E$2:$E$2345<>"",$E$2:$E$2345),0))), E787)} -> R1013 | L787: =INT(YEARFRAC(M787,DATE(2023,6,8))) -> 47 | M787: 27751
A788: Id1706 | B788: 0 | C788: 5400.98 | D788: tier - 2 | E788: R1013 | F788: tier - 2 | G788: tier - 2 | H788: 1984 | I788: {=IF(D788="", INDEX($D$2:$D$2345, MODE(MATCH(IF($D$2:$D$2345<>"",$D$2:$D$2345), IF($D$2:$D$2345<>"",$D$2:$D$2345),0))), D788)} -> tier - 2 | J788: {=IF(G788="", INDEX($G$2:$G$2345, MODE(MATCH(IF($G$2:$G$2345<>"",$G$2:$G$2345), IF($G$2:$G$2345<>"",$G$2:$G$2345),0))), G788)} -> tier - 2 | K788: {=IF(E788="", INDEX($E$2:$E$2345, MODE(MATCH(IF($E$2:$E$2345<>"",$E$2:$E$2345), IF($E$2:$E$2345<>"",$E$2:$E$2345),0))), E788)} -> R1013 | L788: =INT(YEARFRAC(M788,DATE(2023,6,8))) -> 37 | M788: 31260
A789: Id1707 | B789: 0 | C789: 5397.62 | D789: tier - 2 | E789: R1013 | F789: tier - 2 | G789: tier - 2 | H789: 1984 | I789: {=IF(D789="", INDEX($D$2:$D$2345, MODE(MATCH(IF($D$2:$D$2345<>"",$D$2:$D$2345), IF($D$2:$D$2345<>"",$D$2:$D$2345),0))), D789)} -> tier - 2 | J789: {=IF(G789="", INDEX($G$2:$G$2345, MODE(MATCH(IF($G$2:$G$2345<>"",$G$2:$G$2345), IF($G$2:$G$2345<>"",$G$2:$G$2345),0))), G789)} -> tier - 2 | K789: {=IF(E789="", INDEX($E$2:$E$2345, MODE(MATCH(IF($E$2:$E$2345<>"",$E$2:$E$2345), IF($E$2:$E$2345<>"",$E$2:$E$2345),0))), E789)} -> R1013 | L789: =INT(YEARFRAC(M789,DATE(2023,6,8))) -> 38 | M789: 30928
A790: Id1708 | B790: 3 | C790: 5396.44 | D790: tier - 2 | E790: R1013 | F790: tier - 2 | G790: tier - 3 | H790: 1989 | I790: {=IF(D790="", INDEX($D$2:$D$2345, MODE(MATCH(IF($D$2:$D$2345<>"",$D$2:$D$2345), IF($D$2:$D$2345<>"",$D$2:$D$2345),0))), D790)} -> tier - 2 | J790: {=IF(G790="", INDEX($G$2:$G$2345, MODE(MATCH(IF($G$2:$G$2345<>"",$G$2:$G$2345), IF($G$2:$G$2345<>"",$G$2:$G$2345),0))), G790)} -> tier - 3 | K790: {=IF(E790="", INDEX($E$2:$E$2345, MODE(MATCH(IF($E$2:$E$2345<>"",$E$2:$E$2345), IF($E$2:$E$2345<>"",$E$2:$E$2345),0))), E790)} -> R1013 | L790: =INT(YEARFRAC(M790,DATE(2023,6,8))) -> 38 | M790: 30992
A791: Id1709 | B791: 1 | C791: 5385.34 | D791: tier - 2 | E791: R1012 | F791: tier - 2 | G791: tier - 3 | H791: 1988 | I791: {=IF(D791="", INDEX($D$2:$D$2345, MODE(MATCH(IF($D$2:$D$2345<>"",$D$2:$D$2345), IF($D$2:$D$2345<>"",$D$2:$D$2345),0))), D791)} -> tier - 2 | J791: {=IF(G791="", INDEX($G$2:$G$2345, MODE(MATCH(IF($G$2:$G$2345<>"",$G$2:$G$2345), IF($G$2:$G$2345<>"",$G$2:$G$2345),0))), G791)} -> tier - 3 | K791: {=IF(E791="", INDEX($E$2:$E$2345, MODE(MATCH(IF($E$2:$E$2345<>"",$E$2:$E$2345), IF($E$2:$E$2345<>"",$E$2:$E$2345),0))), E791)} -> R1012 | L791: =INT(YEARFRAC(M791,DATE(2023,6,8))) -> 33 | M791: 32728
A792: Id171 | B792: 0 | C792: 37133.9 | D792: tier - 2 | E792: R1013 | F792: tier - 2 | G792: tier - 2 | H792: 1995 | I792: {=IF(D792="", INDEX($D$2:$D$2345, MODE(MATCH(IF($D$2:$D$2345<>"",$D$2:$D$2345), IF($D$2:$D$2345<>"",$D$2:$D$2345),0))), D792)} -> tier - 2 | J792: {=IF(G792="", INDEX($G$2:$G$2345, MODE(MATCH(IF($G$2:$G$2345<>"",$G$2:$G$2345), IF($G$2:$G$2345<>"",$G$2:$G$2345),0))), G792)} -> tier - 2 | K792: {=IF(E792="", INDEX($E$2:$E$2345, MODE(MATCH(IF($E$2:$E$2345<>"",$E$2:$E$2345), IF($E$2:$E$2345<>"",$E$2:$E$2345),0))), E792)} -> R1013 | L792: =INT(YEARFRAC(M792,DATE(2023,6,8))) -> 22 | M792: 36829
A793: Id1710 | B793: 0 | C793: 5383.54 | D793: tier - 2 | E793: R1011 | F793: tier - 2 | G793: tier - 3 | H793: 1984 | I793: {=IF(D793="", INDEX($D$2:$D$2345, MODE(MATCH(IF($D$2:$D$2345<>"",$D$2:$D$2345), IF($D$2:$D$2345<>"",$D$2:$D$2345),0))), D793)} -> tier - 2 | J793: {=IF(G793="", INDEX($G$2:$G$2345, MODE(MATCH(IF($G$2:$G$2345<>"",$G$2:$G$2345), IF($G$2:$G$2345<>"",$G$2:$G$2345),0))), G793)} -> tier - 3 | K793: {=IF(E793="", INDEX($E$2:$E$2345, MODE(MATCH(IF($E$2:$E$2345<>"",$E$2:$E$2345), IF($E$2:$E$2345<>"",$E$2:$E$2345),0))), E793)} -> R1011 | L793: =INT(YEARFRAC(M793,DATE(2023,6,8))) -> 35 | M793: 32295
... A883: Id1792 | B883: 5 | C883: 4830.63 | D883: tier - 2 | E883: R1011 | F883: tier - 2 | G883: tier - 1 | H883: 2002 | I883: {=IF(D883="", INDEX($D$2:$D$2345, MODE(MATCH(IF($D$2:$D$2345<>"",$D$2:$D$2345), IF($D$2:$D$2345<>"",$D$2:$D$2345),0))), D883)} -> tier - 2 | J883: {=IF(G883="", INDEX($G$2:$G$2345, MODE(MATCH(IF($G$2:$G$2345<>"",$G$2:$G$2345), IF($G$2:$G$2345<>"",$G$2:$G$2345),0))), G883)} -> tier - 1 | K883: {=IF(E883="", INDEX($E$2:$E$2345, MODE(MATCH(IF($E$2:$E$2345<>"",$E$2:$E$2345), IF($E$2:$E$2345<>"",$E$2:$E$2345),0))), E883)} -> R1011 | L883: =INT(YEARFRAC(M883,DATE(2023,6,8))) -> 22 | M883: 36704
A884: Id1793 | B884: 3 | C884: 4827.9 | D884: tier - 1 | F884: tier - 1 | G884: tier - 2 | H884: 1995 | I884: {=IF(D884="", INDEX($D$2:$D$2345, MODE(MATCH(IF($D$2:$D$2345<>"",$D$2:$D$2345), IF($D$2:$D$2345<>"",$D$2:$D$2345),0))), D884)} -> tier - 1 | J884: {=IF(G884="", INDEX($G$2:$G$2345, MODE(MATCH(IF($G$2:$G$2345<>"",$G$2:$G$2345), IF($G$2:$G$2345<>"",$G$2:$G$2345),0))), G884)} -> tier - 2 | K884: {=IF(E884="", INDEX($E$2:$E$2345, MODE(MATCH(IF($E$2:$E$2345<>"",$E$2:$E$2345), IF($E$2:$E$2345<>"",$E$2:$E$2345),0))), E884)} -> R1013 | L884: =INT(YEARFRAC(M884,DATE(2023,6,8))) -> 20 | M884: 37591
A885: Id1794 | B885: 1 | C885: 4827.1 | D885: tier - 2 | E885: R1013 | F885: tier - 2 | G885: tier - 1 | H885: 1981 | I885: {=IF(D885="", INDEX($D$2:$D$2345, MODE(MATCH(IF($D$2:$D$2345<>"",$D$2:$D$2345), IF($D$2:$D$2345<>"",$D$2:$D$2345),0))), D885)} -> tier - 2 | J885: {=IF(G885="", INDEX($G$2:$G$2345, MODE(MATCH(IF($G$2:$G$2345<>"",$G$2:$G$2345), IF($G$2:$G$2345<>"",$G$2:$G$2345),0))), G885)} -> tier - 1 | K885: {=IF(E885="", INDEX($E$2:$E$2345, MODE(MATCH(IF($E$2:$E$2345<>"",$E$2:$E$2345), IF($E$2:$E$2345<>"",$E$2:$E$2345),0))), E885)} -> R1013 | L885: =INT(YEARFRAC(M885,DATE(2023,6,8))) -> 27 | M885: 34883
A886: Id1795 | B886: 2 | C886: 4812.34 | D886: tier - 2 | E886: R1013 | F886: tier - 2 | G886: tier - 3 | H886: 1978 | I886: {=IF(D886="", INDEX($D$2:$D$2345, MODE(MATCH(IF($D$2:$D$2345<>"",$D$2:$D$2345), IF($D$2:$D$2345<>"",$D$2:$D$2345),0))), D886)} -> tier - 2 | J886: {=IF(G886="", INDEX($G$2:$G$2345, MODE(MATCH(IF($G$2:$G$2345<>"",$G$2:$G$2345), IF($G$2:$G$2345<>"",$G$2:$G$2345),0))), G886)} -> tier - 3 | K886: {=IF(E886="", INDEX($E$2:$E$2345, MODE(MATCH(IF($E$2:$E$2345<>"",$E$2:$E$2345), IF($E$2:$E$2345<>"",$E$2:$E$2345),0))), E886)} -> R1013 | L886: =INT(YEARFRAC(M886,DATE(2023,6,8))) -> 41 | M886: 29862
A887: Id1796 | B887: 1 | C887: 4795.66 | D887: tier - 2 | E887: R1013 | F887: tier - 2 | G887: tier - 1 | H887: 1989 | I887: {=IF(D887="", INDEX($D$2:$D$2345, MODE(MATCH(IF($D$2:$D$2345<>"",$D$2:$D$2345), IF($D$2:$D$2345<>"",$D$2:$D$2345),0))), D887)} -> tier - 2 | J887: {=IF(G887="", INDEX($G$2:$G$2345, MODE(MATCH(IF($G$2:$G$2345<>"",$G$2:$G$2345), IF($G$2:$G$2345<>"",$G$2:$G$2345),0))), G887)} -> tier - 1 | K887: {=IF(E887="", INDEX($E$2:$E$2345, MODE(MATCH(IF($E$2:$E$2345<>"",$E$2:$E$2345), IF($E$2:$E$2345<>"",$E$2:$E$2345),0))), E887)} -> R1013 | L887: =INT(YEARFRAC(M887,DATE(2023,6,8))) -> 44 | M887: 28840
A888: Id1797 | B888: 3 | C888: 4787.42 | D888: tier - 2 | E888: R1013 | F888: tier - 2 | G888: tier - 3 | H888: 1987 | I888: {=IF(D888="", INDEX($D$2:$D$2345, MODE(MATCH(IF($D$2:$D$2345<>"",$D$2:$D$2345), IF($D$2:$D$2345<>"",$D$2:$D$2345),0))), D888)} -> tier - 2 | J888: {=IF(G888="", INDEX($G$2:$G$2345, MODE(MATCH(IF($G$2:$G$2345<>"",$G$2:$G$2345), IF($G$2:$G$2345<>"",$G$2:$G$2345),0))), G888)} -> tier - 3 | K888: {=IF(E888="", INDEX($E$2:$E$2345, MODE(MATCH(IF($E$2:$E$2345<>"",$E$2:$E$2345), IF($E$2:$E$2345<>"",$E$2:$E$2345),0))), E888)} -> R1013 | L888: =INT(YEARFRAC(M888,DATE(2023,6,8))) -> 33 | M888: 32681
A889: Id1798 | B889: 1 | C889: 4779.6 | D889: tier - 2 | E889: R1013 | F889: tier - 2 | G889: tier - 3 | H889: 1989 | I889: {=IF(D889="", INDEX($D$2:$D$2345, MODE(MATCH(IF($D$2:$D$2345<>"",$D$2:$D$2345), IF($D$2:$D$2345<>"",$D$2:$D$2345),0))), D889)} -> tier - 2 | J889: {=IF(G889="", INDEX($G$2:$G$2345, MODE(MATCH(IF($G$2:$G$2345<>"",$G$2:$G$2345), IF($G$2:$G$2345<>"",$G$2:$G$2345),0))), G889)} -> tier - 3 | K889: {=IF(E889="", INDEX($E$2:$E$2345, MODE(MATCH(IF($E$2:$E$2345<>"",$E$2:$E$2345), IF($E$2:$E$2345<>"",$E$2:$E$2345),0))), E889)} -> R1013 | L889: =INT(YEARFRAC(M889,DATE(2023,6,8))) -> 35 | M889: 32120
A890: Id1799 | B890: 1 | C890: 4766.02 | D890: tier - 2 | E890: R1011 | F890: tier - 2 | G890: tier - 3 | H890: 1989 | I890: {=IF(D890="", INDEX($D$2:$D$2345, MODE(MATCH(IF($D$2:$D$2345<>"",$D$2:$D$2345), IF($D$2:$D$2345<>"",$D$2:$D$2345),0))), D890)} -> tier - 2 | J890: {=IF(G890="", INDEX($G$2:$G$2345, MODE(MATCH(IF($G$2:$G$2345<>"",$G$2:$G$2345), IF($G$2:$G$2345<>"",$G$2:$G$2345),0))), G890)} -> tier - 3 | K890: {=IF(E890="", INDEX($E$2:$E$2345, MODE(MATCH(IF($E$2:$E$2345<>"",$E$2:$E$2345), IF($E$2:$E$2345<>"",$E$2:$E$2345),0))), E890)} -> R1011 | L890: =INT(YEARFRAC(M890,DATE(2023,6,8))) -> 33 | M890: 32721
A891: Id18 | B891: 1 | C891: 47896.79 | D891: tier - 1 | E891: R1024 | F891: tier - 1 | G891: tier - 3 | H891: 1963 | I891: {=IF(D891="", INDEX($D$2:$D$2345, MODE(MATCH(IF($D$2:$D$2345<>"",$D$2:$D$2345), IF($D$2:$D$2345<>"",$D$2:$D$2345),0))), D891)} -> tier - 1 | J891: {=IF(G891="", INDEX($G$2:$G$2345, MODE(MATCH(IF($G$2:$G$2345<>"",$G$2:$G$2345), IF($G$2:$G$2345<>"",$G$2:$G$2345),0))), G891)} -> tier - 3 | K891: {=IF(E891="", INDEX($E$2:$E$2345, MODE(MATCH(IF($E$2:$E$2345<>"",$E$2:$E$2345), IF($E$2:$E$2345<>"",$E$2:$E$2345),0))), E891)} -> R1024 | L891: =INT(YEARFRAC(M891,DATE(2023,6,8))) -> 64 | M891: 21402
A892: Id180 | B892: 2 | C892: 36910.61 | D892: tier - 2 | E892: R1011 | F892: tier - 2 | G892: tier - 2 | H892: 1963 | I892: {=IF(D892="", INDEX($D$2:$D$2345, MODE(MATCH(IF($D$2:$D$2345<>"",$D$2:$D$2345), IF($D$2:$D$2345<>"",$D$2:$D$2345),0))), D892)} -> tier - 2 | J892: {=IF(G892="", INDEX($G$2:$G$2345, MODE(MATCH(IF($G$2:$G$2345<>"",$G$2:$G$2345), IF($G$2:$G$2345<>"",$G$2:$G$2345),0))), G892)} -> tier - 2 | K892: {=IF(E892="", INDEX($E$2:$E$2345, MODE(MATCH(IF($E$2:$E$2345<>"",$E$2:$E$2345), IF($E$2:$E$2345<>"",$E$2:$E$2345),0))), E892)} -> R1011 | L892: =INT(YEARFRAC(M892,DATE(2023,6,8))) -> 31 | M892: 33443
A893: Id1800 | B893: 1 | C893: 4762.33 | D893: tier - 3 | E893: R1011 | F893: tier - 3 | G893: tier - 3 | H893: 1987 | I893: {=IF(D893="", INDEX($D$2:$D$2345, MODE(MATCH(IF($D$2:$D$2345<>"",$D$2:$D$2345), IF($D$2:$D$2345<>"",$D$2:$D$2345),0))), D893)} -> tier - 3 | J893: {=IF(G893="", INDEX($G$2:$G$2345, MODE(MATCH(IF($G$2:$G$2345<>"",$G$2:$G$2345), IF($G$2:$G$2345<>"",$G$2:$G$2345),0))), G893)} -> tier - 3 | K893: {=IF(E893="", INDEX($E$2:$E$2345, MODE(MATCH(IF($E$2:$E$2345<>"",$E$2:$E$2345), IF($E$2:$E$2345<>"",$E$2:$E$2345),0))), E893)} -> R1011 | L893: =INT(YEARFRAC(M893,DATE(2023,6,8))) -> 33 | M893: 32778
A894: Id1801 | B894: 2 | C894: 4753.64 | D894: tier - 2 | E894: R1013 | F894: tier - 2 | G894: tier - 3 | H894: 1992 | I894: {=IF(D894="", INDEX($D$2:$D$2345, MODE(MATCH(IF($D$2:$D$2345<>"",$D$2:$D$2345), IF($D$2:$D$2345<>"",$D$2:$D$2345),0))), D894)} -> tier - 2 | J894: {=IF(G894="", INDEX($G$2:$G$2345, MODE(MATCH(IF($G$2:$G$2345<>"",$G$2:$G$2345), IF($G$2:$G$2345<>"",$G$2:$G$2345),0))), G894)} -> tier - 3 | K894: {=IF(E894="", INDEX($E$2:$E$2345, MODE(MATCH(IF($E$2:$E$2345<>"",$E$2:$E$2345), IF($E$2:$E$2345<>"",$E$2:$E$2345),0))), E894)} -> R1013 | L894: =INT(YEARFRAC(M894,DATE(2023,6,8))) -> 35 | M894: 32005
A895: Id1802 | B895: 1 | C895: 4751.07 | D895: tier - 3 | E895: R1011 | F895: tier - 3 | G895: tier - 1 | H895: 1987 | I895: {=IF(D895="", INDEX($D$2:$D$2345, MODE(MATCH(IF($D$2:$D$2345<>"",$D$2:$D$2345), IF($D$2:$D$2345<>"",$D$2:$D$2345),0))), D895)} -> tier - 3 | J895: {=IF(G895="", INDEX($G$2:$G$2345, MODE(MATCH(IF($G$2:$G$2345<>"",$G$2:$G$2345), IF($G$2:$G$2345<>"",$G$2:$G$2345),0))), G895)} -> tier - 1 | K895: {=IF(E895="", INDEX($E$2:$E$2345, MODE(MATCH(IF($E$2:$E$2345<>"",$E$2:$E$2345), IF($E$2:$E$2345<>"",$E$2:$E$2345),0))), E895)} -> R1011 | L895: =INT(YEARFRAC(M895,DATE(2023,6,8))) -> 30 | M895: 33930
A896: Id1803 | B896: 1 | C896: 4747.05 | D896: tier - 2 | E896: R1013 | F896: tier - 2 | G896: tier - 2 | H896: 1987 | I896: {=IF(D896="", INDEX($D$2:$D$2345, MODE(MATCH(IF($D$2:$D$2345<>"",$D$2:$D$2345), IF($D$2:$D$2345<>"",$D$2:$D$2345),0))), D896)} -> tier - 2 | J896: {=IF(G896="", INDEX($G$2:$G$2345, MODE(MATCH(IF($G$2:$G$2345<>"",$G$2:$G$2345), IF($G$2:$G$2345<>"",$G$2:$G$2345),0))), G896)} -> tier - 2 | K896: {=IF(E896="", INDEX($E$2:$E$2345, MODE(MATCH(IF($E$2:$E$2345<>"",$E$2:$E$2345), IF($E$2:$E$2345<>"",$E$2:$E$2345),0))), E896)} -> R1013 | L896: =INT(YEARFRAC(M896,DATE(2023,6,8))) -> 35 | M896: 32022
... A1467: Id2317 | B1467: 0 | C1467: 773.54 | D1467: tier - 3 | E1467: R1013 | F1467: tier - 3 | G1467: tier - 2 | H1467: 1995 | I1467: {=IF(D1467="", INDEX($D$2:$D$2345, MODE(MATCH(IF($D$2:$D$2345<>"",$D$2:$D$2345), IF($D$2:$D$2345<>"",$D$2:$D$2345),0))), D1467)} -> tier - 3 | J1467: {=IF(G1467="", INDEX($G$2:$G$2345, MODE(MATCH(IF($G$2:$G$2345<>"",$G$2:$G$2345), IF($G$2:$G$2345<>"",$G$2:$G$2345),0))), G1467)} -> tier - 2 | K1467: {=IF(E1467="", INDEX($E$2:$E$2345, MODE(MATCH(IF($E$2:$E$2345<>"",$E$2:$E$2345), IF($E$2:$E$2345<>"",$E$2:$E$2345),0))), E1467)} -> R1013 | L1467: =INT(YEARFRAC(M1467,DATE(2023,6,8))) -> 18 | M1467: 38328
A1468: Id2318 | B1468: 0 | C1468: 770.38 | D1468: tier - 3 | E1468: R1012 | F1468: tier - 3 | H1468: 1996 | I1468: {=IF(D1468="", INDEX($D$2:$D$2345, MODE(MATCH(IF($D$2:$D$2345<>"",$D$2:$D$2345), IF($D$2:$D$2345<>"",$D$2:$D$2345),0))), D1468)} -> tier - 3 | J1468: {=IF(G1468="", INDEX($G$2:$G$2345, MODE(MATCH(IF($G$2:$G$2345<>"",$G$2:$G$2345), IF($G$2:$G$2345<>"",$G$2:$G$2345),0))), G1468)} -> tier - 2 | K1468: {=IF(E1468="", INDEX($E$2:$E$2345, MODE(MATCH(IF($E$2:$E$2345<>"",$E$2:$E$2345), IF($E$2:$E$2345<>"",$E$2:$E$2345),0))), E1468)} -> R1012 | L1468: =INT(YEARFRAC(M1468,DATE(2023,6,8))) -> 27 | M1468: 34960
A1469: Id2319 | B1469: 0 | C1469: 770 | D1469: tier - 3 | E1469: R1013 | F1469: tier - 3 | G1469: tier - 3 | H1469: 1993 | I1469: {=IF(D1469="", INDEX($D$2:$D$2345, MODE(MATCH(IF($D$2:$D$2345<>"",$D$2:$D$2345), IF($D$2:$D$2345<>"",$D$2:$D$2345),0))), D1469)} -> tier - 3 | J1469: {=IF(G1469="", INDEX($G$2:$G$2345, MODE(MATCH(IF($G$2:$G$2345<>"",$G$2:$G$2345), IF($G$2:$G$2345<>"",$G$2:$G$2345),0))), G1469)} -> tier - 3 | K1469: {=IF(E1469="", INDEX($E$2:$E$2345, MODE(MATCH(IF($E$2:$E$2345<>"",$E$2:$E$2345), IF($E$2:$E$2345<>"",$E$2:$E$2345),0))), E1469)} -> R1013 | L1469: =INT(YEARFRAC(M1469,DATE(2023,6,8))) -> 26 | M1469: 35244
A1470: Id232 | B1470: 1 | C1470: 34806.47 | D1470: tier - 1 | E1470: R1013 | F1470: tier - 1 | G1470: tier - 2 | H1470: 1995 | I1470: {=IF(D1470="", INDEX($D$2:$D$2345, MODE(MATCH(IF($D$2:$D$2345<>"",$D$2:$D$2345), IF($D$2:$D$2345<>"",$D$2:$D$2345),0))), D1470)} -> tier - 1 | J1470: {=IF(G1470="", INDEX($G$2:$G$2345, MODE(MATCH(IF($G$2:$G$2345<>"",$G$2:$G$2345), IF($G$2:$G$2345<>"",$G$2:$G$2345),0))), G1470)} -> tier - 2 | K1470: {=IF(E1470="", INDEX($E$2:$E$2345, MODE(MATCH(IF($E$2:$E$2345<>"",$E$2:$E$2345), IF($E$2:$E$2345<>"",$E$2:$E$2345),0))), E1470)} -> R1013 | L1470: =INT(YEARFRAC(M1470,DATE(2023,6,8))) -> 19 | M1470: 37982
A1471: Id2320 | B1471: 0 | C1471: 760 | D1471: tier - 3 | E1471: R1013 | F1471: tier - 3 | G1471: tier - 3 | H1471: 1996 | I1471: {=IF(D1471="", INDEX($D$2:$D$2345, MODE(MATCH(IF($D$2:$D$2345<>"",$D$2:$D$2345), IF($D$2:$D$2345<>"",$D$2:$D$2345),0))), D1471)} -> tier - 3 | J1471: {=IF(G1471="", INDEX($G$2:$G$2345, MODE(MATCH(IF($G$2:$G$2345<>"",$G$2:$G$2345), IF($G$2:$G$2345<>"",$G$2:$G$2345),0))), G1471)} -> tier - 3 | K1471: {=IF(E1471="", INDEX($E$2:$E$2345, MODE(MATCH(IF($E$2:$E$2345<>"",$E$2:$E$2345), IF($E$2:$E$2345<>"",$E$2:$E$2345),0))), E1471)} -> R1013 | L1471: =INT(YEARFRAC(M1471,DATE(2023,6,8))) -> 29 | M1471: 34264
A1472: Id2321 | B1472: 0 | C1472: 760 | D1472: tier - 3 | E1472: R1013 | F1472: tier - 3 | G1472: tier - 1 | H1472: 1993 | I1472: {=IF(D1472="", INDEX($D$2:$D$2345, MODE(MATCH(IF($D$2:$D$2345<>"",$D$2:$D$2345), IF($D$2:$D$2345<>"",$D$2:$D$2345),0))), D1472)} -> tier - 3 | J1472: {=IF(G1472="", INDEX($G$2:$G$2345, MODE(MATCH(IF($G$2:$G$2345<>"",$G$2:$G$2345), IF($G$2:$G$2345<>"",$G$2:$G$2345),0))), G1472)} -> tier - 1 | K1472: {=IF(E1472="", INDEX($E$2:$E$2345, MODE(MATCH(IF($E$2:$E$2345<>"",$E$2:$E$2345), IF($E$2:$E$2345<>"",$E$2:$E$2345),0))), E1472)} -> R1013 | L1472: =INT(YEARFRAC(M1472,DATE(2023,6,8))) -> 26 | M1472: 35286
A1473: Id2322 | B1473: 0 | C1473: 750 | D1473: tier - 3 | E1473: R1012 | F1473: tier - 3 | G1473: tier - 1 | H1473: 2002 | I1473: {=IF(D1473="", INDEX($D$2:$D$2345, MODE(MATCH(IF($D$2:$D$2345<>"",$D$2:$D$2345), IF($D$2:$D$2345<>"",$D$2:$D$2345),0))), D1473)} -> tier - 3 | J1473: {=IF(G1473="", INDEX($G$2:$G$2345, MODE(MATCH(IF($G$2:$G$2345<>"",$G$2:$G$2345), IF($G$2:$G$2345<>"",$G$2:$G$2345),0))), G1473)} -> tier - 1 | K1473: {=IF(E1473="", INDEX($E$2:$E$2345, MODE(MATCH(IF($E$2:$E$2345<>"",$E$2:$E$2345), IF($E$2:$E$2345<>"",$E$2:$E$2345),0))), E1473)} -> R1012 | L1473: =INT(YEARFRAC(M1473,DATE(2023,6,8))) -> 29 | M1473: 34231
A1474: Id2323 | B1474: 0 | C1474: 722.99 | D1474: tier - 3 | E1474: R1013 | F1474: tier - 3 | G1474: tier - 1 | H1474: 1999 | I1474: {=IF(D1474="", INDEX($D$2:$D$2345, MODE(MATCH(IF($D$2:$D$2345<>"",$D$2:$D$2345), IF($D$2:$D$2345<>"",$D$2:$D$2345),0))), D1474)} -> tier - 3 | J1474: {=IF(G1474="", INDEX($G$2:$G$2345, MODE(MATCH(IF($G$2:$G$2345<>"",$G$2:$G$2345), IF($G$2:$G$2345<>"",$G$2:$G$2345),0))), G1474)} -> tier - 1 | K1474: {=IF(E1474="", INDEX($E$2:$E$2345, MODE(MATCH(IF($E$2:$E$2345<>"",$E$2:$E$2345), IF($E$2:$E$2345<>"",$E$2:$E$2345),0))), E1474)} -> R1013 | L1474: =INT(YEARFRAC(M1474,DATE(2023,6,8))) -> 20 | M1474: 37604
A1475: Id2324 | B1475: 0 | C1475: 700 | E1475: R1013 | F1475: tier - 2 | G1475: tier - 3 | H1475: 1999 | I1475: {=IF(D1475="", INDEX($D$2:$D$2345, MODE(MATCH(IF($D$2:$D$2345<>"",$D$2:$D$2345), IF($D$2:$D$2345<>"",$D$2:$D$2345),0))), D1475)} -> tier - 2 | J1475: {=IF(G1475="", INDEX($G$2:$G$2345, MODE(MATCH(IF($G$2:$G$2345<>"",$G$2:$G$2345), IF($G$2:$G$2345<>"",$G$2:$G$2345),0))), G1475)} -> tier - 3 | K1475: {=IF(E1475="", INDEX($E$2:$E$2345, MODE(MATCH(IF($E$2:$E$2345<>"",$E$2:$E$2345), IF($E$2:$E$2345<>"",$E$2:$E$2345),0))), E1475)} -> R1013 | L1475: =INT(YEARFRAC(M1475,DATE(2023,6,8))) -> 23 | M1475: 36520
A1476: Id2325 | B1476: 0 | C1476: 687.54 | D1476: tier - 3 | E1476: R1013 | F1476: tier - 3 | G1476: tier - 2 | H1476: 2001 | I1476: {=IF(D1476="", INDEX($D$2:$D$2345, MODE(MATCH(IF($D$2:$D$2345<>"",$D$2:$D$2345), IF($D$2:$D$2345<>"",$D$2:$D$2345),0))), D1476)} -> tier - 3 | J1476: {=IF(G1476="", INDEX($G$2:$G$2345, MODE(MATCH(IF($G$2:$G$2345<>"",$G$2:$G$2345), IF($G$2:$G$2345<>"",$G$2:$G$2345),0))), G1476)} -> tier - 2 | K1476: {=IF(E1476="", INDEX($E$2:$E$2345, MODE(MATCH(IF($E$2:$E$2345<>"",$E$2:$E$2345), IF($E$2:$E$2345<>"",$E$2:$E$2345),0))), E1476)} -> R1013 | L1476: =INT(YEARFRAC(M1476,DATE(2023,6,8))) -> 23 | M1476: 36415
A1477: Id2326 | B1477: 0 | C1477: 670 | D1477: tier - 3 | E1477: R1013 | F1477: tier - 3 | G1477: tier - 3 | H1477: 1997 | I1477: {=IF(D1477="", INDEX($D$2:$D$2345, MODE(MATCH(IF($D$2:$D$2345<>"",$D$2:$D$2345), IF($D$2:$D$2345<>"",$D$2:$D$2345),0))), D1477)} -> tier - 3 | J1477: {=IF(G1477="", INDEX($G$2:$G$2345, MODE(MATCH(IF($G$2:$G$2345<>"",$G$2:$G$2345), IF($G$2:$G$2345<>"",$G$2:$G$2345),0))), G1477)} -> tier - 3 | K1477: {=IF(E1477="", INDEX($E$2:$E$2345, MODE(MATCH(IF($E$2:$E$2345<>"",$E$2:$E$2345), IF($E$2:$E$2345<>"",$E$2:$E$2345),0))), E1477)} -> R1013 | L1477: =INT(YEARFRAC(M1477,DATE(2023,6,8))) -> 21 | M1477: 37204
A1478: Id2327 | B1478: 0 | C1478: 668 | D1478: tier - 3 | E1478: R1012 | F1478: tier - 3 | G1478: tier - 2 | H1478: 2002 | I1478: {=IF(D1478="", INDEX($D$2:$D$2345, MODE(MATCH(IF($D$2:$D$2345<>"",$D$2:$D$2345), IF($D$2:$D$2345<>"",$D$2:$D$2345),0))), D1478)} -> tier - 3 | J1478: {=IF(G1478="", INDEX($G$2:$G$2345, MODE(MATCH(IF($G$2:$G$2345<>"",$G$2:$G$2345), IF($G$2:$G$2345<>"",$G$2:$G$2345),0))), G1478)} -> tier - 2 | K1478: {=IF(E1478="", INDEX($E$2:$E$2345, MODE(MATCH(IF($E$2:$E$2345<>"",$E$2:$E$2345), IF($E$2:$E$2345<>"",$E$2:$E$2345),0))), E1478)} -> R1012 | L1478: =INT(YEARFRAC(M1478,DATE(2023,6,8))) -> 25 | M1478: 35763
A1479: Id2328 | B1479: 0 | C1479: 650 | D1479: tier - 3 | E1479: R1013 | F1479: tier - 3 | G1479: tier - 3 | H1479: 1995 | I1479: {=IF(D1479="", INDEX($D$2:$D$2345, MODE(MATCH(IF($D$2:$D$2345<>"",$D$2:$D$2345), IF($D$2:$D$2345<>"",$D$2:$D$2345),0))), D1479)} -> tier - 3 | J1479: {=IF(G1479="", INDEX($G$2:$G$2345, MODE(MATCH(IF($G$2:$G$2345<>"",$G$2:$G$2345), IF($G$2:$G$2345<>"",$G$2:$G$2345),0))), G1479)} -> tier - 3 | K1479: {=IF(E1479="", INDEX($E$2:$E$2345, MODE(MATCH(IF($E$2:$E$2345<>"",$E$2:$E$2345), IF($E$2:$E$2345<>"",$E$2:$E$2345),0))), E1479)} -> R1013 | L1479: =INT(YEARFRAC(M1479,DATE(2023,6,8))) -> 20 | M1479: 37441
A1480: Id2329 | B1480: 0 | C1480: 650 | D1480: tier - 3 | E1480: R1013 | F1480: tier - 3 | G1480: tier - 3 | H1480: 1993 | I1480: {=IF(D1480="", INDEX($D$2:$D$2345, MODE(MATCH(IF($D$2:$D$2345<>"",$D$2:$D$2345), IF($D$2:$D$2345<>"",$D$2:$D$2345),0))), D1480)} -> tier - 3 | J1480: {=IF(G1480="", INDEX($G$2:$G$2345, MODE(MATCH(IF($G$2:$G$2345<>"",$G$2:$G$2345), IF($G$2:$G$2345<>"",$G$2:$G$2345),0))), G1480)} -> tier - 3 | K1480: {=IF(E1480="", INDEX($E$2:$E$2345, MODE(MATCH(IF($E$2:$E$2345<>"",$E$2:$E$2345), IF($E$2:$E$2345<>"",$E$2:$E$2345),0))), E1480)} -> R1013 | L1480: =INT(YEARFRAC(M1480,DATE(2023,6,8))) -> 28 | M1480: 34851
A1481: Id233 | B1481: 0 | C1481: 34779.62 | D1481: tier - 1 | E1481: R1011 | F1481: tier - 1 | G1481: tier - 2 | H1481: 2003 | I1481: {=IF(D1481="", INDEX($D$2:$D$2345, MODE(MATCH(IF($D$2:$D$2345<>"",$D$2:$D$2345), IF($D$2:$D$2345<>"",$D$2:$D$2345),0))), D1481)} -> tier - 1 | J1481: {=IF(G1481="", INDEX($G$2:$G$2345, MODE(MATCH(IF($G$2:$G$2345<>"",$G$2:$G$2345), IF($G$2:$G$2345<>"",$G$2:$G$2345),0))), G1481)} -> tier - 2 | K1481: {=IF(E1481="", INDEX($E$2:$E$2345, MODE(MATCH(IF($E$2:$E$2345<>"",$E$2:$E$2345), IF($E$2:$E$2345<>"",$E$2:$E$2345),0))), E1481)} -> R1011 | L1481: =INT(YEARFRAC(M1481,DATE(2023,6,8))) -> 27 | M1481: 34883
A1482: Id2330 | B1482: 0 | C1482: 646.14 | D1482: tier - 3 | E1482: R1012 | F1482: tier - 3 | G1482: tier - 3 | H1482: 2001 | I1482: {=IF(D1482="", INDEX($D$2:$D$2345, MODE(MATCH(IF($D$2:$D$2345<>"",$D$2:$D$2345), IF($D$2:$D$2345<>"",$D$2:$D$2345),0))), D1482)} -> tier - 3 | J1482: {=IF(G1482="", INDEX($G$2:$G$2345, MODE(MATCH(IF($G$2:$G$2345<>"",$G$2:$G$2345), IF($G$2:$G$2345<>"",$G$2:$G$2345),0))), G1482)} -> tier - 3 | K1482: {=IF(E1482="", INDEX($E$2:$E$2345, MODE(MATCH(IF($E$2:$E$2345<>"",$E$2:$E$2345), IF($E$2:$E$2345<>"",$E$2:$E$2345),0))), E1482)} -> R1012 | L1482: =INT(YEARFRAC(M1482,DATE(2023,6,8))) -> 29 | M1482: 34293
A1483: Id2331 | B1483: 0 | C1483: 637.26 | D1483: tier - 3 | E1483: R1013 | F1483: tier - 3 | G1483: tier - 3 | H1483: 1998 | I1483: {=IF(D1483="", INDEX($D$2:$D$2345, MODE(MATCH(IF($D$2:$D$2345<>"",$D$2:$D$2345), IF($D$2:$D$2345<>"",$D$2:$D$2345),0))), D1483)} -> tier - 3 | J1483: {=IF(G1483="", INDEX($G$2:$G$2345, MODE(MATCH(IF($G$2:$G$2345<>"",$G$2:$G$2345), IF($G$2:$G$2345<>"",$G$2:$G$2345),0))), G1483)} -> tier - 3 | K1483: {=IF(E1483="", INDEX($E$2:$E$2345, MODE(MATCH(IF($E$2:$E$2345<>"",$E$2:$E$2345), IF($E$2:$E$2345<>"",$E$2:$E$2345),0))), E1483)} -> R1013 | L1483: =INT(YEARFRAC(M1483,DATE(2023,6,8))) -> 21 | M1483: 37099
A1484: Id2332 | B1484: 0 | C1484: 604.54 | D1484: tier - 3 | E1484: R1013 | F1484: tier - 3 | G1484: tier - 3 | H1484: 1992 | I1484: {=IF(D1484="", INDEX($D$2:$D$2345, MODE(MATCH(IF($D$2:$D$2345<>"",$D$2:$D$2345), IF($D$2:$D$2345<>"",$D$2:$D$2345),0))), D1484)} -> tier - 3 | J1484: {=IF(G1484="", INDEX($G$2:$G$2345, MODE(MATCH(IF($G$2:$G$2345<>"",$G$2:$G$2345), IF($G$2:$G$2345<>"",$G$2:$G$2345),0))), G1484)} -> tier - 3 | K1484: {=IF(E1484="", INDEX($E$2:$E$2345, MODE(MATCH(IF($E$2:$E$2345<>"",$E$2:$E$2345), IF($E$2:$E$2345<>"",$E$2:$E$2345),0))), E1484)} -> R1013 | L1484: =INT(YEARFRAC(M1484,DATE(2023,6,8))) -> 24 | M1484: 36051
A1485: Id2333 | B1485: 0 | C1485: 600 | D1485: tier - 2 | E1485: R1013 | F1485: tier - 2 | G1485: tier - 1 | H1485: 1993 | I1485: {=IF(D1485="", INDEX($D$2:$D$2345, MODE(MATCH(IF($D$2:$D$2345<>"",$D$2:$D$2345), IF($D$2:$D$2345<>"",$D$2:$D$2345),0))), D1485)} -> tier - 2 | J1485: {=IF(G1485="", INDEX($G$2:$G$2345, MODE(MATCH(IF($G$2:$G$2345<>"",$G$2:$G$2345), IF($G$2:$G$2345<>"",$G$2:$G$2345),0))), G1485)} -> tier - 1 | K1485: {=IF(E1485="", INDEX($E$2:$E$2345, MODE(MATCH(IF($E$2:$E$2345<>"",$E$2:$E$2345), IF($E$2:$E$2345<>"",$E$2:$E$2345),0))), E1485)} -> R1013 | L1485: =INT(YEARFRAC(M1485,DATE(2023,6,8))) -> 30 | M1485: 33785
A1486: Id2334 | B1486: 0 | C1486: 570.62 | D1486: tier - 2 | E1486: R1013 | F1486: tier - 2 | G1486: tier - 1 | H1486: 1992 | I1486: {=IF(D1486="", INDEX($D$2:$D$2345, MODE(MATCH(IF($D$2:$D$2345<>"",$D$2:$D$2345), IF($D$2:$D$2345<>"",$D$2:$D$2345),0))), D1486)} -> tier - 2 | J1486: {=IF(G1486="", INDEX($G$2:$G$2345, MODE(MATCH(IF($G$2:$G$2345<>"",$G$2:$G$2345), IF($G$2:$G$2345<>"",$G$2:$G$2345),0))), G1486)} -> tier - 1 | K1486: {=IF(E1486="", INDEX($E$2:$E$2345, MODE(MATCH(IF($E$2:$E$2345<>"",$E$2:$E$2345), IF($E$2:$E$2345<>"",$E$2:$E$2345),0))), E1486)} -> R1013 | L1486: =INT(YEARFRAC(M1486,DATE(2023,6,8))) -> 29 | M1486: 34303
A1487: Id2335 | B1487: 0 | C1487: 563.84 | D1487: tier - 2 | E1487: R1013 | F1487: tier - 2 | G1487: tier - 3 | H1487: 1992 | I1487: {=IF(D1487="", INDEX($D$2:$D$2345, MODE(MATCH(IF($D$2:$D$2345<>"",$D$2:$D$2345), IF($D$2:$D$2345<>"",$D$2:$D$2345),0))), D1487)} -> tier - 2 | J1487: {=IF(G1487="", INDEX($G$2:$G$2345, MODE(MATCH(IF($G$2:$G$2345<>"",$G$2:$G$2345), IF($G$2:$G$2345<>"",$G$2:$G$2345),0))), G1487)} -> tier - 3 | K1487: R1013 | L1487: =INT(YEARFRAC(M1487,DATE(2023,6,8))) -> 30 | M1487: 33794
A1488: Id234 | B1488: 0 | C1488: 34672.15 | D1488: tier - 1 | E1488: R1013 | F1488: tier - 1 | G1488: tier - 3 | H1488: 1994 | I1488: {=IF(D1488="", INDEX($D$2:$D$2345, MODE(MATCH(IF($D$2:$D$2345<>"",$D$2:$D$2345), IF($D$2:$D$2345<>"",$D$2:$D$2345),0))), D1488)} -> tier - 1 | J1488: {=IF(G1488="", INDEX($G$2:$G$2345, MODE(MATCH(IF($G$2:$G$2345<>"",$G$2:$G$2345), IF($G$2:$G$2345<>"",$G$2:$G$2345),0))), G1488)} -> tier - 3 | K1488: {=IF(E1488="", INDEX($E$2:$E$2345, MODE(MATCH(IF($E$2:$E$2345<>"",$E$2:$E$2345), IF($E$2:$E$2345<>"",$E$2:$E$2345),0))), E1488)} -> R1013 | L1488: =INT(YEARFRAC(M1488,DATE(2023,6,8))) -> 19 | M1488: 37809
A1489: Id235 | B1489: 0 | C1489: 34617.84 | D1489: tier - 1 | E1489: R1016 | F1489: tier - 1 | G1489: tier - 3 | H1489: 2004 | I1489: {=IF(D1489="", INDEX($D$2:$D$2345, MODE(MATCH(IF($D$2:$D$2345<>"",$D$2:$D$2345), IF($D$2:$D$2345<>"",$D$2:$D$2345),0))), D1489)} -> tier - 1 | J1489: {=IF(G1489="", INDEX($G$2:$G$2345, MODE(MATCH(IF($G$2:$G$2345<>"",$G$2:$G$2345), IF($G$2:$G$2345<>"",$G$2:$G$2345),0))), G1489)} -> tier - 3 | K1489: {=IF(E1489="", INDEX($E$2:$E$2345, MODE(MATCH(IF($E$2:$E$2345<>"",$E$2:$E$2345), IF($E$2:$E$2345<>"",$E$2:$E$2345),0))), E1489)} -> R1016 | L1489: =INT(YEARFRAC(M1489,DATE(2023,6,8))) -> 28 | M1489: 34616
A1490: Id236 | B1490: 2 | C1490: 34543.39 | D1490: tier - 2 | E1490: R1011 | F1490: tier - 2 | G1490: tier - 3 | H1490: 1976 | I1490: {=IF(D1490="", INDEX($D$2:$D$2345, MODE(MATCH(IF($D$2:$D$2345<>"",$D$2:$D$2345), IF($D$2:$D$2345<>"",$D$2:$D$2345),0))), D1490)} -> tier - 2 | J1490: {=IF(G1490="", INDEX($G$2:$G$2345, MODE(MATCH(IF($G$2:$G$2345<>"",$G$2:$G$2345), IF($G$2:$G$2345<>"",$G$2:$G$2345),0))), G1490)} -> tier - 3 | K1490: {=IF(E1490="", INDEX($E$2:$E$2345, MODE(MATCH(IF($E$2:$E$2345<>"",$E$2:$E$2345), IF($E$2:$E$2345<>"",$E$2:$E$2345),0))), E1490)} -> R1011 | L1490: =INT(YEARFRAC(M1490,DATE(2023,6,8))) -> 18 | M1490: 38316
A1491: Id237 | B1491: 0 | C1491: 34472.84 | D1491: tier - 1 | E1491: R1011 | F1491: tier - 1 | G1491: tier - 3 | H1491: 1998 | I1491: {=IF(D1491="", INDEX($D$2:$D$2345, MODE(MATCH(IF($D$2:$D$2345<>"",$D$2:$D$2345), IF($D$2:$D$2345<>"",$D$2:$D$2345),0))), D1491)} -> tier - 1 | J1491: {=IF(G1491="", INDEX($G$2:$G$2345, MODE(MATCH(IF($G$2:$G$2345<>"",$G$2:$G$2345), IF($G$2:$G$2345<>"",$G$2:$G$2345),0))), G1491)} -> tier - 3 | K1491: {=IF(E1491="", INDEX($E$2:$E$2345, MODE(MATCH(IF($E$2:$E$2345<>"",$E$2:$E$2345), IF($E$2:$E$2345<>"",$E$2:$E$2345),0))), E1491)} -> R1011 | L1491: =INT(YEARFRAC(M1491,DATE(2023,6,8))) -> 46 | M1491: 27935
A1492: Id238 | B1492: 3 | C1492: 34456.27 | D1492: tier - 1 | E1492: R1011 | F1492: tier - 1 | G1492: tier - 2 | H1492: 1990 | I1492: {=IF(D1492="", INDEX($D$2:$D$2345, MODE(MATCH(IF($D$2:$D$2345<>"",$D$2:$D$2345), IF($D$2:$D$2345<>"",$D$2:$D$2345),0))), D1492)} -> tier - 1 | J1492: {=IF(G1492="", INDEX($G$2:$G$2345, MODE(MATCH(IF($G$2:$G$2345<>"",$G$2:$G$2345), IF($G$2:$G$2345<>"",$G$2:$G$2345),0))), G1492)} -> tier - 2 | K1492: {=IF(E1492="", INDEX($E$2:$E$2345, MODE(MATCH(IF($E$2:$E$2345<>"",$E$2:$E$2345), IF($E$2:$E$2345<>"",$E$2:$E$2345),0))), E1492)} -> R1011 | L1492: =INT(YEARFRAC(M1492,DATE(2023,6,8))) -> 24 | M1492: 36062
A1493: Id239 | B1493: 0 | C1493: 34439.86 | D1493: tier - 2 | E1493: R1013 | F1493: tier - 2 | G1493: tier - 1 | H1493: 2003 | I1493: {=IF(D1493="", INDEX($D$2:$D$2345, MODE(MATCH(IF($D$2:$D$2345<>"",$D$2:$D$2345), IF($D$2:$D$2345<>"",$D$2:$D$2345),0))), D1493)} -> tier - 2 | J1493: {=IF(G1493="", INDEX($G$2:$G$2345, MODE(MATCH(IF($G$2:$G$2345<>"",$G$2:$G$2345), IF($G$2:$G$2345<>"",$G$2:$G$2345),0))), G1493)} -> tier - 1 | K1493: {=IF(E1493="", INDEX($E$2:$E$2345, MODE(MATCH(IF($E$2:$E$2345<>"",$E$2:$E$2345), IF($E$2:$E$2345<>"",$E$2:$E$2345),0))), E1493)} -> R1013 | L1493: =INT(YEARFRAC(M1493,DATE(2023,6,8))) -> 32 | M1493: 33151
A1494: Id24 | B1494: 2 | C1494: 47269.85 | D1494: tier - 1 | E1494: R1013 | F1494: tier - 1 | G1494: tier - 2 | H1494: 1970 | I1494: {=IF(D1494="", INDEX($D$2:$D$2345, MODE(MATCH(IF($D$2:$D$2345<>"",$D$2:$D$2345), IF($D$2:$D$2345<>"",$D$2:$D$2345),0))), D1494)} -> tier - 1 | J1494: {=IF(G1494="", INDEX($G$2:$G$2345, MODE(MATCH(IF($G$2:$G$2345<>"",$G$2:$G$2345), IF($G$2:$G$2345<>"",$G$2:$G$2345),0))), G1494)} -> tier - 2 | K1494: {=IF(E1494="", INDEX($E$2:$E$2345, MODE(MATCH(IF($E$2:$E$2345<>"",$E$2:$E$2345), IF($E$2:$E$2345<>"",$E$2:$E$2345),0))), E1494)} -> R1013 | L1494: =INT(YEARFRAC(M1494,DATE(2023,6,8))) -> 64 | M1494: 21547
A1495: Id240 | B1495: 3 | C1495: 34402.22 | D1495: tier - 2 | E1495: R1011 | F1495: tier - 2 | G1495: tier - 3 | H1495: 1984 | I1495: {=IF(D1495="", INDEX($D$2:$D$2345, MODE(MATCH(IF($D$2:$D$2345<>"",$D$2:$D$2345), IF($D$2:$D$2345<>"",$D$2:$D$2345),0))), D1495)} -> tier - 2 | J1495: {=IF(G1495="", INDEX($G$2:$G$2345, MODE(MATCH(IF($G$2:$G$2345<>"",$G$2:$G$2345), IF($G$2:$G$2345<>"",$G$2:$G$2345),0))), G1495)} -> tier - 3 | K1495: {=IF(E1495="", INDEX($E$2:$E$2345, MODE(MATCH(IF($E$2:$E$2345<>"",$E$2:$E$2345), IF($E$2:$E$2345<>"",$E$2:$E$2345),0))), E1495)} -> R1011 | L1495: =INT(YEARFRAC(M1495,DATE(2023,6,8))) -> 19 | M1495: 37895
A1496: Id241 | B1496: 3 | C1496: 34307.22 | D1496: tier - 2 | E1496: R1012 | F1496: tier - 2 | G1496: tier - 2 | H1496: 1983 | I1496: {=IF(D1496="", INDEX($D$2:$D$2345, MODE(MATCH(IF($D$2:$D$2345<>"",$D$2:$D$2345), IF($D$2:$D$2345<>"",$D$2:$D$2345),0))), D1496)} -> tier - 2 | J1496: {=IF(G1496="", INDEX($G$2:$G$2345, MODE(MATCH(IF($G$2:$G$2345<>"",$G$2:$G$2345), IF($G$2:$G$2345<>"",$G$2:$G$2345),0))), G1496)} -> tier - 2 | K1496: {=IF(E1496="", INDEX($E$2:$E$2345, MODE(MATCH(IF($E$2:$E$2345<>"",$E$2:$E$2345), IF($E$2:$E$2345<>"",$E$2:$E$2345),0))), E1496)} -> R1012 | L1496: =INT(YEARFRAC(M1496,DATE(2023,6,8))) -> 38 | M1496: 30957
A1497: Id242 | B1497: 3 | C1497: 34293.12 | D1497: tier - 1 | E1497: R1011 | F1497: tier - 1 | G1497: tier - 2 | H1497: 1986 | I1497: {=IF(D1497="", INDEX($D$2:$D$2345, MODE(MATCH(IF($D$2:$D$2345<>"",$D$2:$D$2345), IF($D$2:$D$2345<>"",$D$2:$D$2345),0))), D1497)} -> tier - 1 | J1497: {=IF(G1497="", INDEX($G$2:$G$2345, MODE(MATCH(IF($G$2:$G$2345<>"",$G$2:$G$2345), IF($G$2:$G$2345<>"",$G$2:$G$2345),0))), G1497)} -> tier - 2 | K1497: {=IF(E1497="", INDEX($E$2:$E$2345, MODE(MATCH(IF($E$2:$E$2345<>"",$E$2:$E$2345), IF($E$2:$E$2345<>"",$E$2:$E$2345),0))), E1497)} -> R1011 | L1497: =INT(YEARFRAC(M1497,DATE(2023,6,8))) -> 18 | M1497: 38271
A1498: Id243 | B1498: 0 | C1498: 34289.43 | D1498: tier - 1 | E1498: R1011 | F1498: tier - 1 | G1498: tier - 1 | H1498: 1995 | I1498: {=IF(D1498="", INDEX($D$2:$D$2345, MODE(MATCH(IF($D$2:$D$2345<>"",$D$2:$D$2345), IF($D$2:$D$2345<>"",$D$2:$D$2345),0))), D1498)} -> tier - 1 | J1498: {=IF(G1498="", INDEX($G$2:$G$2345, MODE(MATCH(IF($G$2:$G$2345<>"",$G$2:$G$2345), IF($G$2:$G$2345<>"",$G$2:$G$2345),0))), G1498)} -> tier - 1 | K1498: {=IF(E1498="", INDEX($E$2:$E$2345, MODE(MATCH(IF($E$2:$E$2345<>"",$E$2:$E$2345), IF($E$2:$E$2345<>"",$E$2:$E$2345),0))), E1498)} -> R1011 | L1498: =INT(YEARFRAC(M1498,DATE(2023,6,8))) -> 36 | M1498: 31715
A1499: Id244 | B1499: 0 | C1499: 34254.05 | D1499: tier - 1 | E1499: R1019 | F1499: tier - 1 | G1499: tier - 3 | H1499: 1998 | I1499: {=IF(D1499="", INDEX($D$2:$D$2345, MODE(MATCH(IF($D$2:$D$2345<>"",$D$2:$D$2345), IF($D$2:$D$2345<>"",$D$2:$D$2345),0))), D1499)} -> tier - 1 | J1499: {=IF(G1499="", INDEX($G$2:$G$2345, MODE(MATCH(IF($G$2:$G$2345<>"",$G$2:$G$2345), IF($G$2:$G$2345<>"",$G$2:$G$2345),0))), G1499)} -> tier - 3 | K1499: {=IF(E1499="", INDEX($E$2:$E$2345, MODE(MATCH(IF($E$2:$E$2345<>"",$E$2:$E$2345), IF($E$2:$E$2345<>"",$E$2:$E$2345),0))), E1499)} -> R1019 | L1499: =INT(YEARFRAC(M1499,DATE(2023,6,8))) -> 27 | M1499: 34861
... A2344: missing | B2344: 2 | C2344: 38711 | D2344: tier - 1 | E2344: R1011 | F2344: tier - 1 | G2344: tier - 3 | H2344: 1991 | I2344: {=IF(D2344="", INDEX($D$2:$D$2345, MODE(MATCH(IF($D$2:$D$2345<>"",$D$2:$D$2345), IF($D$2:$D$2345<>"",$D$2:$D$2345),0))), D2344)} -> tier - 1 | J2344: {=IF(G2344="", INDEX($G$2:$G$2345, MODE(MATCH(IF($G$2:$G$2345<>"",$G$2:$G$2345), IF($G$2:$G$2345<>"",$G$2:$G$2345),0))), G2344)} -> tier - 3 | K2344: {=IF(E2344="", INDEX($E$2:$E$2345, MODE(MATCH(IF($E$2:$E$2345<>"",$E$2:$E$2345), IF($E$2:$E$2345<>"",$E$2:$E$2345),0))), E2344)} -> R1011 | L2344: =INT(YEARFRAC(M2344,DATE(2023,6,8))) -> 31 | M2344: 33564

Sheet MedicHistory
A1: Customer ID | B1: BMI | C1: HBA1C | D1: Heart Issues | E1: Any Transplants | F1: Cancer history | G1: MajorSurgeries | H1: smoker2 | I1: Weight status | J1: Smoker | K1: Diabetic | L1: Diabetics
A2: Id1 | B2: 47.41 | C2: 7.47 | D2: No | E2: No | F2: No | G2: 0 | H2: yes | I2: =IF(Medic_History[[#This Row],[BMI]]>=30,"Obisity",IF(Medic_History[[#This Row],[BMI]]>=25,"over weight",IF(Medic_History[[#This Row],[BMI]]>=18.5,"Normal weight","Under weight"))) -> Obisity | J2: {=IF(H2="", INDEX($H$2:$H$2336, MODE(MATCH(IF($H$2:$H$2336<>"",$H$2:$H$2336), IF($H$2:$H$2336<>"",$H$2:$H$2336),0))), H3)} -> yes | K2: =IF(C2<=5.7,"Normal",IF(C2<=6.2,"prediabetes","Diabetes")) -> Diabetes | L2: =IF(C2<=5.7,"Normal",IF(C2<=6.2,"prediabetes","Diabetes")) -> Diabetes
A3: Id2 | B3: 30.36 | C3: 5.77 | D3: No | E3: No | F3: No | G3: 0 | H3: yes | I3: =IF(Medic_History[[#This Row],[BMI]]>=30,"Obisity",IF(Medic_History[[#This Row],[BMI]]>=25,"over weight",IF(Medic_History[[#This Row],[BMI]]>=18.5,"Normal weight","Under weight"))) -> Obisity | J3: {=IF(H3="", INDEX($H$2:$H$2336, MODE(MATCH(IF($H$2:$H$2336<>"",$H$2:$H$2336), IF($H$2:$H$2336<>"",$H$2:$H$2336),0))), H4)} -> yes | K3: =IF(B3<5.7,"Normal",IF(B3<6.2,"prediabetes","Diabetes")) -> Diabetes | L3: =IF(C3<=5.7,"Normal",IF(C3<=6.2,"prediabetes","Diabetes")) -> prediabetes
A4: Id3 | B4: 34.485 | C4: 11.87 | D4: yes | E4: No | F4: No | G4: 2 | H4: yes | I4: =IF(Medic_History[[#This Row],[BMI]]>=30,"Obisity",IF(Medic_History[[#This Row],[BMI]]>=25,"over weight",IF(Medic_History[[#This Row],[BMI]]>=18.5,"Normal weight","Under weight"))) -> Obisity | J4: {=IF(H4="", INDEX($H$2:$H$2336, MODE(MATCH(IF($H$2:$H$2336<>"",$H$2:$H$2336), IF($H$2:$H$2336<>"",$H$2:$H$2336),0))), H5)} -> yes | K4: =IF(B4<5.7,"Normal",IF(B4<6.2,"prediabetes","Diabetes")) -> Diabetes | L4: =IF(C4<=5.7,"Normal",IF(C4<=6.2,"prediabetes","Diabetes")) -> Diabetes
A5: Id4 | B5: 38.095 | C5: 6.05 | D5: No | E5: No | F5: No | G5: 0 | H5: yes | I5: =IF(Medic_History[[#This Row],[BMI]]>=30,"Obisity",IF(Medic_History[[#This Row],[BMI]]>=25,"over weight",IF(Medic_History[[#This Row],[BMI]]>=18.5,"Normal weight","Under weight"))) -> Obisity | J5: {=IF(H5="", INDEX($H$2:$H$2336, MODE(MATCH(IF($H$2:$H$2336<>"",$H$2:$H$2336), IF($H$2:$H$2336<>"",$H$2:$H$2336),0))), H6)} -> yes | K5: =IF(B5<5.7,"Normal",IF(B5<6.2,"prediabetes","Diabetes")) -> Diabetes | L5: =IF(C5<=5.7,"Normal",IF(C5<=6.2,"prediabetes","Diabetes")) -> prediabetes
A6: Id5 | B6: 35.53 | C6: 5.45 | D6: No | E6: No | F6: No | G6: 0 | H6: yes | I6: =IF(Medic_History[[#This Row],[BMI]]>=30,"Obisity",IF(Medic_History[[#This Row],[BMI]]>=25,"over weight",IF(Medic_History[[#This Row],[BMI]]>=18.5,"Normal weight","Under weight"))) -> Obisity | J6: {=IF(H6="", INDEX($H$2:$H$2336, MODE(MATCH(IF($H$2:$H$2336<>"",$H$2:$H$2336), IF($H$2:$H$2336<>"",$H$2:$H$2336),0))), H7)} -> yes | K6: =IF(B6<5.7,"Normal",IF(B6<6.2,"prediabetes","Diabetes")) -> Diabetes | L6: =IF(C6<=5.7,"Normal",IF(C6<=6.2,"prediabetes","Diabetes")) -> Normal
A7: Id6 | B7: 32.8 | C7: 6.59 | D7: No | E7: No | F7: No | G7: 0 | H7: yes | I7: =IF(Medic_History[[#This Row],[BMI]]>=30,"Obisity",IF(Medic_History[[#This Row],[BMI]]>=25,"over weight",IF(Medic_History[[#This Row],[BMI]]>=18.5,"Normal weight","Under weight"))) -> Obisity | J7: {=IF(H7="", INDEX($H$2:$H$2336, MODE(MATCH(IF($H$2:$H$2336<>"",$H$2:$H$2336), IF($H$2:$H$2336<>"",$H$2:$H$2336),0))), H8)} -> yes | K7: =IF(B7<5.7,"Normal",IF(B7<6.2,"prediabetes","Diabetes")) -> Diabetes | L7: =IF(C7<=5.7,"Normal",IF(C7<=6.2,"prediabetes","Diabetes")) -> Diabetes
A8: Id7 | B8: 36.4 | C8: 6.07 | D8: No | E8: No | F8: No | G8: 0 | H8: yes | I8: =IF(Medic_History[[#This Row],[BMI]]>=30,"Obisity",IF(Medic_History[[#This Row],[BMI]]>=25,"over weight",IF(Medic_History[[#This Row],[BMI]]>=18.5,"Normal weight","Under weight"))) -> Obisity | J8: {=IF(H8="", INDEX($H$2:$H$2336, MODE(MATCH(IF($H$2:$H$2336<>"",$H$2:$H$2336), IF($H$2:$H$2336<>"",$H$2:$H$2336),0))), H9)} -> yes | K8: =IF(B8<5.7,"Normal",IF(B8<6.2,"prediabetes","Diabetes")) -> Diabetes | L8: =IF(C8<=5.7,"Normal",IF(C8<=6.2,"prediabetes","Diabetes")) -> prediabetes
A9: Id8 | B9: 36.96 | C9: 7.93 | D9: No | E9: No | F9: No | G9: 3 | H9: yes | I9: =IF(Medic_History[[#This Row],[BMI]]>=30,"Obisity",IF(Medic_History[[#This Row],[BMI]]>=25,"over weight",IF(Medic_History[[#This Row],[BMI]]>=18.5,"Normal weight","Under weight"))) -> Obisity | J9: {=IF(H9="", INDEX($H$2:$H$2336, MODE(MATCH(IF($H$2:$H$2336<>"",$H$2:$H$2336), IF($H$2:$H$2336<>"",$H$2:$H$2336),0))), H10)} -> yes | K9: =IF(B9<5.7,"Normal",IF(B9<6.2,"prediabetes","Diabetes")) -> Diabetes | L9: =IF(C9<=5.7,"Normal",IF(C9<=6.2,"prediabetes","Diabetes")) -> Diabetes
A10: Id9 | B10: 41.14 | C10: 9.58 | D10: yes | E10: No | F10: Yes | G10: 1 | H10: yes | I10: =IF(Medic_History[[#This Row],[BMI]]>=30,"Obisity",IF(Medic_History[[#This Row],[BMI]]>=25,"over weight",IF(Medic_History[[#This Row],[BMI]]>=18.5,"Normal weight","Under weight"))) -> Obisity | J10: {=IF(H10="", INDEX($H$2:$H$2336, MODE(MATCH(IF($H$2:$H$2336<>"",$H$2:$H$2336), IF($H$2:$H$2336<>"",$H$2:$H$2336),0))), H11)} -> yes | K10: =IF(B10<=5.7,"Normal",IF(B10<=6.2,"prediabetes","Diabetes")) -> Diabetes | L10: =IF(C10<=5.7,"Normal",IF(C10<=6.2,"prediabetes","Diabetes")) -> Diabetes
A11: Id10 | B11: 38.06 | C11: 10.79 | D11: No | E11: No | F11: No | G11: 0 | H11: yes | I11: =IF(Medic_History[[#This Row],[BMI]]>=30,"Obisity",IF(Medic_History[[#This Row],[BMI]]>=25,"over weight",IF(Medic_History[[#This Row],[BMI]]>=18.5,"Normal weight","Under weight"))) -> Obisity | J11: {=IF(H11="", INDEX($H$2:$H$2336, MODE(MATCH(IF($H$2:$H$2336<>"",$H$2:$H$2336), IF($H$2:$H$2336<>"",$H$2:$H$2336),0))), H12)} -> yes | K11: =IF(B11<5.7,"Normal",IF(B11<6.2,"prediabetes","Diabetes")) -> Diabetes | L11: =IF(C11<=5.7,"Normal",IF(C11<=6.2,"prediabetes","Diabetes")) -> Diabetes
A12: Id11 | B12: 37.7 | C12: 5.96 | D12: yes | E12: No | F12: No | G12: 2 | H12: yes | I12: =IF(Medic_History[[#This Row],[BMI]]>=30,"Obisity",IF(Medic_History[[#This Row],[BMI]]>=25,"over weight",IF(Medic_History[[#This Row],[BMI]]>=18.5,"Normal weight","Under weight"))) -> Obisity | J12: {=IF(H12="", INDEX($H$2:$H$2336, MODE(MATCH(IF($H$2:$H$2336<>"",$H$2:$H$2336), IF($H$2:$H$2336<>"",$H$2:$H$2336),0))), H13)} -> yes | K12: =IF(B12<5.7,"Normal",IF(B12<6.2,"prediabetes","Diabetes")) -> Diabetes | L12: =IF(C12<=5.7,"Normal",IF(C12<=6.2,"prediabetes","Diabetes")) -> prediabetes
A13: Id12 | B13: 42.13 | C13: 11.9 | D13: No | E13: No | F13: No | G13: 0 | H13: yes | I13: =IF(Medic_History[[#This Row],[BMI]]>=30,"Obisity",IF(Medic_History[[#This Row],[BMI]]>=25,"over weight",IF(Medic_History[[#This Row],[BMI]]>=18.5,"Normal weight","Under weight"))) -> Obisity | J13: {=IF(H13="", INDEX($H$2:$H$2336, MODE(MATCH(IF($H$2:$H$2336<>"",$H$2:$H$2336), IF($H$2:$H$2336<>"",$H$2:$H$2336),0))), H14)} -> yes | K13: =IF(B13<5.7,"Normal",IF(B13<6.2,"prediabetes","Diabetes")) -> Diabetes | L13: =IF(C13<=5.7,"Normal",IF(C13<=6.2,"prediabetes","Diabetes")) -> Diabetes
A14: Id13 | B14: 40.92 | C14: 8.41 | D14: No | E14: No | F14: No | G14: 0 | H14: yes | I14: =IF(Medic_History[[#This Row],[BMI]]>=30,"Obisity",IF(Medic_History[[#This Row],[BMI]]>=25,"over weight",IF(Medic_History[[#This Row],[BMI]]>=18.5,"Normal weight","Under weight"))) -> Obisity | J14: {=IF(H14="", INDEX($H$2:$H$2336, MODE(MATCH(IF($H$2:$H$2336<>"",$H$2:$H$2336), IF($H$2:$H$2336<>"",$H$2:$H$2336),0))), H15)} -> yes | K14: =IF(B14<5.7,"Normal",IF(B14<6.2,"prediabetes","Diabetes")) -> Diabetes | L14: =IF(C14<=5.7,"Normal",IF(C14<=6.2,"prediabetes","Diabetes")) -> Diabetes
A15: Id14 | B15: 40.565 | C15: 7.02 | D15: No | E15: No | F15: No | G15: 0 | H15: yes | I15: =IF(Medic_History[[#This Row],[BMI]]>=30,"Obisity",IF(Medic_History[[#This Row],[BMI]]>=25,"over weight",IF(Medic_History[[#This Row],[BMI]]>=18.5,"Normal weight","Under weight"))) -> Obisity | J15: {=IF(H15="", INDEX($H$2:$H$2336, MODE(MATCH(IF($H$2:$H$2336<>"",$H$2:$H$2336), IF($H$2:$H$2336<>"",$H$2:$H$2336),0))), H16)} -> yes | K15: =IF(B15<5.7,"Normal",IF(B15<6.2,"prediabetes","Diabetes")) -> Diabetes | L15: =IF(C15<=5.7,"Normal",IF(C15<=6.2,"prediabetes","Diabetes")) -> Diabetes
A16: Id15 | B16: 36.385 | C16: 7.59 | D16: yes | E16: No | F16: No | G16: 2 | H16: yes | I16: =IF(Medic_History[[#This Row],[BMI]]>=30,"Obisity",IF(Medic_History[[#This Row],[BMI]]>=25,"over weight",IF(Medic_History[[#This Row],[BMI]]>=18.5,"Normal weight","Under weight"))) -> Obisity | J16: {=IF(H16="", INDEX($H$2:$H$2336, MODE(MATCH(IF($H$2:$H$2336<>"",$H$2:$H$2336), IF($H$2:$H$2336<>"",$H$2:$H$2336),0))), H17)} -> yes | K16: =IF(B16<5.7,"Normal",IF(B16<6.2,"prediabetes","Diabetes")) -> Diabetes | L16: =IF(C16<=5.7,"Normal",IF(C16<=6.2,"prediabetes","Diabetes")) -> Diabetes
A17: Id16 | B17: 39.9 | C17: 11.32 | D17: No | E17: No | F17: No | G17: 0 | H17: yes | I17: =IF(Medic_History[[#This Row],[BMI]]>=30,"Obisity",IF(Medic_History[[#This Row],[BMI]]>=25,"over weight",IF(Medic_History[[#This Row],[BMI]]>=18.5,"Normal weight","Under weight"))) -> Obisity | J17: {=IF(H17="", INDEX($H$2:$H$2336, MODE(MATCH(IF($H$2:$H$2336<>"",$H$2:$H$2336), IF($H$2:$H$2336<>"",$H$2:$H$2336),0))), H18)} -> yes | K17: =IF(B17<5.7,"Normal",IF(B17<6.2,"prediabetes","Diabetes")) -> Diabetes | L17: =IF(C17<=5.7,"Normal",IF(C17<=6.2,"prediabetes","Diabetes")) -> Diabetes
A18: Id17 | B18: 33.8 | C18: 7.67 | D18: No | E18: No | F18: No | G18: 3 | H18: yes | I18: =IF(Medic_History[[#This Row],[BMI]]>=30,"Obisity",IF(Medic_History[[#This Row],[BMI]]>=25,"over weight",IF(Medic_History[[#This Row],[BMI]]>=18.5,"Normal weight","Under weight"))) -> Obisity | J18: {=IF(H18="", INDEX($H$2:$H$2336, MODE(MATCH(IF($H$2:$H$2336<>"",$H$2:$H$2336), IF($H$2:$H$2336<>"",$H$2:$H$2336),0))), H19)} -> yes | K18: =IF(B18<5.7,"Normal",IF(B18<6.2,"prediabetes","Diabetes")) -> Diabetes | L18: =IF(C18<=5.7,"Normal",IF(C18<=6.2,"prediabetes","Diabetes")) -> Diabetes
A19: Id18 | B19: 36.765 | C19: 7.29 | D19: yes | E19: No | F19: Yes | G19: 1 | H19: yes | I19: =IF(Medic_History[[#This Row],[BMI]]>=30,"Obisity",IF(Medic_History[[#This Row],[BMI]]>=25,"over weight",IF(Medic_History[[#This Row],[BMI]]>=18.5,"Normal weight","Under weight"))) -> Obisity | J19: {=IF(H19="", INDEX($H$2:$H$2336, MODE(MATCH(IF($H$2:$H$2336<>"",$H$2:$H$2336), IF($H$2:$H$2336<>"",$H$2:$H$2336),0))), H20)} -> yes | K19: =IF(B19<5.7,"Normal",IF(B19<6.2,"prediabetes","Diabetes")) -> Diabetes | L19: =IF(C19<=5.7,"Normal",IF(C19<=6.2,"prediabetes","Diabetes")) -> Diabetes
A20: Id19 | B20: 36.955 | C20: 4.72 | D20: yes | E20: No | F20: No | G20: 1 | H20: yes | I20: =IF(Medic_History[[#This Row],[BMI]]>=30,"Obisity",IF(Medic_History[[#This Row],[BMI]]>=25,"over weight",IF(Medic_History[[#This Row],[BMI]]>=18.5,"Normal weight","Under weight"))) -> Obisity | J20: {=IF(H20="", INDEX($H$2:$H$2336, MODE(MATCH(IF($H$2:$H$2336<>"",$H$2:$H$2336), IF($H$2:$H$2336<>"",$H$2:$H$2336),0))), H21)} -> yes | K20: =IF(B20<5.7,"Normal",IF(B20<6.2,"prediabetes","Diabetes")) -> Diabetes | L20: =IF(C20<=5.7,"Normal",IF(C20<=6.2,"prediabetes","Diabetes")) -> Normal
A21: Id20 | B21: 42.9 | C21: 11.41 | D21: No | E21: No | F21: No | G21: 0 | H21: yes | I21: =IF(Medic_History[[#This Row],[BMI]]>=30,"Obisity",IF(Medic_History[[#This Row],[BMI]]>=25,"over weight",IF(Medic_History[[#This Row],[BMI]]>=18.5,"Normal weight","Under weight"))) -> Obisity | J21: {=IF(H21="", INDEX($H$2:$H$2336, MODE(MATCH(IF($H$2:$H$2336<>"",$H$2:$H$2336), IF($H$2:$H$2336<>"",$H$2:$H$2336),0))), H22)} -> yes | K21: =IF(B21<5.7,"Normal",IF(B21<6.2,"prediabetes","Diabetes")) -> Diabetes | L21: =IF(C21<=5.7,"Normal",IF(C21<=6.2,"prediabetes","Diabetes")) -> Diabetes
A22: Id21 | B22: 36.3 | C22: 11.5 | D22: yes | E22: No | F22: No | G22: 2 | H22: yes | I22: =IF(Medic_History[[#This Row],[BMI]]>=30,"Obisity",IF(Medic_History[[#This Row],[BMI]]>=25,"over weight",IF(Medic_History[[#This Row],[BMI]]>=18.5,"Normal weight","Under weight"))) -> Obisity | J22: {=IF(H22="", INDEX($H$2:$H$2336, MODE(MATCH(IF($H$2:$H$2336<>"",$H$2:$H$2336), IF($H$2:$H$2336<>"",$H$2:$H$2336),0))), H23)} -> yes | K22: =IF(B22<5.7,"Normal",IF(B22<6.2,"prediabetes","Diabetes")) -> Diabetes | L22: =IF(C22<=5.7,"Normal",IF(C22<=6.2,"prediabetes","Diabetes")) -> Diabetes
... A2335: Id2334 | B2335: 17.6 | C2335: 4.39 | D2335: No | E2335: No | F2335: No | G2335: 1 | H2335: No | I2335: =IF(Medic_History[[#This Row],[BMI]]>=30,"Obisity",IF(Medic_History[[#This Row],[BMI]]>=25,"over weight",IF(Medic_History[[#This Row],[BMI]]>=18.5,"Normal weight","Under weight"))) -> Under weight | J2335: {=IF(H2335="", INDEX($H$2:$H$2336, MODE(MATCH(IF($H$2:$H$2336<>"",$H$2:$H$2336), IF($H$2:$H$2336<>"",$H$2:$H$2336),0))), H2336)} -> No | K2335: =IF(B2335<5.7,"Normal",IF(B2335<6.2,"prediabetes","Diabetes")) -> Diabetes | L2335: =IF(C2335<=5.7,"Normal",IF(C2335<=6.2,"prediabetes","Diabetes")) -> Normal
A2336: Id2335 | B2336: 17.58 | C2336: 4.51 | D2336: No | E2336: No | F2336: No | G2336: 1 | H2336: No | I2336: =IF(Medic_History[[#This Row],[BMI]]>=30,"Obisity",IF(Medic_History[[#This Row],[BMI]]>=25,"over weight",IF(Medic_History[[#This Row],[BMI]]>=18.5,"Normal weight","Under weight"))) -> Under weight | J2336: {=IF(H2336="", INDEX($H$2:$H$2336, MODE(MATCH(IF($H$2:$H$2336<>"",$H$2:$H$2336), IF($H$2:$H$2336<>"",$H$2:$H$2336),0))), H2337)} -> 0 | L2336: =IF(C2336<=5.7,"Normal",IF(C2336<=6.2,"prediabetes","Diabetes")) -> Normal

Sheet Healthcare (3)
A1: Customer ID | B1: First | C1: BMI | D1: HBA1C | E1: Heart Issues | F1: Any Transplants | G1: Cancer history | H1: MajorSurgeries | I1: smoker2 | J1: Diabetics | K1: Weight status | L1: charges | M1: Hsp Tier | N1: Cty Tier | O1: StateID | P1: Age | Q1: Date of Birth
A2: Id1 | B2: {=_xlfn.XLOOKUP(A2,[1]Customer!A:A,[1]Customer!C:C,"")} -> Kelly | C2: {=_xlfn.XLOOKUP($A2,[1]MedicHistory!A:A,[1]MedicHistory!B:B,"")} -> 47.41 | D2: =_xlfn.XLOOKUP($A2,[1]MedicHistory!A:A,[1]MedicHistory!C:C,"") -> 7.47 | E2: =_xlfn.XLOOKUP($A2,[1]MedicHistory!A:A,[1]MedicHistory!D:D,"") -> No | F2: =_xlfn.XLOOKUP($A2,[1]MedicHistory!A:A,[1]MedicHistory!E:E,"") -> No | G2: =_xlfn.XLOOKUP($A2,[1]MedicHistory!A:A,[1]MedicHistory!F:F,"") -> No | H2: =_xlfn.XLOOKUP($A2,[1]MedicHistory!A:A,[1]MedicHistory!G:G,"") -> 0 | I2: =_xlfn.XLOOKUP($A2,[1]MedicHistory!A:A,[1]MedicHistory!H:H,"") -> yes | J2: Diabetic | K2: =_xlfn.XLOOKUP($A2,[1]MedicHistory!A:A,[1]MedicHistory!I:I,"") -> Obisity | L2: =_xlfn.XLOOKUP($A2,[1]Hospitalisation!A:A,[1]Hospitalisation!C:C,"") -> 63770.43 | M2: =_xlfn.XLOOKUP($A2,[1]Hospitalisation!A:A,[1]Hospitalisation!I:I,"") -> tier - 1 | N2: =_xlfn.XLOOKUP($A2,[1]Hospitalisation!A:A,[1]Hospitalisation!J:J,"") -> tier - 3 | O2: =_xlfn.XLOOKUP($A2,[1]Hospitalisation!A:A,[1]Hospitalisation!K:K,"") -> R1013 | P2: =_xlfn.XLOOKUP($A2,[1]Hospitalisation!A:A,[1]Hospitalisation!L:L,"") -> 39 | Q2: =_xlfn.XLOOKUP($A2,[1]Hospitalisation!A:A,[1]Hospitalisation!M:M,"") -> 30601
A3: Id2 | B3: =_xlfn.XLOOKUP(A3,[1]Customer!A:A,[1]Customer!C:C,"") -> Matthew | C3: {=_xlfn.XLOOKUP($A3,[1]MedicHistory!A:A,[1]MedicHistory!B:B,"")} -> 30.36 | D3: {=_xlfn.XLOOKUP($A3,[1]MedicHistory!A:A,[1]MedicHistory!C:C,"")} -> 5.77 | E3: =_xlfn.XLOOKUP($A3,[1]MedicHistory!A:A,[1]MedicHistory!D:D,"") -> No | F3: =_xlfn.XLOOKUP($A3,[1]MedicHistory!A:A,[1]MedicHistory!E:E,"") -> No | G3: =_xlfn.XLOOKUP($A3,[1]MedicHistory!A:A,[1]MedicHistory!F:F,"") -> No | H3: =_xlfn.XLOOKUP($A3,[1]MedicHistory!A:A,[1]MedicHistory!G:G,"") -> 0 | I3: =_xlfn.XLOOKUP($A3,[1]MedicHistory!A:A,[1]MedicHistory!H:H,"") -> yes | J3: =_xlfn.XLOOKUP($A3,[1]MedicHistory!A:A,[1]MedicHistory!K:K,"") -> Prediabetic | K3: =_xlfn.XLOOKUP($A3,[1]MedicHistory!A:A,[1]MedicHistory!I:I,"") -> Obisity | L3: =_xlfn.XLOOKUP($A3,[1]Hospitalisation!A:A,[1]Hospitalisation!C:C,"") -> 62592.87 | M3: =_xlfn.XLOOKUP($A3,[1]Hospitalisation!A:A,[1]Hospitalisation!I:I,"") -> tier - 2 | N3: =_xlfn.XLOOKUP($A3,[1]Hospitalisation!A:A,[1]Hospitalisation!J:J,"") -> tier - 3 | O3: =_xlfn.XLOOKUP($A3,[1]Hospitalisation!A:A,[1]Hospitalisation!K:K,"") -> R1013 | P3: =_xlfn.XLOOKUP($A3,[1]Hospitalisation!A:A,[1]Hospitalisation!L:L,"") -> 55 | Q3: =_xlfn.XLOOKUP($A3,[1]Hospitalisation!A:A,[1]Hospitalisation!M:M,"") -> 24997
A4: Id3 | B4: =_xlfn.XLOOKUP(A4,[1]Customer!A:A,[1]Customer!C:C,"") -> Phil | C4: {=_xlfn.XLOOKUP($A4,[1]MedicHistory!A:A,[1]MedicHistory!B:B,"")} -> 34.485 | D4: {=_xlfn.XLOOKUP($A4,[1]MedicHistory!A:A,[1]MedicHistory!C:C,"")} -> 11.87 | E4: =_xlfn.XLOOKUP($A4,[1]MedicHistory!A:A,[1]MedicHistory!D:D,"") -> yes | F4: =_xlfn.XLOOKUP($A4,[1]MedicHistory!A:A,[1]MedicHistory!E:E,"") -> No | G4: =_xlfn.XLOOKUP($A4,[1]MedicHistory!A:A,[1]MedicHistory!F:F,"") -> No | H4: =_xlfn.XLOOKUP($A4,[1]MedicHistory!A:A,[1]MedicHistory!G:G,"") -> 2 | I4: =_xlfn.XLOOKUP($A4,[1]MedicHistory!A:A,[1]MedicHistory!H:H,"") -> yes | J4: =_xlfn.XLOOKUP($A4,[1]MedicHistory!A:A,[1]MedicHistory!K:K,"") -> Diabetic | K4: =_xlfn.XLOOKUP($A4,[1]MedicHistory!A:A,[1]MedicHistory!I:I,"") -> Obisity | L4: =_xlfn.XLOOKUP($A4,[1]Hospitalisation!A:A,[1]Hospitalisation!C:C,"") -> 60021.4 | M4: =_xlfn.XLOOKUP($A4,[1]Hospitalisation!A:A,[1]Hospitalisation!I:I,"") -> tier - 1 | N4: =_xlfn.XLOOKUP($A4,[1]Hospitalisation!A:A,[1]Hospitalisation!J:J,"") -> tier - 1 | O4: =_xlfn.XLOOKUP($A4,[1]Hospitalisation!A:A,[1]Hospitalisation!K:K,"") -> R1012 | P4: =_xlfn.XLOOKUP($A4,[1]Hospitalisation!A:A,[1]Hospitalisation!L:L,"") -> 45 | Q4: =_xlfn.XLOOKUP($A4,[1]Hospitalisation!A:A,[1]Hospitalisation!M:M,"") -> 28379
A5: Id4 | B5: =_xlfn.XLOOKUP(A5,[1]Customer!A:A,[1]Customer!C:C,"") -> Kelsey | C5: {=_xlfn.XLOOKUP($A5,[1]MedicHistory!A:A,[1]MedicHistory!B:B,"")} -> 38.095 | D5: {=_xlfn.XLOOKUP($A5,[1]MedicHistory!A:A,[1]MedicHistory!C:C,"")} -> 6.05 | E5: =_xlfn.XLOOKUP($A5,[1]MedicHistory!A:A,[1]MedicHistory!D:D,"") -> No | F5: =_xlfn.XLOOKUP($A5,[1]MedicHistory!A:A,[1]MedicHistory!E:E,"") -> No | G5: =_xlfn.XLOOKUP($A5,[1]MedicHistory!A:A,[1]MedicHistory!F:F,"") -> No | H5: =_xlfn.XLOOKUP($A5,[1]MedicHistory!A:A,[1]MedicHistory!G:G,"") -> 0 | I5: =_xlfn.XLOOKUP($A5,[1]MedicHistory!A:A,[1]MedicHistory!H:H,"") -> yes | J5: =_xlfn.XLOOKUP($A5,[1]MedicHistory!A:A,[1]MedicHistory!K:K,"") -> Prediabetic | K5: =_xlfn.XLOOKUP($A5,[1]MedicHistory!A:A,[1]MedicHistory!I:I,"") -> Obisity | L5: =_xlfn.XLOOKUP($A5,[1]Hospitalisation!A:A,[1]Hospitalisation!C:C,"") -> 58571.07 | M5: =_xlfn.XLOOKUP($A5,[1]Hospitalisation!A:A,[1]Hospitalisation!I:I,"") -> tier - 1 | N5: =_xlfn.XLOOKUP($A5,[1]Hospitalisation!A:A,[1]Hospitalisation!J:J,"") -> tier - 3 | O5: =_xlfn.XLOOKUP($A5,[1]Hospitalisation!A:A,[1]Hospitalisation!K:K,"") -> R1024 | P5: =_xlfn.XLOOKUP($A5,[1]Hospitalisation!A:A,[1]Hospitalisation!L:L,"") -> 53 | Q5: =_xlfn.XLOOKUP($A5,[1]Hospitalisation!A:A,[1]Hospitalisation!M:M,"") -> 25725
A6: Id5 | B6: =_xlfn.XLOOKUP(A6,[1]Customer!A:A,[1]Customer!C:C,"") -> Kristyn | C6: {=_xlfn.XLOOKUP($A6,[1]MedicHistory!A:A,[1]MedicHistory!B:B,"")} -> 35.53 | D6: {=_xlfn.XLOOKUP($A6,[1]MedicHistory!A:A,[1]MedicHistory!C:C,"")} -> 5.45 | E6: =_xlfn.XLOOKUP($A6,[1]MedicHistory!A:A,[1]MedicHistory!D:D,"") -> No | F6: =_xlfn.XLOOKUP($A6,[1]MedicHistory!A:A,[1]MedicHistory!E:E,"") -> No | G6: =_xlfn.XLOOKUP($A6,[1]MedicHistory!A:A,[1]MedicHistory!F:F,"") -> No | H6: =_xlfn.XLOOKUP($A6,[1]MedicHistory!A:A,[1]MedicHistory!G:G,"") -> 0 | I6: =_xlfn.XLOOKUP($A6,[1]MedicHistory!A:A,[1]MedicHistory!H:H,"") -> yes | J6: =_xlfn.XLOOKUP($A6,[1]MedicHistory!A:A,[1]MedicHistory!K:K,"") -> Normal | K6: =_xlfn.XLOOKUP($A6,[1]MedicHistory!A:A,[1]MedicHistory!I:I,"") -> Obisity | L6: =_xlfn.XLOOKUP($A6,[1]Hospitalisation!A:A,[1]Hospitalisation!C:C,"") -> 55135.4 | M6: =_xlfn.XLOOKUP($A6,[1]Hospitalisation!A:A,[1]Hospitalisation!I:I,"") -> tier - 1 | N6: =_xlfn.XLOOKUP($A6,[1]Hospitalisation!A:A,[1]Hospitalisation!J:J,"") -> tier - 2 | O6: =_xlfn.XLOOKUP($A6,[1]Hospitalisation!A:A,[1]Hospitalisation!K:K,"") -> R1012 | P6: =_xlfn.XLOOKUP($A6,[1]Hospitalisation!A:A,[1]Hospitalisation!L:L,"") -> 31 | Q6: =_xlfn.XLOOKUP($A6,[1]Hospitalisation!A:A,[1]Hospitalisation!M:M,"") -> 33408
A7: Id6 | B7: =_xlfn.XLOOKUP(A7,[1]Customer!A:A,[1]Customer!C:C,"") -> Russell | C7: {=_xlfn.XLOOKUP($A7,[1]MedicHistory!A:A,[1]MedicHistory!B:B,"")} -> 32.8 | D7: {=_xlfn.XLOOKUP($A7,[1]MedicHistory!A:A,[1]MedicHistory!C:C,"")} -> 6.59 | E7: =_xlfn.XLOOKUP($A7,[1]MedicHistory!A:A,[1]MedicHistory!D:D,"") -> No | F7: =_xlfn.XLOOKUP($A7,[1]MedicHistory!A:A,[1]MedicHistory!E:E,"") -> No | G7: =_xlfn.XLOOKUP($A7,[1]MedicHistory!A:A,[1]MedicHistory!F:F,"") -> No | H7: =_xlfn.XLOOKUP($A7,[1]MedicHistory!A:A,[1]MedicHistory!G:G,"") -> 0 | I7: =_xlfn.XLOOKUP($A7,[1]MedicHistory!A:A,[1]MedicHistory!H:H,"") -> yes | J7: =_xlfn.XLOOKUP($A7,[1]MedicHistory!A:A,[1]MedicHistory!K:K,"") -> Diabetic | K7: =_xlfn.XLOOKUP($A7,[1]MedicHistory!A:A,[1]MedicHistory!I:I,"") -> Obisity | L7: =_xlfn.XLOOKUP($A7,[1]Hospitalisation!A:A,[1]Hospitalisation!C:C,"") -> 52590.83 | M7: =_xlfn.XLOOKUP($A7,[1]Hospitalisation!A:A,[1]Hospitalisation!I:I,"") -> tier - 1 | N7: =_xlfn.XLOOKUP($A7,[1]Hospitalisation!A:A,[1]Hospitalisation!J:J,"") -> tier - 3 | O7: =_xlfn.XLOOKUP($A7,[1]Hospitalisation!A:A,[1]Hospitalisation!K:K,"") -> R1011 | P7: =_xlfn.XLOOKUP($A7,[1]Hospitalisation!A:A,[1]Hospitalisation!L:L,"") -> 33 | Q7: =_xlfn.XLOOKUP($A7,[1]Hospitalisation!A:A,[1]Hospitalisation!M:M,"") -> 32724
A8: Id7 | B8: =_xlfn.XLOOKUP(A8,[1]Customer!A:A,[1]Customer!C:C,"") -> Scott | C8: {=_xlfn.XLOOKUP($A8,[1]MedicHistory!A:A,[1]MedicHistory!B:B,"")} -> 36.4 | D8: {=_xlfn.XLOOKUP($A8,[1]MedicHistory!A:A,[1]MedicHistory!C:C,"")} -> 6.07 | E8: =_xlfn.XLOOKUP($A8,[1]MedicHistory!A:A,[1]MedicHistory!D:D,"") -> No | F8: =_xlfn.XLOOKUP($A8,[1]MedicHistory!A:A,[1]MedicHistory!E:E,"") -> No | G8: =_xlfn.XLOOKUP($A8,[1]MedicHistory!A:A,[1]MedicHistory!F:F,"") -> No | H8: =_xlfn.XLOOKUP($A8,[1]MedicHistory!A:A,[1]MedicHistory!G:G,"") -> 0 | I8: =_xlfn.XLOOKUP($A8,[1]MedicHistory!A:A,[1]MedicHistory!H:H,"") -> yes | J8: =_xlfn.XLOOKUP($A8,[1]MedicHistory!A:A,[1]MedicHistory!K:K,"") -> Prediabetic | K8: =_xlfn.XLOOKUP($A8,[1]MedicHistory!A:A,[1]MedicHistory!I:I,"") -> Obisity | L8: =_xlfn.XLOOKUP($A8,[1]Hospitalisation!A:A,[1]Hospitalisation!C:C,"") -> 51194.56 | M8: =_xlfn.XLOOKUP($A8,[1]Hospitalisation!A:A,[1]Hospitalisation!I:I,"") -> tier - 1 | N8: =_xlfn.XLOOKUP($A8,[1]Hospitalisation!A:A,[1]Hospitalisation!J:J,"") -> tier - 3 | O8: =_xlfn.XLOOKUP($A8,[1]Hospitalisation!A:A,[1]Hospitalisation!K:K,"") -> R1011 | P8: =_xlfn.XLOOKUP($A8,[1]Hospitalisation!A:A,[1]Hospitalisation!L:L,"") -> 60 | Q8: =_xlfn.XLOOKUP($A8,[1]Hospitalisation!A:A,[1]Hospitalisation!M:M,"") -> 22946
A9: Id8 | B9: =_xlfn.XLOOKUP(A9,[1]Customer!A:A,[1]Customer!C:C,"") -> Stephen | C9: {=_xlfn.XLOOKUP($A9,[1]MedicHistory!A:A,[1]MedicHistory!B:B,"")} -> 36.96 | D9: {=_xlfn.XLOOKUP($A9,[1]MedicHistory!A:A,[1]MedicHistory!C:C,"")} -> 7.93 | E9: =_xlfn.XLOOKUP($A9,[1]MedicHistory!A:A,[1]MedicHistory!D:D,"") -> No | F9: =_xlfn.XLOOKUP($A9,[1]MedicHistory!A:A,[1]MedicHistory!E:E,"") -> No | G9: =_xlfn.XLOOKUP($A9,[1]MedicHistory!A:A,[1]MedicHistory!F:F,"") -> No | H9: =_xlfn.XLOOKUP($A9,[1]MedicHistory!A:A,[1]MedicHistory!G:G,"") -> 3 | I9: =_xlfn.XLOOKUP($A9,[1]MedicHistory!A:A,[1]MedicHistory!H:H,"") -> yes | J9: =_xlfn.XLOOKUP($A9,[1]MedicHistory!A:A,[1]MedicHistory!K:K,"") -> Diabetic | K9: =_xlfn.XLOOKUP($A9,[1]MedicHistory!A:A,[1]MedicHistory!I:I,"") -> Obisity | L9: =_xlfn.XLOOKUP($A9,[1]Hospitalisation!A:A,[1]Hospitalisation!C:C,"") -> 49577.66 | M9: =_xlfn.XLOOKUP($A9,[1]Hospitalisation!A:A,[1]Hospitalisation!I:I,"") -> tier - 2 | N9: =_xlfn.XLOOKUP($A9,[1]Hospitalisation!A:A,[1]Hospitalisation!J:J,"") -> tier - 2 | O9: =_xlfn.XLOOKUP($A9,[1]Hospitalisation!A:A,[1]Hospitalisation!K:K,"") -> R1013 | P9: =_xlfn.XLOOKUP($A9,[1]Hospitalisation!A:A,[1]Hospitalisation!L:L,"") -> 28 | Q9: =_xlfn.XLOOKUP($A9,[1]Hospitalisation!A:A,[1]Hospitalisation!M:M,"") -> 34512
A10: Id9 | B10: =_xlfn.XLOOKUP(A10,[1]Customer!A:A,[1]Customer!C:C,"") -> Patrick | C10: {=_xlfn.XLOOKUP($A10,[1]MedicHistory!A:A,[1]MedicHistory!B:B,"")} -> 41.14 | D10: {=_xlfn.XLOOKUP($A10,[1]MedicHistory!A:A,[1]MedicHistory!C:C,"")} -> 9.58 | E10: =_xlfn.XLOOKUP($A10,[1]MedicHistory!A:A,[1]MedicHistory!D:D,"") -> yes | F10: =_xlfn.XLOOKUP($A10,[1]MedicHistory!A:A,[1]MedicHistory!E:E,"") -> No | G10: =_xlfn.XLOOKUP($A10,[1]MedicHistory!A:A,[1]MedicHistory!F:F,"") -> Yes | H10: =_xlfn.XLOOKUP($A10,[1]MedicHistory!A:A,[1]MedicHistory!G:G,"") -> 1 | I10: =_xlfn.XLOOKUP($A10,[1]MedicHistory!A:A,[1]MedicHistory!H:H,"") -> yes | J10: =_xlfn.XLOOKUP($A10,[1]MedicHistory!A:A,[1]MedicHistory!K:K,"") -> Diabetic | K10: =_xlfn.XLOOKUP($A10,[1]MedicHistory!A:A,[1]MedicHistory!I:I,"") -> Obisity | L10: =_xlfn.XLOOKUP($A10,[1]Hospitalisation!A:A,[1]Hospitalisation!C:C,"") -> 48970.25 | M10: =_xlfn.XLOOKUP($A10,[1]Hospitalisation!A:A,[1]Hospitalisation!I:I,"") -> tier - 1 | N10: =_xlfn.XLOOKUP($A10,[1]Hospitalisation!A:A,[1]Hospitalisation!J:J,"") -> tier - 2 | O10: =_xlfn.XLOOKUP($A10,[1]Hospitalisation!A:A,[1]Hospitalisation!K:K,"") -> R1013 | P10: =_xlfn.XLOOKUP($A10,[1]Hospitalisation!A:A,[1]Hospitalisation!L:L,"") -> 64 | Q10: =_xlfn.XLOOKUP($A10,[1]Hospitalisation!A:A,[1]Hospitalisation!M:M,"") -> 21432
A11: Id10 | B11: =_xlfn.XLOOKUP(A11,[1]Customer!A:A,[1]Customer!C:C,"") -> Brooke | C11: {=_xlfn.XLOOKUP($A11,[1]MedicHistory!A:A,[1]MedicHistory!B:B,"")} -> 38.06 | D11: {=_xlfn.XLOOKUP($A11,[1]MedicHistory!A:A,[1]MedicHistory!C:C,"")} -> 10.79 | E11: =_xlfn.XLOOKUP($A11,[1]MedicHistory!A:A,[1]MedicHistory!D:D,"") -> No | F11: =_xlfn.XLOOKUP($A11,[1]MedicHistory!A:A,[1]MedicHistory!E:E,"") -> No | G11: =_xlfn.XLOOKUP($A11,[1]MedicHistory!A:A,[1]MedicHistory!F:F,"") -> No | H11: =_xlfn.XLOOKUP($A11,[1]MedicHistory!A:A,[1]MedicHistory!G:G,"") -> 0 | I11: =_xlfn.XLOOKUP($A11,[1]MedicHistory!A:A,[1]MedicHistory!H:H,"") -> yes | J11: =_xlfn.XLOOKUP($A11,[1]MedicHistory!A:A,[1]MedicHistory!K:K,"") -> Diabetic | K11: =_xlfn.XLOOKUP($A11,[1]MedicHistory!A:A,[1]MedicHistory!I:I,"") -> Obisity | L11: =_xlfn.XLOOKUP($A11,[1]Hospitalisation!A:A,[1]Hospitalisation!C:C,"") -> 48885.14 | M11: =_xlfn.XLOOKUP($A11,[1]Hospitalisation!A:A,[1]Hospitalisation!I:I,"") -> tier - 1 | N11: =_xlfn.XLOOKUP($A11,[1]Hospitalisation!A:A,[1]Hospitalisation!J:J,"") -> tier - 2 | O11: =_xlfn.XLOOKUP($A11,[1]Hospitalisation!A:A,[1]Hospitalisation!K:K,"") -> R1013 | P11: =_xlfn.XLOOKUP($A11,[1]Hospitalisation!A:A,[1]Hospitalisation!L:L,"") -> 59 | Q11: =_xlfn.XLOOKUP($A11,[1]Hospitalisation!A:A,[1]Hospitalisation!M:M,"") -> 23374
A12: Id11 | B12: =_xlfn.XLOOKUP(A12,[1]Customer!A:A,[1]Customer!C:C,"") -> Andrea Paola | C12: {=_xlfn.XLOOKUP($A12,[1]MedicHistory!A:A,[1]MedicHistory!B:B,"")} -> 37.7 | D12: {=_xlfn.XLOOKUP($A12,[1]MedicHistory!A:A,[1]MedicHistory!C:C,"")} -> 5.96 | E12: =_xlfn.XLOOKUP($A12,[1]MedicHistory!A:A,[1]MedicHistory!D:D,"") -> yes | F12: =_xlfn.XLOOKUP($A12,[1]MedicHistory!A:A,[1]MedicHistory!E:E,"") -> No | G12: =_xlfn.XLOOKUP($A12,[1]MedicHistory!A:A,[1]MedicHistory!F:F,"") -> No | H12: =_xlfn.XLOOKUP($A12,[1]MedicHistory!A:A,[1]MedicHistory!G:G,"") -> 2 | I12: =_xlfn.XLOOKUP($A12,[1]MedicHistory!A:A,[1]MedicHistory!H:H,"") -> yes | J12: =_xlfn.XLOOKUP($A12,[1]MedicHistory!A:A,[1]MedicHistory!K:K,"") -> Prediabetic | K12: =_xlfn.XLOOKUP($A12,[1]MedicHistory!A:A,[1]MedicHistory!I:I,"") -> Obisity | L12: =_xlfn.XLOOKUP($A12,[1]Hospitalisation!A:A,[1]Hospitalisation!C:C,"") -> 48824.45 | M12: =_xlfn.XLOOKUP($A12,[1]Hospitalisation!A:A,[1]Hospitalisation!I:I,"") -> tier - 2 | N12: =_xlfn.XLOOKUP($A12,[1]Hospitalisation!A:A,[1]Hospitalisation!J:J,"") -> tier - 1 | O12: =_xlfn.XLOOKUP($A12,[1]Hospitalisation!A:A,[1]Hospitalisation!K:K,"") -> R1011 | P12: =_xlfn.XLOOKUP($A12,[1]Hospitalisation!A:A,[1]Hospitalisation!L:L,"") -> 44 | Q12: =_xlfn.XLOOKUP($A12,[1]Hospitalisation!A:A,[1]Hospitalisation!M:M,"") -> 28693
A13: Id12 | B13: =_xlfn.XLOOKUP(A13,[1]Customer!A:A,[1]Customer!C:C,"") -> David | C13: {=_xlfn.XLOOKUP($A13,[1]MedicHistory!A:A,[1]MedicHistory!B:B,"")} -> 42.13 | D13: {=_xlfn.XLOOKUP($A13,[1]MedicHistory!A:A,[1]MedicHistory!C:C,"")} -> 11.9 | E13: =_xlfn.XLOOKUP($A13,[1]MedicHistory!A:A,[1]MedicHistory!D:D,"") -> No | F13: =_xlfn.XLOOKUP($A13,[1]MedicHistory!A:A,[1]MedicHistory!E:E,"") -> No | G13: =_xlfn.XLOOKUP($A13,[1]MedicHistory!A:A,[1]MedicHistory!F:F,"") -> No | H13: =_xlfn.XLOOKUP($A13,[1]MedicHistory!A:A,[1]MedicHistory!G:G,"") -> 0 | I13: =_xlfn.XLOOKUP($A13,[1]MedicHistory!A:A,[1]MedicHistory!H:H,"") -> yes | J13: =_xlfn.XLOOKUP($A13,[1]MedicHistory!A:A,[1]MedicHistory!K:K,"") -> Diabetic | K13: =_xlfn.XLOOKUP($A13,[1]MedicHistory!A:A,[1]MedicHistory!I:I,"") -> Obisity | L13: =_xlfn.XLOOKUP($A13,[1]Hospitalisation!A:A,[1]Hospitalisation!C:C,"") -> 48675.52 | M13: =_xlfn.XLOOKUP($A13,[1]Hospitalisation!A:A,[1]Hospitalisation!I:I,"") -> tier - 1 | N13: =_xlfn.XLOOKUP($A13,[1]Hospitalisation!A:A,[1]Hospitalisation!J:J,"") -> tier - 2 | O13: =_xlfn.XLOOKUP($A13,[1]Hospitalisation!A:A,[1]Hospitalisation!K:K,"") -> R1013 | P13: =_xlfn.XLOOKUP($A13,[1]Hospitalisation!A:A,[1]Hospitalisation!L:L,"") -> 63 | Q13: =_xlfn.XLOOKUP($A13,[1]Hospitalisation!A:A,[1]Hospitalisation!M:M,"") -> 21850
A14: Id13 | B14: =_xlfn.XLOOKUP(A14,[1]Customer!A:A,[1]Customer!C:C,"") -> Wade | C14: {=_xlfn.XLOOKUP($A14,[1]MedicHistory!A:A,[1]MedicHistory!B:B,"")} -> 40.92 | D14: {=_xlfn.XLOOKUP($A14,[1]MedicHistory!A:A,[1]MedicHistory!C:C,"")} -> 8.41 | E14: =_xlfn.XLOOKUP($A14,[1]MedicHistory!A:A,[1]MedicHistory!D:D,"") -> No | F14: =_xlfn.XLOOKUP($A14,[1]MedicHistory!A:A,[1]MedicHistory!E:E,"") -> No | G14: =_xlfn.XLOOKUP($A14,[1]MedicHistory!A:A,[1]MedicHistory!F:F,"") -> No | H14: =_xlfn.XLOOKUP($A14,[1]MedicHistory!A:A,[1]MedicHistory!G:G,"") -> 0 | I14: =_xlfn.XLOOKUP($A14,[1]MedicHistory!A:A,[1]MedicHistory!H:H,"") -> yes | J14: =_xlfn.XLOOKUP($A14,[1]MedicHistory!A:A,[1]MedicHistory!K:K,"") -> Diabetic | K14: =_xlfn.XLOOKUP($A14,[1]MedicHistory!A:A,[1]MedicHistory!I:I,"") -> Obisity | L14: =_xlfn.XLOOKUP($A14,[1]Hospitalisation!A:A,[1]Hospitalisation!C:C,"") -> 48673.56 | M14: =_xlfn.XLOOKUP($A14,[1]Hospitalisation!A:A,[1]Hospitalisation!I:I,"") -> tier - 1 | N14: =_xlfn.XLOOKUP($A14,[1]Hospitalisation!A:A,[1]Hospitalisation!J:J,"") -> tier - 2 | O14: =_xlfn.XLOOKUP($A14,[1]Hospitalisation!A:A,[1]Hospitalisation!K:K,"") -> R1013 | P14: =_xlfn.XLOOKUP($A14,[1]Hospitalisation!A:A,[1]Hospitalisation!L:L,"") -> 57 | Q14: =_xlfn.XLOOKUP($A14,[1]Hospitalisation!A:A,[1]Hospitalisation!M:M,"") -> 24026
... A21: Id20 | B21: =_xlfn.XLOOKUP(A21,[1]Customer!A:A,[1]Customer!C:C,"") -> John | C21: {=_xlfn.XLOOKUP($A21,[1]MedicHistory!A:A,[1]MedicHistory!B:B,"")} -> 42.9 | D21: {=_xlfn.XLOOKUP($A21,[1]MedicHistory!A:A,[1]MedicHistory!C:C,"")} -> 11.41 | E21: =_xlfn.XLOOKUP($A21,[1]MedicHistory!A:A,[1]MedicHistory!D:D,"") -> No | F21: =_xlfn.XLOOKUP($A21,[1]MedicHistory!A:A,[1]MedicHistory!E:E,"") -> No | G21: =_xlfn.XLOOKUP($A21,[1]MedicHistory!A:A,[1]MedicHistory!F:F,"") -> No | H21: =_xlfn.XLOOKUP($A21,[1]MedicHistory!A:A,[1]MedicHistory!G:G,"") -> 0 | I21: =_xlfn.XLOOKUP($A21,[1]MedicHistory!A:A,[1]MedicHistory!H:H,"") -> yes | J21: =_xlfn.XLOOKUP($A21,[1]MedicHistory!A:A,[1]MedicHistory!K:K,"") -> Diabetic | K21: =_xlfn.XLOOKUP($A21,[1]MedicHistory!A:A,[1]MedicHistory!I:I,"") -> Obisity | L21: =_xlfn.XLOOKUP($A21,[1]Hospitalisation!A:A,[1]Hospitalisation!C:C,"") -> 47462.89 | M21: =_xlfn.XLOOKUP($A21,[1]Hospitalisation!A:A,[1]Hospitalisation!I:I,"") -> tier - 1 | N21: =_xlfn.XLOOKUP($A21,[1]Hospitalisation!A:A,[1]Hospitalisation!J:J,"") -> tier - 2 | O21: =_xlfn.XLOOKUP($A21,[1]Hospitalisation!A:A,[1]Hospitalisation!K:K,"") -> R1013 | P21: =_xlfn.XLOOKUP($A21,[1]Hospitalisation!A:A,[1]Hospitalisation!L:L,"") -> 58 | Q21: =_xlfn.XLOOKUP($A21,[1]Hospitalisation!A:A,[1]Hospitalisation!M:M,"") -> 23647
A22: Id21 | B22: =_xlfn.XLOOKUP(A22,[1]Customer!A:A,[1]Customer!C:C,"") -> Myles | C22: {=_xlfn.XLOOKUP($A22,[1]MedicHistory!A:A,[1]MedicHistory!B:B,"")} -> 36.3 | D22: {=_xlfn.XLOOKUP($A22,[1]MedicHistory!A:A,[1]MedicHistory!C:C,"")} -> 11.5 | E22: =_xlfn.XLOOKUP($A22,[1]MedicHistory!A:A,[1]MedicHistory!D:D,"") -> yes | F22: =_xlfn.XLOOKUP($A22,[1]MedicHistory!A:A,[1]MedicHistory!E:E,"") -> No | G22: =_xlfn.XLOOKUP($A22,[1]MedicHistory!A:A,[1]MedicHistory!F:F,"") -> No | H22: 0 | I22: =_xlfn.XLOOKUP($A22,[1]MedicHistory!A:A,[1]MedicHistory!H:H,"") -> yes | J22: =_xlfn.XLOOKUP($A22,[1]MedicHistory!A:A,[1]MedicHistory!K:K,"") -> Diabetic | K22: =_xlfn.XLOOKUP($A22,[1]MedicHistory!A:A,[1]MedicHistory!I:I,"") -> Obisity | L22: =_xlfn.XLOOKUP($A22,[1]Hospitalisation!A:A,[1]Hospitalisation!C:C,"") -> 47403.88 | M22: =_xlfn.XLOOKUP($A22,[1]Hospitalisation!A:A,[1]Hospitalisation!I:I,"") -> tier - 1 | N22: =_xlfn.XLOOKUP($A22,[1]Hospitalisation!A:A,[1]Hospitalisation!J:J,"") -> tier - 3 | O22: =_xlfn.XLOOKUP($A22,[1]Hospitalisation!A:A,[1]Hospitalisation!K:K,"") -> R1011 | P22: =_xlfn.XLOOKUP($A22,[1]Hospitalisation!A:A,[1]Hospitalisation!L:L,"") -> 51 | Q22: =_xlfn.XLOOKUP($A22,[1]Hospitalisation!A:A,[1]Hospitalisation!M:M,"") -> 26097
A23: Id22 | B23: =_xlfn.XLOOKUP(A23,[1]Customer!A:A,[1]Customer!C:C,"") -> Madelyn | C23: {=_xlfn.XLOOKUP($A23,[1]MedicHistory!A:A,[1]MedicHistory!B:B,"")} -> 32.2 | D23: {=_xlfn.XLOOKUP($A23,[1]MedicHistory!A:A,[1]MedicHistory!C:C,"")} -> 6.22 | E23: =_xlfn.XLOOKUP($A23,[1]MedicHistory!A:A,[1]MedicHistory!D:D,"") -> yes | F23: =_xlfn.XLOOKUP($A23,[1]MedicHistory!A:A,[1]MedicHistory!E:E,"") -> No | G23: =_xlfn.XLOOKUP($A23,[1]MedicHistory!A:A,[1]MedicHistory!F:F,"") -> No | H23: =_xlfn.XLOOKUP($A23,[1]MedicHistory!A:A,[1]MedicHistory!G:G,"") -> 2 | I23: =_xlfn.XLOOKUP($A23,[1]MedicHistory!A:A,[1]MedicHistory!H:H,"") -> yes | J23: =_xlfn.XLOOKUP($A23,[1]MedicHistory!A:A,[1]MedicHistory!K:K,"") -> Prediabetic | K23: =_xlfn.XLOOKUP($A23,[1]MedicHistory!A:A,[1]MedicHistory!I:I,"") -> Obisity | L23: =_xlfn.XLOOKUP($A23,[1]Hospitalisation!A:A,[1]Hospitalisation!C:C,"") -> 47305.31 | M23: =_xlfn.XLOOKUP($A23,[1]Hospitalisation!A:A,[1]Hospitalisation!I:I,"") -> tier - 2 | N23: =_xlfn.XLOOKUP($A23,[1]Hospitalisation!A:A,[1]Hospitalisation!J:J,"") -> tier - 1 | O23: =_xlfn.XLOOKUP($A23,[1]Hospitalisation!A:A,[1]Hospitalisation!K:K,"") -> R1011 | P23: =_xlfn.XLOOKUP($A23,[1]Hospitalisation!A:A,[1]Hospitalisation!L:L,"") -> 61 | Q23: =_xlfn.XLOOKUP($A23,[1]Hospitalisation!A:A,[1]Hospitalisation!M:M,"") -> 22558
A24: Id23 | B24: =_xlfn.XLOOKUP(A24,[1]Customer!A:A,[1]Customer!C:C,"") -> Nicole | C24: {=_xlfn.XLOOKUP($A24,[1]MedicHistory!A:A,[1]MedicHistory!B:B,"")} -> 31.3 | D24: {=_xlfn.XLOOKUP($A24,[1]MedicHistory!A:A,[1]MedicHistory!C:C,"")} -> 11.38 | E24: =_xlfn.XLOOKUP($A24,[1]MedicHistory!A:A,[1]MedicHistory!D:D,"") -> No | F24: =_xlfn.XLOOKUP($A24,[1]MedicHistory!A:A,[1]MedicHistory!E:E,"") -> No | G24: =_xlfn.XLOOKUP($A24,[1]MedicHistory!A:A,[1]MedicHistory!F:F,"") -> No | H24: =_xlfn.XLOOKUP($A24,[1]MedicHistory!A:A,[1]MedicHistory!G:G,"") -> 3 | I24: =_xlfn.XLOOKUP($A24,[1]MedicHistory!A:A,[1]MedicHistory!H:H,"") -> yes | J24: =_xlfn.XLOOKUP($A24,[1]MedicHistory!A:A,[1]MedicHistory!K:K,"") -> Diabetic | K24: =_xlfn.XLOOKUP($A24,[1]MedicHistory!A:A,[1]MedicHistory!I:I,"") -> Obisity | L24: =_xlfn.XLOOKUP($A24,[1]Hospitalisation!A:A,[1]Hospitalisation!C:C,"") -> 47291.06 | M24: =_xlfn.XLOOKUP($A24,[1]Hospitalisation!A:A,[1]Hospitalisation!I:I,"") -> tier - 2 | N24: =_xlfn.XLOOKUP($A24,[1]Hospitalisation!A:A,[1]Hospitalisation!J:J,"") -> tier - 1 | O24: =_xlfn.XLOOKUP($A24,[1]Hospitalisation!A:A,[1]Hospitalisation!K:K,"") -> R1011 | P24: =_xlfn.XLOOKUP($A24,[1]Hospitalisation!A:A,[1]Hospitalisation!L:L,"") -> 63 | Q24: =_xlfn.XLOOKUP($A24,[1]Hospitalisation!A:A,[1]Hospitalisation!M:M,"") -> 21796
A25: Id24 | B25: =_xlfn.XLOOKUP(A25,[1]Customer!A:A,[1]Customer!C:C,"") -> Eric | C25: {=_xlfn.XLOOKUP($A25,[1]MedicHistory!A:A,[1]MedicHistory!B:B,"")} -> 41.8 | D25: {=_xlfn.XLOOKUP($A25,[1]MedicHistory!A:A,[1]MedicHistory!C:C,"")} -> 7.89 | E25: =_xlfn.XLOOKUP($A25,[1]MedicHistory!A:A,[1]MedicHistory!D:D,"") -> yes | F25: =_xlfn.XLOOKUP($A25,[1]MedicHistory!A:A,[1]MedicHistory!E:E,"") -> No | G25: =_xlfn.XLOOKUP($A25,[1]MedicHistory!A:A,[1]MedicHistory!F:F,"") -> No | H25: =_xlfn.XLOOKUP($A25,[1]MedicHistory!A:A,[1]MedicHistory!G:G,"") -> 2 | I25: =_xlfn.XLOOKUP($A25,[1]MedicHistory!A:A,[1]MedicHistory!H:H,"") -> yes | J25: =_xlfn.XLOOKUP($A25,[1]MedicHistory!A:A,[1]MedicHistory!K:K,"") -> Diabetic | K25: =_xlfn.XLOOKUP($A25,[1]MedicHistory!A:A,[1]MedicHistory!I:I,"") -> Obisity | L25: =_xlfn.XLOOKUP($A25,[1]Hospitalisation!A:A,[1]Hospitalisation!C:C,"") -> 47269.85 | M25: =_xlfn.XLOOKUP($A25,[1]Hospitalisation!A:A,[1]Hospitalisation!I:I,"") -> tier - 1 | N25: =_xlfn.XLOOKUP($A25,[1]Hospitalisation!A:A,[1]Hospitalisation!J:J,"") -> tier - 2 | O25: =_xlfn.XLOOKUP($A25,[1]Hospitalisation!A:A,[1]Hospitalisation!K:K,"") -> R1013 | P25: =_xlfn.XLOOKUP($A25,[1]Hospitalisation!A:A,[1]Hospitalisation!L:L,"") -> 64 | Q25: =_xlfn.XLOOKUP($A25,[1]Hospitalisation!A:A,[1]Hospitalisation!M:M,"") -> 21547
A26: Id25 | B26: =_xlfn.XLOOKUP(A26,[1]Customer!A:A,[1]Customer!C:C,"") -> Emiliano | C26: {=_xlfn.XLOOKUP($A26,[1]MedicHistory!A:A,[1]MedicHistory!B:B,"")} -> 35.09 | D26: {=_xlfn.XLOOKUP($A26,[1]MedicHistory!A:A,[1]MedicHistory!C:C,"")} -> 4.38 | E26: =_xlfn.XLOOKUP($A26,[1]MedicHistory!A:A,[1]MedicHistory!D:D,"") -> yes | F26: =_xlfn.XLOOKUP($A26,[1]MedicHistory!A:A,[1]MedicHistory!E:E,"") -> No | G26: =_xlfn.XLOOKUP($A26,[1]MedicHistory!A:A,[1]MedicHistory!F:F,"") -> No | H26: =_xlfn.XLOOKUP($A26,[1]MedicHistory!A:A,[1]MedicHistory!G:G,"") -> 2 | I26: =_xlfn.XLOOKUP($A26,[1]MedicHistory!A:A,[1]MedicHistory!H:H,"") -> yes | J26: =_xlfn.XLOOKUP($A26,[1]MedicHistory!A:A,[1]MedicHistory!K:K,"") -> Normal | K26: =_xlfn.XLOOKUP($A26,[1]MedicHistory!A:A,[1]MedicHistory!I:I,"") -> Obisity | L26: =_xlfn.XLOOKUP($A26,[1]Hospitalisation!A:A,[1]Hospitalisation!C:C,"") -> 47055.53 | M26: =_xlfn.XLOOKUP($A26,[1]Hospitalisation!A:A,[1]Hospitalisation!I:I,"") -> tier - 2 | N26: =_xlfn.XLOOKUP($A26,[1]Hospitalisation!A:A,[1]Hospitalisation!J:J,"") -> tier - 1 | O26: =_xlfn.XLOOKUP($A26,[1]Hospitalisation!A:A,[1]Hospitalisation!K:K,"") -> R1013 | P26: =_xlfn.XLOOKUP($A26,[1]Hospitalisation!A:A,[1]Hospitalisation!L:L,"") -> 52 | Q26: =_xlfn.XLOOKUP($A26,[1]Hospitalisation!A:A,[1]Hospitalisation!M:M,"") -> 25763
A27: Id26 | B27: =_xlfn.XLOOKUP(A27,[1]Customer!A:A,[1]Customer!C:C,"") -> Adam | C27: {=_xlfn.XLOOKUP($A27,[1]MedicHistory!A:A,[1]MedicHistory!B:B,"")} -> 33.88 | D27: {=_xlfn.XLOOKUP($A27,[1]MedicHistory!A:A,[1]MedicHistory!C:C,"")} -> 7.01 | E27: =_xlfn.XLOOKUP($A27,[1]MedicHistory!A:A,[1]MedicHistory!D:D,"") -> No | F27: =_xlfn.XLOOKUP($A27,[1]MedicHistory!A:A,[1]MedicHistory!E:E,"") -> No | G27: =_xlfn.XLOOKUP($A27,[1]MedicHistory!A:A,[1]MedicHistory!F:F,"") -> No | H27: =_xlfn.XLOOKUP($A27,[1]MedicHistory!A:A,[1]MedicHistory!G:G,"") -> 3 | I27: =_xlfn.XLOOKUP($A27,[1]MedicHistory!A:A,[1]MedicHistory!H:H,"") -> yes | J27: =_xlfn.XLOOKUP($A27,[1]MedicHistory!A:A,[1]MedicHistory!K:K,"") -> Diabetic | K27: =_xlfn.XLOOKUP($A27,[1]MedicHistory!A:A,[1]MedicHistory!I:I,"") -> Obisity | L27: =_xlfn.XLOOKUP($A27,[1]Hospitalisation!A:A,[1]Hospitalisation!C:C,"") -> 46889.26 | M27: =_xlfn.XLOOKUP($A27,[1]Hospitalisation!A:A,[1]Hospitalisation!I:I,"") -> tier - 2 | N27: =_xlfn.XLOOKUP($A27,[1]Hospitalisation!A:A,[1]Hospitalisation!J:J,"") -> tier - 3 | O27: =_xlfn.XLOOKUP($A27,[1]Hospitalisation!A:A,[1]Hospitalisation!K:K,"") -> R1013 | P27: =_xlfn.XLOOKUP($A27,[1]Hospitalisation!A:A,[1]Hospitalisation!L:L,"") -> 63 | Q27: =_xlfn.XLOOKUP($A27,[1]Hospitalisation!A:A,[1]Hospitalisation!M:M,"") -> 21808
A28: Id27 | B28: =_xlfn.XLOOKUP(A28,[1]Customer!A:A,[1]Customer!C:C,"") -> Zach | C28: {=_xlfn.XLOOKUP($A28,[1]MedicHistory!A:A,[1]MedicHistory!B:B,"")} -> 30.875 | D28: {=_xlfn.XLOOKUP($A28,[1]MedicHistory!A:A,[1]MedicHistory!C:C,"")} -> 11.88 | E28: =_xlfn.XLOOKUP($A28,[1]MedicHistory!A:A,[1]MedicHistory!D:D,"") -> No | F28: =_xlfn.XLOOKUP($A28,[1]MedicHistory!A:A,[1]MedicHistory!E:E,"") -> No | G28: =_xlfn.XLOOKUP($A28,[1]MedicHistory!A:A,[1]MedicHistory!F:F,"") -> No | H28: =_xlfn.XLOOKUP($A28,[1]MedicHistory!A:A,[1]MedicHistory!G:G,"") -> 0 | I28: =_xlfn.XLOOKUP($A28,[1]MedicHistory!A:A,[1]MedicHistory!H:H,"") -> yes | J28: =_xlfn.XLOOKUP($A28,[1]MedicHistory!A:A,[1]MedicHistory!K:K,"") -> Diabetic | K28: =_xlfn.XLOOKUP($A28,[1]MedicHistory!A:A,[1]MedicHistory!I:I,"") -> Obisity | L28: =_xlfn.XLOOKUP($A28,[1]Hospitalisation!A:A,[1]Hospitalisation!C:C,"") -> 46718.16 | M28: =_xlfn.XLOOKUP($A28,[1]Hospitalisation!A:A,[1]Hospitalisation!I:I,"") -> tier - 1 | N28: =_xlfn.XLOOKUP($A28,[1]Hospitalisation!A:A,[1]Hospitalisation!J:J,"") -> tier - 1 | O28: =_xlfn.XLOOKUP($A28,[1]Hospitalisation!A:A,[1]Hospitalisation!K:K,"") -> R1012 | P28: =_xlfn.XLOOKUP($A28,[1]Hospitalisation!A:A,[1]Hospitalisation!L:L,"") -> 64 | Q28: =_xlfn.XLOOKUP($A28,[1]Hospitalisation!A:A,[1]Hospitalisation!M:M,"") -> 21506
A29: Id28 | B29: =_xlfn.XLOOKUP(A29,[1]Customer!A:A,[1]Customer!C:C,"") -> Stephanie | C29: {=_xlfn.XLOOKUP($A29,[1]MedicHistory!A:A,[1]MedicHistory!B:B,"")} -> 36.86 | D29: {=_xlfn.XLOOKUP($A29,[1]MedicHistory!A:A,[1]MedicHistory!C:C,"")} -> 5.19 | E29: =_xlfn.XLOOKUP($A29,[1]MedicHistory!A:A,[1]MedicHistory!D:D,"") -> yes | F29: =_xlfn.XLOOKUP($A29,[1]MedicHistory!A:A,[1]MedicHistory!E:E,"") -> No | G29: =_xlfn.XLOOKUP($A29,[1]MedicHistory!A:A,[1]MedicHistory!F:F,"") -> Yes | H29: =_xlfn.XLOOKUP($A29,[1]MedicHistory!A:A,[1]MedicHistory!G:G,"") -> 1 | I29: =_xlfn.XLOOKUP($A29,[1]MedicHistory!A:A,[1]MedicHistory!H:H,"") -> yes | J29: =_xlfn.XLOOKUP($A29,[1]MedicHistory!A:A,[1]MedicHistory!K:K,"") -> Normal | K29: =_xlfn.XLOOKUP($A29,[1]MedicHistory!A:A,[1]MedicHistory!I:I,"") -> Obisity | L29: =_xlfn.XLOOKUP($A29,[1]Hospitalisation!A:A,[1]Hospitalisation!C:C,"") -> 46661.44 | M29: =_xlfn.XLOOKUP($A29,[1]Hospitalisation!A:A,[1]Hospitalisation!I:I,"") -> tier - 1 | N29: =_xlfn.XLOOKUP($A29,[1]Hospitalisation!A:A,[1]Hospitalisation!J:J,"") -> tier - 3 | O29: =_xlfn.XLOOKUP($A29,[1]Hospitalisation!A:A,[1]Hospitalisation!K:K,"") -> R1012 | P29: =_xlfn.XLOOKUP($A29,[1]Hospitalisation!A:A,[1]Hospitalisation!L:L,"") -> 62 | Q29: =_xlfn.XLOOKUP($A29,[1]Hospitalisation!A:A,[1]Hospitalisation!M:M,"") -> 22090
A30: Id29 | B30: =_xlfn.XLOOKUP(A30,[1]Customer!A:A,[1]Customer!C:C,"") -> Stephen | C30: {=_xlfn.XLOOKUP($A30,[1]MedicHistory!A:A,[1]MedicHistory!B:B,"")} -> 35.86 | D30: {=_xlfn.XLOOKUP($A30,[1]MedicHistory!A:A,[1]MedicHistory!C:C,"")} -> 6.74 | E30: =_xlfn.XLOOKUP($A30,[1]MedicHistory!A:A,[1]MedicHistory!D:D,"") -> yes | F30: =_xlfn.XLOOKUP($A30,[1]MedicHistory!A:A,[1]MedicHistory!E:E,"") -> No | G30: =_xlfn.XLOOKUP($A30,[1]MedicHistory!A:A,[1]MedicHistory!F:F,"") -> No | H30: =_xlfn.XLOOKUP($A30,[1]MedicHistory!A:A,[1]MedicHistory!G:G,"") -> 2 | I30: =_xlfn.XLOOKUP($A30,[1]MedicHistory!A:A,[1]MedicHistory!H:H,"") -> yes | J30: =_xlfn.XLOOKUP($A30,[1]MedicHistory!A:A,[1]MedicHistory!K:K,"") -> Diabetic | K30: =_xlfn.XLOOKUP($A30,[1]MedicHistory!A:A,[1]MedicHistory!I:I,"") -> Obisity | L30: =_xlfn.XLOOKUP($A30,[1]Hospitalisation!A:A,[1]Hospitalisation!C:C,"") -> 46599.11 | M30: =_xlfn.XLOOKUP($A30,[1]Hospitalisation!A:A,[1]Hospitalisation!I:I,"") -> tier - 1 | N30: =_xlfn.XLOOKUP($A30,[1]Hospitalisation!A:A,[1]Hospitalisation!J:J,"") -> tier - 1 | O30: =_xlfn.XLOOKUP($A30,[1]Hospitalisation!A:A,[1]Hospitalisation!K:K,"") -> R1013 | P30: =_xlfn.XLOOKUP($A30,[1]Hospitalisation!A:A,[1]Hospitalisation!L:L,"") -> 53 | Q30: =_xlfn.XLOOKUP($A30,[1]Hospitalisation!A:A,[1]Hospitalisation!M:M,"") -> 25423
A31: Id30 | B31: =_xlfn.XLOOKUP(A31,[1]Customer!A:A,[1]Customer!C:C,"") -> Natalie | C31: {=_xlfn.XLOOKUP($A31,[1]MedicHistory!A:A,[1]MedicHistory!B:B,"")} -> 37.05 | D31: {=_xlfn.XLOOKUP($A31,[1]MedicHistory!A:A,[1]MedicHistory!C:C,"")} -> 8.44 | E31: =_xlfn.XLOOKUP($A31,[1]MedicHistory!A:A,[1]MedicHistory!D:D,"") -> No | F31: =_xlfn.XLOOKUP($A31,[1]MedicHistory!A:A,[1]MedicHistory!E:E,"") -> No | G31: =_xlfn.XLOOKUP($A31,[1]MedicHistory!A:A,[1]MedicHistory!F:F,"") -> No | H31: =_xlfn.XLOOKUP($A31,[1]MedicHistory!A:A,[1]MedicHistory!G:G,"") -> 0 | I31: =_xlfn.XLOOKUP($A31,[1]MedicHistory!A:A,[1]MedicHistory!H:H,"") -> yes | J31: =_xlfn.XLOOKUP($A31,[1]MedicHistory!A:A,[1]MedicHistory!K:K,"") -> Diabetic | K31: =_xlfn.XLOOKUP($A31,[1]MedicHistory!A:A,[1]MedicHistory!I:I,"") -> Obisity | L31: =_xlfn.XLOOKUP($A31,[1]Hospitalisation!A:A,[1]Hospitalisation!C:C,"") -> 46255.11 | M31: =_xlfn.XLOOKUP($A31,[1]Hospitalisation!A:A,[1]Hospitalisation!I:I,"") -> tier - 1 | N31: =_xlfn.XLOOKUP($A31,[1]Hospitalisation!A:A,[1]Hospitalisation!J:J,"") -> tier - 3 | O31: =_xlfn.XLOOKUP($A31,[1]Hospitalisation!A:A,[1]Hospitalisation!K:K,"") -> R1024 | P31: =_xlfn.XLOOKUP($A31,[1]Hospitalisation!A:A,[1]Hospitalisation!L:L,"") -> 61 | Q31: =_xlfn.XLOOKUP($A31,[1]Hospitalisation!A:A,[1]Hospitalisation!M:M,"") -> 22621
A32: Id31 | B32: =_xlfn.XLOOKUP(A32,[1]Customer!A:A,[1]Customer!C:C,"") -> Nicole | C32: {=_xlfn.XLOOKUP($A32,[1]MedicHistory!A:A,[1]MedicHistory!B:B,"")} -> 43.89 | D32: {=_xlfn.XLOOKUP($A32,[1]MedicHistory!A:A,[1]MedicHistory!C:C,"")} -> 8.71 | E32: =_xlfn.XLOOKUP($A32,[1]MedicHistory!A:A,[1]MedicHistory!D:D,"") -> No | F32: =_xlfn.XLOOKUP($A32,[1]MedicHistory!A:A,[1]MedicHistory!E:E,"") -> No | G32: =_xlfn.XLOOKUP($A32,[1]MedicHistory!A:A,[1]MedicHistory!F:F,"") -> No | H32: =_xlfn.XLOOKUP($A32,[1]MedicHistory!A:A,[1]MedicHistory!G:G,"") -> 0 | I32: =_xlfn.XLOOKUP($A32,[1]MedicHistory!A:A,[1]MedicHistory!H:H,"") -> yes | J32: =_xlfn.XLOOKUP($A32,[1]MedicHistory!A:A,[1]MedicHistory!K:K,"") -> Diabetic | K32: =_xlfn.XLOOKUP($A32,[1]MedicHistory!A:A,[1]MedicHistory!I:I,"") -> Obisity | L32: =_xlfn.XLOOKUP($A32,[1]Hospitalisation!A:A,[1]Hospitalisation!C:C,"") -> 46200.99 | M32: =_xlfn.XLOOKUP($A32,[1]Hospitalisation!A:A,[1]Hospitalisation!I:I,"") -> tier - 1 | N32: =_xlfn.XLOOKUP($A32,[1]Hospitalisation!A:A,[1]Hospitalisation!J:J,"") -> tier - 1 | O32: =_xlfn.XLOOKUP($A32,[1]Hospitalisation!A:A,[1]Hospitalisation!K:K,"") -> R1013 | P32: =_xlfn.XLOOKUP($A32,[1]Hospitalisation!A:A,[1]Hospitalisation!L:L,"") -> 51 | Q32: =_xlfn.XLOOKUP($A32,[1]Hospitalisation!A:A,[1]Hospitalisation!M:M,"") -> 26162
A33: Id32 | B33: =_xlfn.XLOOKUP(A33,[1]Customer!A:A,[1]Customer!C:C,"") -> Jefferson | C33: {=_xlfn.XLOOKUP($A33,[1]MedicHistory!A:A,[1]MedicHistory!B:B,"")} -> 42.35 | D33: {=_xlfn.XLOOKUP($A33,[1]MedicHistory!A:A,[1]MedicHistory!C:C,"")} -> 5.08 | E33: =_xlfn.XLOOKUP($A33,[1]MedicHistory!A:A,[1]MedicHistory!D:D,"") -> yes | F33: =_xlfn.XLOOKUP($A33,[1]MedicHistory!A:A,[1]MedicHistory!E:E,"") -> No | G33: =_xlfn.XLOOKUP($A33,[1]MedicHistory!A:A,[1]MedicHistory!F:F,"") -> No | H33: =_xlfn.XLOOKUP($A33,[1]MedicHistory!A:A,[1]MedicHistory!G:G,"") -> 0 | I33: =_xlfn.XLOOKUP($A33,[1]MedicHistory!A:A,[1]MedicHistory!H:H,"") -> yes | J33: =_xlfn.XLOOKUP($A33,[1]MedicHistory!A:A,[1]MedicHistory!K:K,"") -> Normal | K33: =_xlfn.XLOOKUP($A33,[1]MedicHistory!A:A,[1]MedicHistory!I:I,"") -> Obisity | L33: =_xlfn.XLOOKUP($A33,[1]Hospitalisation!A:A,[1]Hospitalisation!C:C,"") -> 46151.12 | M33: =_xlfn.XLOOKUP($A33,[1]Hospitalisation!A:A,[1]Hospitalisation!I:I,"") -> tier - 1 | N33: =_xlfn.XLOOKUP($A33,[1]Hospitalisation!A:A,[1]Hospitalisation!J:J,"") -> tier - 3 | O33: =_xlfn.XLOOKUP($A33,[1]Hospitalisation!A:A,[1]Hospitalisation!K:K,"") -> R1013 | P33: =_xlfn.XLOOKUP($A33,[1]Hospitalisation!A:A,[1]Hospitalisation!L:L,"") -> 44 | Q33: =_xlfn.XLOOKUP($A33,[1]Hospitalisation!A:A,[1]Hospitalisation!M:M,"") -> 28826
A34: Id33 | B34: =_xlfn.XLOOKUP(A34,[1]Customer!A:A,[1]Customer!C:C,"") -> Brendan | C34: {=_xlfn.XLOOKUP($A34,[1]MedicHistory!A:A,[1]MedicHistory!B:B,"")} -> 31.35 | D34: {=_xlfn.XLOOKUP($A34,[1]MedicHistory!A:A,[1]MedicHistory!C:C,"")} -> 6.86 | E34: =_xlfn.XLOOKUP($A34,[1]MedicHistory!A:A,[1]MedicHistory!D:D,"") -> No | F34: =_xlfn.XLOOKUP($A34,[1]MedicHistory!A:A,[1]MedicHistory!E:E,"") -> No | G34: =_xlfn.XLOOKUP($A34,[1]MedicHistory!A:A,[1]MedicHistory!F:F,"") -> No | H34: =_xlfn.XLOOKUP($A34,[1]MedicHistory!A:A,[1]MedicHistory!G:G,"") -> 0 | I34: =_xlfn.XLOOKUP($A34,[1]MedicHistory!A:A,[1]MedicHistory!H:H,"") -> yes | J34: =_xlfn.XLOOKUP($A34,[1]MedicHistory!A:A,[1]MedicHistory!K:K,"") -> Diabetic | K34: =_xlfn.XLOOKUP($A34,[1]MedicHistory!A:A,[1]MedicHistory!I:I,"") -> Obisity | L34: =_xlfn.XLOOKUP($A34,[1]Hospitalisation!A:A,[1]Hospitalisation!C:C,"") -> 46130.53 | M34: =_xlfn.XLOOKUP($A34,[1]Hospitalisation!A:A,[1]Hospitalisation!I:I,"") -> tier - 1 | N34: =_xlfn.XLOOKUP($A34,[1]Hospitalisation!A:A,[1]Hospitalisation!J:J,"") -> tier - 1 | O34: =_xlfn.XLOOKUP($A34,[1]Hospitalisation!A:A,[1]Hospitalisation!K:K,"") -> R1012 | P34: =_xlfn.XLOOKUP($A34,[1]Hospitalisation!A:A,[1]Hospitalisation!L:L,"") -> 46 | Q34: =_xlfn.XLOOKUP($A34,[1]Hospitalisation!A:A,[1]Hospitalisation!M:M,"") -> 28098
... A560: Id559 | B560: =_xlfn.XLOOKUP(A560,[1]Customer!A:A,[1]Customer!C:C,"") -> Angela | C560: {=_xlfn.XLOOKUP($A560,[1]MedicHistory!A:A,[1]MedicHistory!B:B,"")} -> 28.88 | D560: {=_xlfn.XLOOKUP($A560,[1]MedicHistory!A:A,[1]MedicHistory!C:C,"")} -> 5.35 | E560: =_xlfn.XLOOKUP($A560,[1]MedicHistory!A:A,[1]MedicHistory!D:D,"") -> No | F560: =_xlfn.XLOOKUP($A560,[1]MedicHistory!A:A,[1]MedicHistory!E:E,"") -> No | G560: =_xlfn.XLOOKUP($A560,[1]MedicHistory!A:A,[1]MedicHistory!F:F,"") -> Yes | H560: =_xlfn.XLOOKUP($A560,[1]MedicHistory!A:A,[1]MedicHistory!G:G,"") -> 1 | I560: =_xlfn.XLOOKUP($A560,[1]MedicHistory!A:A,[1]MedicHistory!H:H,"") -> yes | J560: =_xlfn.XLOOKUP($A560,[1]MedicHistory!A:A,[1]MedicHistory!K:K,"") -> Normal | K560: =_xlfn.XLOOKUP($A560,[1]MedicHistory!A:A,[1]MedicHistory!I:I,"") -> over weight | L560: =_xlfn.XLOOKUP($A560,[1]Hospitalisation!A:A,[1]Hospitalisation!C:C,"") -> 17748.51 | M560: =_xlfn.XLOOKUP($A560,[1]Hospitalisation!A:A,[1]Hospitalisation!I:I,"") -> tier - 1 | N560: =_xlfn.XLOOKUP($A560,[1]Hospitalisation!A:A,[1]Hospitalisation!J:J,"") -> tier - 1 | O560: =_xlfn.XLOOKUP($A560,[1]Hospitalisation!A:A,[1]Hospitalisation!K:K,"") -> R1012 | P560: =_xlfn.XLOOKUP($A560,[1]Hospitalisation!A:A,[1]Hospitalisation!L:L,"") -> 56 | Q560: =_xlfn.XLOOKUP($A560,[1]Hospitalisation!A:A,[1]Hospitalisation!M:M,"") -> 24302
A561: Id560 | B561: =_xlfn.XLOOKUP(A561,[1]Customer!A:A,[1]Customer!C:C,"") -> Oz | C561: {=_xlfn.XLOOKUP($A561,[1]MedicHistory!A:A,[1]MedicHistory!B:B,"")} -> 23.98 | D561: {=_xlfn.XLOOKUP($A561,[1]MedicHistory!A:A,[1]MedicHistory!C:C,"")} -> 4.9 | E561: =_xlfn.XLOOKUP($A561,[1]MedicHistory!A:A,[1]MedicHistory!D:D,"") -> No | F561: =_xlfn.XLOOKUP($A561,[1]MedicHistory!A:A,[1]MedicHistory!E:E,"") -> No | G561: =_xlfn.XLOOKUP($A561,[1]MedicHistory!A:A,[1]MedicHistory!F:F,"") -> No | H561: =_xlfn.XLOOKUP($A561,[1]MedicHistory!A:A,[1]MedicHistory!G:G,"") -> 0 | I561: yes | J561: =_xlfn.XLOOKUP($A561,[1]MedicHistory!A:A,[1]MedicHistory!K:K,"") -> Normal | K561: =_xlfn.XLOOKUP($A561,[1]MedicHistory!A:A,[1]MedicHistory!I:I,"") -> Normal weight | L561: =_xlfn.XLOOKUP($A561,[1]Hospitalisation!A:A,[1]Hospitalisation!C:C,"") -> 17663.14 | M561: =_xlfn.XLOOKUP($A561,[1]Hospitalisation!A:A,[1]Hospitalisation!I:I,"") -> tier - 1 | N561: =_xlfn.XLOOKUP($A561,[1]Hospitalisation!A:A,[1]Hospitalisation!J:J,"") -> tier - 3 | O561: =_xlfn.XLOOKUP($A561,[1]Hospitalisation!A:A,[1]Hospitalisation!K:K,"") -> R1013 | P561: =_xlfn.XLOOKUP($A561,[1]Hospitalisation!A:A,[1]Hospitalisation!L:L,"") -> 19 | Q561: =_xlfn.XLOOKUP($A561,[1]Hospitalisation!A:A,[1]Hospitalisation!M:M,"") -> 37803
A562: Id561 | B562: =_xlfn.XLOOKUP(A562,[1]Customer!A:A,[1]Customer!C:C,"") -> Erin | C562: {=_xlfn.XLOOKUP($A562,[1]MedicHistory!A:A,[1]MedicHistory!B:B,"")} -> 23.65 | D562: {=_xlfn.XLOOKUP($A562,[1]MedicHistory!A:A,[1]MedicHistory!C:C,"")} -> 4.5 | E562: =_xlfn.XLOOKUP($A562,[1]MedicHistory!A:A,[1]MedicHistory!D:D,"") -> No | F562: =_xlfn.XLOOKUP($A562,[1]MedicHistory!A:A,[1]MedicHistory!E:E,"") -> No | G562: =_xlfn.XLOOKUP($A562,[1]MedicHistory!A:A,[1]MedicHistory!F:F,"") -> No | H562: =_xlfn.XLOOKUP($A562,[1]MedicHistory!A:A,[1]MedicHistory!G:G,"") -> 0 | I562: =_xlfn.XLOOKUP($A562,[1]MedicHistory!A:A,[1]MedicHistory!H:H,"") -> No | J562: =_xlfn.XLOOKUP($A562,[1]MedicHistory!A:A,[1]MedicHistory!K:K,"") -> Normal | K562: =_xlfn.XLOOKUP($A562,[1]MedicHistory!A:A,[1]MedicHistory!I:I,"") -> Normal weight | L562: =_xlfn.XLOOKUP($A562,[1]Hospitalisation!A:A,[1]Hospitalisation!C:C,"") -> 17626.24 | M562: =_xlfn.XLOOKUP($A562,[1]Hospitalisation!A:A,[1]Hospitalisation!I:I,"") -> tier - 1 | N562: =_xlfn.XLOOKUP($A562,[1]Hospitalisation!A:A,[1]Hospitalisation!J:J,"") -> tier - 3 | O562: =_xlfn.XLOOKUP($A562,[1]Hospitalisation!A:A,[1]Hospitalisation!K:K,"") -> R1013 | P562: =_xlfn.XLOOKUP($A562,[1]Hospitalisation!A:A,[1]Hospitalisation!L:L,"") -> 28 | Q562: =_xlfn.XLOOKUP($A562,[1]Hospitalisation!A:A,[1]Hospitalisation!M:M,"") -> 34632
A563: Id562 | B563: =_xlfn.XLOOKUP(A563,[1]Customer!A:A,[1]Customer!C:C,"") -> Bobby | C563: {=_xlfn.XLOOKUP($A563,[1]MedicHistory!A:A,[1]MedicHistory!B:B,"")} -> 49.09 | D563: {=_xlfn.XLOOKUP($A563,[1]MedicHistory!A:A,[1]MedicHistory!C:C,"")} -> 8.38 | E563: =_xlfn.XLOOKUP($A563,[1]MedicHistory!A:A,[1]MedicHistory!D:D,"") -> yes | F563: =_xlfn.XLOOKUP($A563,[1]MedicHistory!A:A,[1]MedicHistory!E:E,"") -> No | G563: =_xlfn.XLOOKUP($A563,[1]MedicHistory!A:A,[1]MedicHistory!F:F,"") -> No | H563: =_xlfn.XLOOKUP($A563,[1]MedicHistory!A:A,[1]MedicHistory!G:G,"") -> 2 | I563: =_xlfn.XLOOKUP($A563,[1]MedicHistory!A:A,[1]MedicHistory!H:H,"") -> No | J563: =_xlfn.XLOOKUP($A563,[1]MedicHistory!A:A,[1]MedicHistory!K:K,"") -> Diabetic | K563: =_xlfn.XLOOKUP($A563,[1]MedicHistory!A:A,[1]MedicHistory!I:I,"") -> Obisity | L563: =_xlfn.XLOOKUP($A563,[1]Hospitalisation!A:A,[1]Hospitalisation!C:C,"") -> 17584.72 | M563: =_xlfn.XLOOKUP($A563,[1]Hospitalisation!A:A,[1]Hospitalisation!I:I,"") -> tier - 1 | N563: =_xlfn.XLOOKUP($A563,[1]Hospitalisation!A:A,[1]Hospitalisation!J:J,"") -> tier - 3 | O563: =_xlfn.XLOOKUP($A563,[1]Hospitalisation!A:A,[1]Hospitalisation!K:K,"") -> R1012 | P563: =_xlfn.XLOOKUP($A563,[1]Hospitalisation!A:A,[1]Hospitalisation!L:L,"") -> 32 | Q563: =_xlfn.XLOOKUP($A563,[1]Hospitalisation!A:A,[1]Hospitalisation!M:M,"") -> 33080
A564: Id563 | B564: =_xlfn.XLOOKUP(A564,[1]Customer!A:A,[1]Customer!C:C,"") -> Daniel | C564: {=_xlfn.XLOOKUP($A564,[1]MedicHistory!A:A,[1]MedicHistory!B:B,"")} -> 28.025 | D564: {=_xlfn.XLOOKUP($A564,[1]MedicHistory!A:A,[1]MedicHistory!C:C,"")} -> 7.03 | E564: =_xlfn.XLOOKUP($A564,[1]MedicHistory!A:A,[1]MedicHistory!D:D,"") -> No | F564: =_xlfn.XLOOKUP($A564,[1]MedicHistory!A:A,[1]MedicHistory!E:E,"") -> No | G564: =_xlfn.XLOOKUP($A564,[1]MedicHistory!A:A,[1]MedicHistory!F:F,"") -> No | H564: =_xlfn.XLOOKUP($A564,[1]MedicHistory!A:A,[1]MedicHistory!G:G,"") -> 0 | I564: =_xlfn.XLOOKUP($A564,[1]MedicHistory!A:A,[1]MedicHistory!H:H,"") -> yes | J564: =_xlfn.XLOOKUP($A564,[1]MedicHistory!A:A,[1]MedicHistory!K:K,"") -> Diabetic | K564: =_xlfn.XLOOKUP($A564,[1]MedicHistory!A:A,[1]MedicHistory!I:I,"") -> over weight | L564: =_xlfn.XLOOKUP($A564,[1]Hospitalisation!A:A,[1]Hospitalisation!C:C,"") -> 17560.38 | M564: =_xlfn.XLOOKUP($A564,[1]Hospitalisation!A:A,[1]Hospitalisation!I:I,"") -> tier - 1 | N564: =_xlfn.XLOOKUP($A564,[1]Hospitalisation!A:A,[1]Hospitalisation!J:J,"") -> tier - 1 | O564: =_xlfn.XLOOKUP($A564,[1]Hospitalisation!A:A,[1]Hospitalisation!K:K,"") -> R1012 | P564: =_xlfn.XLOOKUP($A564,[1]Hospitalisation!A:A,[1]Hospitalisation!L:L,"") -> 52 | Q564: =_xlfn.XLOOKUP($A564,[1]Hospitalisation!A:A,[1]Hospitalisation!M:M,"") -> 25805
A565: Id564 | B565: =_xlfn.XLOOKUP(A565,[1]Customer!A:A,[1]Customer!C:C,"") -> Marie | C565: {=_xlfn.XLOOKUP($A565,[1]MedicHistory!A:A,[1]MedicHistory!B:B,"")} -> 43.32 | D565: {=_xlfn.XLOOKUP($A565,[1]MedicHistory!A:A,[1]MedicHistory!C:C,"")} -> 8.75 | E565: =_xlfn.XLOOKUP($A565,[1]MedicHistory!A:A,[1]MedicHistory!D:D,"") -> yes | F565: =_xlfn.XLOOKUP($A565,[1]MedicHistory!A:A,[1]MedicHistory!E:E,"") -> No | G565: =_xlfn.XLOOKUP($A565,[1]MedicHistory!A:A,[1]MedicHistory!F:F,"") -> Yes | H565: =_xlfn.XLOOKUP($A565,[1]MedicHistory!A:A,[1]MedicHistory!G:G,"") -> 1 | I565: =_xlfn.XLOOKUP($A565,[1]MedicHistory!A:A,[1]MedicHistory!H:H,"") -> No | J565: =_xlfn.XLOOKUP($A565,[1]MedicHistory!A:A,[1]MedicHistory!K:K,"") -> Diabetic | K565: =_xlfn.XLOOKUP($A565,[1]MedicHistory!A:A,[1]MedicHistory!I:I,"") -> Obisity | L565: =_xlfn.XLOOKUP($A565,[1]Hospitalisation!A:A,[1]Hospitalisation!C:C,"") -> 17556.88 | M565: =_xlfn.XLOOKUP($A565,[1]Hospitalisation!A:A,[1]Hospitalisation!I:I,"") -> tier - 1 | N565: =_xlfn.XLOOKUP($A565,[1]Hospitalisation!A:A,[1]Hospitalisation!J:J,"") -> tier - 2 | O565: =_xlfn.XLOOKUP($A565,[1]Hospitalisation!A:A,[1]Hospitalisation!K:K,"") -> R1012 | P565: =_xlfn.XLOOKUP($A565,[1]Hospitalisation!A:A,[1]Hospitalisation!L:L,"") -> 20 | Q565: =_xlfn.XLOOKUP($A565,[1]Hospitalisation!A:A,[1]Hospitalisation!M:M,"") -> 37576
A566: Id565 | B566: =_xlfn.XLOOKUP(A566,[1]Customer!A:A,[1]Customer!C:C,"") -> Katie | C566: {=_xlfn.XLOOKUP($A566,[1]MedicHistory!A:A,[1]MedicHistory!B:B,"")} -> 45.92 | D566: {=_xlfn.XLOOKUP($A566,[1]MedicHistory!A:A,[1]MedicHistory!C:C,"")} -> 9.51 | E566: =_xlfn.XLOOKUP($A566,[1]MedicHistory!A:A,[1]MedicHistory!D:D,"") -> No | F566: =_xlfn.XLOOKUP($A566,[1]MedicHistory!A:A,[1]MedicHistory!E:E,"") -> No | G566: =_xlfn.XLOOKUP($A566,[1]MedicHistory!A:A,[1]MedicHistory!F:F,"") -> No | H566: =_xlfn.XLOOKUP($A566,[1]MedicHistory!A:A,[1]MedicHistory!G:G,"") -> 0 | I566: =_xlfn.XLOOKUP($A566,[1]MedicHistory!A:A,[1]MedicHistory!H:H,"") -> No | J566: =_xlfn.XLOOKUP($A566,[1]MedicHistory!A:A,[1]MedicHistory!K:K,"") -> Diabetic | K566: =_xlfn.XLOOKUP($A566,[1]MedicHistory!A:A,[1]MedicHistory!I:I,"") -> Obisity | L566: =_xlfn.XLOOKUP($A566,[1]Hospitalisation!A:A,[1]Hospitalisation!C:C,"") -> 17507.47 | M566: =_xlfn.XLOOKUP($A566,[1]Hospitalisation!A:A,[1]Hospitalisation!I:I,"") -> tier - 1 | N566: =_xlfn.XLOOKUP($A566,[1]Hospitalisation!A:A,[1]Hospitalisation!J:J,"") -> tier - 1 | O566: =_xlfn.XLOOKUP($A566,[1]Hospitalisation!A:A,[1]Hospitalisation!K:K,"") -> R1026 | P566: =_xlfn.XLOOKUP($A566,[1]Hospitalisation!A:A,[1]Hospitalisation!L:L,"") -> 59 | Q566: =_xlfn.XLOOKUP($A566,[1]Hospitalisation!A:A,[1]Hospitalisation!M:M,"") -> 23204
A567: Id566 | B567: =_xlfn.XLOOKUP(A567,[1]Customer!A:A,[1]Customer!C:C,"") -> Eric | C567: {=_xlfn.XLOOKUP($A567,[1]MedicHistory!A:A,[1]MedicHistory!B:B,"")} -> 44.03 | D567: {=_xlfn.XLOOKUP($A567,[1]MedicHistory!A:A,[1]MedicHistory!C:C,"")} -> 9.36 | E567: =_xlfn.XLOOKUP($A567,[1]MedicHistory!A:A,[1]MedicHistory!D:D,"") -> No | F567: =_xlfn.XLOOKUP($A567,[1]MedicHistory!A:A,[1]MedicHistory!E:E,"") -> No | G567: =_xlfn.XLOOKUP($A567,[1]MedicHistory!A:A,[1]MedicHistory!F:F,"") -> No | H567: =_xlfn.XLOOKUP($A567,[1]MedicHistory!A:A,[1]MedicHistory!G:G,"") -> 0 | I567: =_xlfn.XLOOKUP($A567,[1]MedicHistory!A:A,[1]MedicHistory!H:H,"") -> No | J567: =_xlfn.XLOOKUP($A567,[1]MedicHistory!A:A,[1]MedicHistory!K:K,"") -> Diabetic | K567: =_xlfn.XLOOKUP($A567,[1]MedicHistory!A:A,[1]MedicHistory!I:I,"") -> Obisity | L567: =_xlfn.XLOOKUP($A567,[1]Hospitalisation!A:A,[1]Hospitalisation!C:C,"") -> 17505.65 | M567: =_xlfn.XLOOKUP($A567,[1]Hospitalisation!A:A,[1]Hospitalisation!I:I,"") -> tier - 1 | N567: =_xlfn.XLOOKUP($A567,[1]Hospitalisation!A:A,[1]Hospitalisation!J:J,"") -> tier - 2 | O567: =_xlfn.XLOOKUP($A567,[1]Hospitalisation!A:A,[1]Hospitalisation!K:K,"") -> R1023 | P567: =_xlfn.XLOOKUP($A567,[1]Hospitalisation!A:A,[1]Hospitalisation!L:L,"") -> 54 | Q567: =_xlfn.XLOOKUP($A567,[1]Hospitalisation!A:A,[1]Hospitalisation!M:M,"") -> 25005
A568: Id567 | B568: =_xlfn.XLOOKUP(A568,[1]Customer!A:A,[1]Customer!C:C,"") -> Tara | C568: {=_xlfn.XLOOKUP($A568,[1]MedicHistory!A:A,[1]MedicHistory!B:B,"")} -> 24.6 | D568: {=_xlfn.XLOOKUP($A568,[1]MedicHistory!A:A,[1]MedicHistory!C:C,"")} -> 4.81 | E568: =_xlfn.XLOOKUP($A568,[1]MedicHistory!A:A,[1]MedicHistory!D:D,"") -> No | F568: =_xlfn.XLOOKUP($A568,[1]MedicHistory!A:A,[1]MedicHistory!E:E,"") -> No | G568: =_xlfn.XLOOKUP($A568,[1]MedicHistory!A:A,[1]MedicHistory!F:F,"") -> No | H568: =_xlfn.XLOOKUP($A568,[1]MedicHistory!A:A,[1]MedicHistory!G:G,"") -> 0 | I568: =_xlfn.XLOOKUP($A568,[1]MedicHistory!A:A,[1]MedicHistory!H:H,"") -> yes | J568: =_xlfn.XLOOKUP($A568,[1]MedicHistory!A:A,[1]MedicHistory!K:K,"") -> Normal | K568: =_xlfn.XLOOKUP($A568,[1]MedicHistory!A:A,[1]MedicHistory!I:I,"") -> Normal weight | L568: =_xlfn.XLOOKUP($A568,[1]Hospitalisation!A:A,[1]Hospitalisation!C:C,"") -> 17496.31 | M568: =_xlfn.XLOOKUP($A568,[1]Hospitalisation!A:A,[1]Hospitalisation!I:I,"") -> tier - 1 | N568: =_xlfn.XLOOKUP($A568,[1]Hospitalisation!A:A,[1]Hospitalisation!J:J,"") -> tier - 2 | O568: =_xlfn.XLOOKUP($A568,[1]Hospitalisation!A:A,[1]Hospitalisation!K:K,"") -> R1011 | P568: =_xlfn.XLOOKUP($A568,[1]Hospitalisation!A:A,[1]Hospitalisation!L:L,"") -> 57 | Q568: =_xlfn.XLOOKUP($A568,[1]Hospitalisation!A:A,[1]Hospitalisation!M:M,"") -> 24105
A569: Id568 | B569: =_xlfn.XLOOKUP(A569,[1]Customer!A:A,[1]Customer!C:C,"") -> Haley | C569: {=_xlfn.XLOOKUP($A569,[1]MedicHistory!A:A,[1]MedicHistory!B:B,"")} -> 49.15 | D569: {=_xlfn.XLOOKUP($A569,[1]MedicHistory!A:A,[1]MedicHistory!C:C,"")} -> 8.08 | E569: =_xlfn.XLOOKUP($A569,[1]MedicHistory!A:A,[1]MedicHistory!D:D,"") -> No | F569: =_xlfn.XLOOKUP($A569,[1]MedicHistory!A:A,[1]MedicHistory!E:E,"") -> No | G569: =_xlfn.XLOOKUP($A569,[1]MedicHistory!A:A,[1]MedicHistory!F:F,"") -> No | H569: =_xlfn.XLOOKUP($A569,[1]MedicHistory!A:A,[1]MedicHistory!G:G,"") -> 0 | I569: =_xlfn.XLOOKUP($A569,[1]MedicHistory!A:A,[1]MedicHistory!H:H,"") -> No | J569: =_xlfn.XLOOKUP($A569,[1]MedicHistory!A:A,[1]MedicHistory!K:K,"") -> Diabetic | K569: =_xlfn.XLOOKUP($A569,[1]MedicHistory!A:A,[1]MedicHistory!I:I,"") -> Obisity | L569: =_xlfn.XLOOKUP($A569,[1]Hospitalisation!A:A,[1]Hospitalisation!C:C,"") -> 17479.53 | M569: =_xlfn.XLOOKUP($A569,[1]Hospitalisation!A:A,[1]Hospitalisation!I:I,"") -> tier - 1 | N569: =_xlfn.XLOOKUP($A569,[1]Hospitalisation!A:A,[1]Hospitalisation!J:J,"") -> tier - 1 | O569: =_xlfn.XLOOKUP($A569,[1]Hospitalisation!A:A,[1]Hospitalisation!K:K,"") -> R1012 | P569: =_xlfn.XLOOKUP($A569,[1]Hospitalisation!A:A,[1]Hospitalisation!L:L,"") -> 33 | Q569: =_xlfn.XLOOKUP($A569,[1]Hospitalisation!A:A,[1]Hospitalisation!M:M,"") -> 33032
A570: Id569 | B570: =_xlfn.XLOOKUP(A570,[1]Customer!A:A,[1]Customer!C:C,"") -> Kayla | C570: {=_xlfn.XLOOKUP($A570,[1]MedicHistory!A:A,[1]MedicHistory!B:B,"")} -> 28.31 | D570: {=_xlfn.XLOOKUP($A570,[1]MedicHistory!A:A,[1]MedicHistory!C:C,"")} -> 6.29 | E570: =_xlfn.XLOOKUP($A570,[1]MedicHistory!A:A,[1]MedicHistory!D:D,"") -> No | F570: =_xlfn.XLOOKUP($A570,[1]MedicHistory!A:A,[1]MedicHistory!E:E,"") -> No | G570: =_xlfn.XLOOKUP($A570,[1]MedicHistory!A:A,[1]MedicHistory!F:F,"") -> Yes | H570: =_xlfn.XLOOKUP($A570,[1]MedicHistory!A:A,[1]MedicHistory!G:G,"") -> 1 | I570: =_xlfn.XLOOKUP($A570,[1]MedicHistory!A:A,[1]MedicHistory!H:H,"") -> yes | J570: =_xlfn.XLOOKUP($A570,[1]MedicHistory!A:A,[1]MedicHistory!K:K,"") -> Prediabetic | K570: =_xlfn.XLOOKUP($A570,[1]MedicHistory!A:A,[1]MedicHistory!I:I,"") -> over weight | L570: =_xlfn.XLOOKUP($A570,[1]Hospitalisation!A:A,[1]Hospitalisation!C:C,"") -> 17468.98 | M570: =_xlfn.XLOOKUP($A570,[1]Hospitalisation!A:A,[1]Hospitalisation!I:I,"") -> tier - 2 | N570: =_xlfn.XLOOKUP($A570,[1]Hospitalisation!A:A,[1]Hospitalisation!J:J,"") -> tier - 1 | O570: =_xlfn.XLOOKUP($A570,[1]Hospitalisation!A:A,[1]Hospitalisation!K:K,"") -> R1012 | P570: =_xlfn.XLOOKUP($A570,[1]Hospitalisation!A:A,[1]Hospitalisation!L:L,"") -> 51 | Q570: =_xlfn.XLOOKUP($A570,[1]Hospitalisation!A:A,[1]Hospitalisation!M:M,"") -> 26239
A571: Id570 | B571: =_xlfn.XLOOKUP(A571,[1]Customer!A:A,[1]Customer!C:C,"") -> Mark | C571: {=_xlfn.XLOOKUP($A571,[1]MedicHistory!A:A,[1]MedicHistory!B:B,"")} -> 22.99 | D571: {=_xlfn.XLOOKUP($A571,[1]MedicHistory!A:A,[1]MedicHistory!C:C,"")} -> 6.29 | E571: =_xlfn.XLOOKUP($A571,[1]MedicHistory!A:A,[1]MedicHistory!D:D,"") -> No | F571: =_xlfn.XLOOKUP($A571,[1]MedicHistory!A:A,[1]MedicHistory!E:E,"") -> No | G571: =_xlfn.XLOOKUP($A571,[1]MedicHistory!A:A,[1]MedicHistory!F:F,"") -> No | H571: =_xlfn.XLOOKUP($A571,[1]MedicHistory!A:A,[1]MedicHistory!G:G,"") -> 1 | I571: =_xlfn.XLOOKUP($A571,[1]MedicHistory!A:A,[1]MedicHistory!H:H,"") -> yes | J571: =_xlfn.XLOOKUP($A571,[1]MedicHistory!A:A,[1]MedicHistory!K:K,"") -> Prediabetic | K571: =_xlfn.XLOOKUP($A571,[1]MedicHistory!A:A,[1]MedicHistory!I:I,"") -> Normal weight | L571: =_xlfn.XLOOKUP($A571,[1]Hospitalisation!A:A,[1]Hospitalisation!C:C,"") -> 17361.77 | M571: =_xlfn.XLOOKUP($A571,[1]Hospitalisation!A:A,[1]Hospitalisation!I:I,"") -> tier - 2 | N571: =_xlfn.XLOOKUP($A571,[1]Hospitalisation!A:A,[1]Hospitalisation!J:J,"") -> tier - 1 | O571: =_xlfn.XLOOKUP($A571,[1]Hospitalisation!A:A,[1]Hospitalisation!K:K,"") -> R1012 | P571: =_xlfn.XLOOKUP($A571,[1]Hospitalisation!A:A,[1]Hospitalisation!L:L,"") -> 19 | Q571: =_xlfn.XLOOKUP($A571,[1]Hospitalisation!A:A,[1]Hospitalisation!M:M,"") -> 37912
A572: Id571 | B572: =_xlfn.XLOOKUP(A572,[1]Customer!A:A,[1]Customer!C:C,"") -> Patrick | C572: {=_xlfn.XLOOKUP($A572,[1]MedicHistory!A:A,[1]MedicHistory!B:B,"")} -> 29.07 | D572: {=_xlfn.XLOOKUP($A572,[1]MedicHistory!A:A,[1]MedicHistory!C:C,"")} -> 5.12 | E572: =_xlfn.XLOOKUP($A572,[1]MedicHistory!A:A,[1]MedicHistory!D:D,"") -> No | F572: =_xlfn.XLOOKUP($A572,[1]MedicHistory!A:A,[1]MedicHistory!E:E,"") -> No | G572: =_xlfn.XLOOKUP($A572,[1]MedicHistory!A:A,[1]MedicHistory!F:F,"") -> Yes | H572: =_xlfn.XLOOKUP($A572,[1]MedicHistory!A:A,[1]MedicHistory!G:G,"") -> 1 | I572: =_xlfn.XLOOKUP($A572,[1]MedicHistory!A:A,[1]MedicHistory!H:H,"") -> yes | J572: =_xlfn.XLOOKUP($A572,[1]MedicHistory!A:A,[1]MedicHistory!K:K,"") -> Normal | K572: =_xlfn.XLOOKUP($A572,[1]MedicHistory!A:A,[1]MedicHistory!I:I,"") -> over weight | L572: =_xlfn.XLOOKUP($A572,[1]Hospitalisation!A:A,[1]Hospitalisation!C:C,"") -> 17352.68 | M572: =_xlfn.XLOOKUP($A572,[1]Hospitalisation!A:A,[1]Hospitalisation!I:I,"") -> tier - 2 | N572: =_xlfn.XLOOKUP($A572,[1]Hospitalisation!A:A,[1]Hospitalisation!J:J,"") -> tier - 3 | O572: =_xlfn.XLOOKUP($A572,[1]Hospitalisation!A:A,[1]Hospitalisation!K:K,"") -> R1012 | P572: =_xlfn.XLOOKUP($A572,[1]Hospitalisation!A:A,[1]Hospitalisation!L:L,"") -> 30 | Q572: =_xlfn.XLOOKUP($A572,[1]Hospitalisation!A:A,[1]Hospitalisation!M:M,"") -> 33909
A573: Id572 | B573: =_xlfn.XLOOKUP(A573,[1]Customer!A:A,[1]Customer!C:C,"") -> Alejandro | C573: {=_xlfn.XLOOKUP($A573,[1]MedicHistory!A:A,[1]MedicHistory!B:B,"")} -> 42.02 | D573: {=_xlfn.XLOOKUP($A573,[1]MedicHistory!A:A,[1]MedicHistory!C:C,"")} -> 9.95 | E573: =_xlfn.XLOOKUP($A573,[1]MedicHistory!A:A,[1]MedicHistory!D:D,"") -> yes | F573: =_xlfn.XLOOKUP($A573,[1]MedicHistory!A:A,[1]MedicHistory!E:E,"") -> No | G573: =_xlfn.XLOOKUP($A573,[1]MedicHistory!A:A,[1]MedicHistory!F:F,"") -> Yes | H573: =_xlfn.XLOOKUP($A573,[1]MedicHistory!A:A,[1]MedicHistory!G:G,"") -> 1 | I573: =_xlfn.XLOOKUP($A573,[1]MedicHistory!A:A,[1]MedicHistory!H:H,"") -> No | J573: =_xlfn.XLOOKUP($A573,[1]MedicHistory!A:A,[1]MedicHistory!K:K,"") -> Diabetic | K573: =_xlfn.XLOOKUP($A573,[1]MedicHistory!A:A,[1]MedicHistory!I:I,"") -> Obisity | L573: =_xlfn.XLOOKUP($A573,[1]Hospitalisation!A:A,[1]Hospitalisation!C:C,"") -> 17337.58 | M573: =_xlfn.XLOOKUP($A573,[1]Hospitalisation!A:A,[1]Hospitalisation!I:I,"") -> tier - 2 | N573: =_xlfn.XLOOKUP($A573,[1]Hospitalisation!A:A,[1]Hospitalisation!J:J,"") -> tier - 3 | O573: =_xlfn.XLOOKUP($A573,[1]Hospitalisation!A:A,[1]Hospitalisation!K:K,"") -> R1023 | P573: =_xlfn.XLOOKUP($A573,[1]Hospitalisation!A:A,[1]Hospitalisation!L:L,"") -> 19 | Q573: =_xlfn.XLOOKUP($A573,[1]Hospitalisation!A:A,[1]Hospitalisation!M:M,"") -> 37814
... A635: Id634 | B635: =_xlfn.XLOOKUP(A635,[1]Customer!A:A,[1]Customer!C:C,"") -> Maya | C635: {=_xlfn.XLOOKUP($A635,[1]MedicHistory!A:A,[1]MedicHistory!B:B,"")} -> 44.64 | D635: {=_xlfn.XLOOKUP($A635,[1]MedicHistory!A:A,[1]MedicHistory!C:C,"")} -> 7.18 | E635: =_xlfn.XLOOKUP($A635,[1]MedicHistory!A:A,[1]MedicHistory!D:D,"") -> No | F635: =_xlfn.XLOOKUP($A635,[1]MedicHistory!A:A,[1]MedicHistory!E:E,"") -> No | G635: =_xlfn.XLOOKUP($A635,[1]MedicHistory!A:A,[1]MedicHistory!F:F,"") -> No | H635: =_xlfn.XLOOKUP($A635,[1]MedicHistory!A:A,[1]MedicHistory!G:G,"") -> 0 | I635: =_xlfn.XLOOKUP($A635,[1]MedicHistory!A:A,[1]MedicHistory!H:H,"") -> No | J635: =_xlfn.XLOOKUP($A635,[1]MedicHistory!A:A,[1]MedicHistory!K:K,"") -> Diabetic | K635: =_xlfn.XLOOKUP($A635,[1]MedicHistory!A:A,[1]MedicHistory!I:I,"") -> Obisity | L635: =_xlfn.XLOOKUP($A635,[1]Hospitalisation!A:A,[1]Hospitalisation!C:C,"") -> 15532.16 | M635: =_xlfn.XLOOKUP($A635,[1]Hospitalisation!A:A,[1]Hospitalisation!I:I,"") -> tier - 2 | N635: =_xlfn.XLOOKUP($A635,[1]Hospitalisation!A:A,[1]Hospitalisation!J:J,"") -> tier - 2 | O635: =_xlfn.XLOOKUP($A635,[1]Hospitalisation!A:A,[1]Hospitalisation!K:K,"") -> R1026 | P635: =_xlfn.XLOOKUP($A635,[1]Hospitalisation!A:A,[1]Hospitalisation!L:L,"") -> 63 | Q635: =_xlfn.XLOOKUP($A635,[1]Hospitalisation!A:A,[1]Hospitalisation!M:M,"") -> 21729
A636: Id635 | B636: =_xlfn.XLOOKUP(A636,[1]Customer!A:A,[1]Customer!C:C,"") -> Zachary | C636: {=_xlfn.XLOOKUP($A636,[1]MedicHistory!A:A,[1]MedicHistory!B:B,"")} -> 25.175 | D636: {=_xlfn.XLOOKUP($A636,[1]MedicHistory!A:A,[1]MedicHistory!C:C,"")} -> 4.96 | E636: =_xlfn.XLOOKUP($A636,[1]MedicHistory!A:A,[1]MedicHistory!D:D,"") -> No | F636: =_xlfn.XLOOKUP($A636,[1]MedicHistory!A:A,[1]MedicHistory!E:E,"") -> yes | G636: =_xlfn.XLOOKUP($A636,[1]MedicHistory!A:A,[1]MedicHistory!F:F,"") -> No | H636: =_xlfn.XLOOKUP($A636,[1]MedicHistory!A:A,[1]MedicHistory!G:G,"") -> 1 | I636: No | J636: =_xlfn.XLOOKUP($A636,[1]MedicHistory!A:A,[1]MedicHistory!K:K,"") -> Normal | K636: =_xlfn.XLOOKUP($A636,[1]MedicHistory!A:A,[1]MedicHistory!I:I,"") -> over weight | L636: =_xlfn.XLOOKUP($A636,[1]Hospitalisation!A:A,[1]Hospitalisation!C:C,"") -> 15518.18 | M636: =_xlfn.XLOOKUP($A636,[1]Hospitalisation!A:A,[1]Hospitalisation!I:I,"") -> tier - 2 | N636: =_xlfn.XLOOKUP($A636,[1]Hospitalisation!A:A,[1]Hospitalisation!J:J,"") -> tier - 3 | O636: =_xlfn.XLOOKUP($A636,[1]Hospitalisation!A:A,[1]Hospitalisation!K:K,"") -> R1015 | P636: =_xlfn.XLOOKUP($A636,[1]Hospitalisation!A:A,[1]Hospitalisation!L:L,"") -> 48 | Q636: =_xlfn.XLOOKUP($A636,[1]Hospitalisation!A:A,[1]Hospitalisation!M:M,"") -> 27227
A637: Id636 | B637: =_xlfn.XLOOKUP(A637,[1]Customer!A:A,[1]Customer!C:C,"") -> Hilda | C637: {=_xlfn.XLOOKUP($A637,[1]MedicHistory!A:A,[1]MedicHistory!B:B,"")} -> 43.11 | D637: {=_xlfn.XLOOKUP($A637,[1]MedicHistory!A:A,[1]MedicHistory!C:C,"")} -> 4.67 | E637: =_xlfn.XLOOKUP($A637,[1]MedicHistory!A:A,[1]MedicHistory!D:D,"") -> yes | F637: =_xlfn.XLOOKUP($A637,[1]MedicHistory!A:A,[1]MedicHistory!E:E,"") -> No | G637: =_xlfn.XLOOKUP($A637,[1]MedicHistory!A:A,[1]MedicHistory!F:F,"") -> No | H637: =_xlfn.XLOOKUP($A637,[1]MedicHistory!A:A,[1]MedicHistory!G:G,"") -> 0 | I637: =_xlfn.XLOOKUP($A637,[1]MedicHistory!A:A,[1]MedicHistory!H:H,"") -> No | J637: =_xlfn.XLOOKUP($A637,[1]MedicHistory!A:A,[1]MedicHistory!K:K,"") -> Normal | K637: =_xlfn.XLOOKUP($A637,[1]MedicHistory!A:A,[1]MedicHistory!I:I,"") -> Obisity | L637: =_xlfn.XLOOKUP($A637,[1]Hospitalisation!A:A,[1]Hospitalisation!C:C,"") -> 15450.48 | M637: =_xlfn.XLOOKUP($A637,[1]Hospitalisation!A:A,[1]Hospitalisation!I:I,"") -> tier - 2 | N637: =_xlfn.XLOOKUP($A637,[1]Hospitalisation!A:A,[1]Hospitalisation!J:J,"") -> tier - 1 | O637: =_xlfn.XLOOKUP($A637,[1]Hospitalisation!A:A,[1]Hospitalisation!K:K,"") -> R1026 | P637: =_xlfn.XLOOKUP($A637,[1]Hospitalisation!A:A,[1]Hospitalisation!L:L,"") -> 18 | Q637: =_xlfn.XLOOKUP($A637,[1]Hospitalisation!A:A,[1]Hospitalisation!M:M,"") -> 38188
A638: Id637 | B638: =_xlfn.XLOOKUP(A638,[1]Customer!A:A,[1]Customer!C:C,"") -> Stephanie | C638: {=_xlfn.XLOOKUP($A638,[1]MedicHistory!A:A,[1]MedicHistory!B:B,"")} -> 53.32 | D638: {=_xlfn.XLOOKUP($A638,[1]MedicHistory!A:A,[1]MedicHistory!C:C,"")} -> 5.06 | E638: =_xlfn.XLOOKUP($A638,[1]MedicHistory!A:A,[1]MedicHistory!D:D,"") -> No | F638: =_xlfn.XLOOKUP($A638,[1]MedicHistory!A:A,[1]MedicHistory!E:E,"") -> No | G638: =_xlfn.XLOOKUP($A638,[1]MedicHistory!A:A,[1]MedicHistory!F:F,"") -> No | H638: =_xlfn.XLOOKUP($A638,[1]MedicHistory!A:A,[1]MedicHistory!G:G,"") -> 0 | I638: =_xlfn.XLOOKUP($A638,[1]MedicHistory!A:A,[1]MedicHistory!H:H,"") -> No | J638: =_xlfn.XLOOKUP($A638,[1]MedicHistory!A:A,[1]MedicHistory!K:K,"") -> Normal | K638: =_xlfn.XLOOKUP($A638,[1]MedicHistory!A:A,[1]MedicHistory!I:I,"") -> Obisity | L638: =_xlfn.XLOOKUP($A638,[1]Hospitalisation!A:A,[1]Hospitalisation!C:C,"") -> 15440.2 | M638: =_xlfn.XLOOKUP($A638,[1]Hospitalisation!A:A,[1]Hospitalisation!I:I,"") -> tier - 2 | N638: =_xlfn.XLOOKUP($A638,[1]Hospitalisation!A:A,[1]Hospitalisation!J:J,"") -> tier - 1 | O638: =_xlfn.XLOOKUP($A638,[1]Hospitalisation!A:A,[1]Hospitalisation!K:K,"") -> R1012 | P638: =_xlfn.XLOOKUP($A638,[1]Hospitalisation!A:A,[1]Hospitalisation!L:L,"") -> 46 | Q638: =_xlfn.XLOOKUP($A638,[1]Hospitalisation!A:A,[1]Hospitalisation!M:M,"") -> 28058
A639: Id638 | B639: =_xlfn.XLOOKUP(A639,[1]Customer!A:A,[1]Customer!C:C,"") -> Doug | C639: {=_xlfn.XLOOKUP($A639,[1]MedicHistory!A:A,[1]MedicHistory!B:B,"")} -> 38.04 | D639: {=_xlfn.XLOOKUP($A639,[1]MedicHistory!A:A,[1]MedicHistory!C:C,"")} -> 5.02 | E639: =_xlfn.XLOOKUP($A639,[1]MedicHistory!A:A,[1]MedicHistory!D:D,"") -> yes | F639: =_xlfn.XLOOKUP($A639,[1]MedicHistory!A:A,[1]MedicHistory!E:E,"") -> No | G639: =_xlfn.XLOOKUP($A639,[1]MedicHistory!A:A,[1]MedicHistory!F:F,"") -> No | H639: =_xlfn.XLOOKUP($A639,[1]MedicHistory!A:A,[1]MedicHistory!G:G,"") -> 1 | I639: =_xlfn.XLOOKUP($A639,[1]MedicHistory!A:A,[1]MedicHistory!H:H,"") -> No | J639: =_xlfn.XLOOKUP($A639,[1]MedicHistory!A:A,[1]MedicHistory!K:K,"") -> Normal | K639: =_xlfn.XLOOKUP($A639,[1]MedicHistory!A:A,[1]MedicHistory!I:I,"") -> Obisity | L639: =_xlfn.XLOOKUP($A639,[1]Hospitalisation!A:A,[1]Hospitalisation!C:C,"") -> 15377.77 | M639: =_xlfn.XLOOKUP($A639,[1]Hospitalisation!A:A,[1]Hospitalisation!I:I,"") -> tier - 2 | N639: =_xlfn.XLOOKUP($A639,[1]Hospitalisation!A:A,[1]Hospitalisation!J:J,"") -> tier - 2 | O639: =_xlfn.XLOOKUP($A639,[1]Hospitalisation!A:A,[1]Hospitalisation!K:K,"") -> R1012 | P639: =_xlfn.XLOOKUP($A639,[1]Hospitalisation!A:A,[1]Hospitalisation!L:L,"") -> 32 | Q639: =_xlfn.XLOOKUP($A639,[1]Hospitalisation!A:A,[1]Hospitalisation!M:M,"") -> 33120
A640: Id639 | B640: =_xlfn.XLOOKUP(A640,[1]Customer!A:A,[1]Customer!C:C,"") -> Bethany | C640: {=_xlfn.XLOOKUP($A640,[1]MedicHistory!A:A,[1]MedicHistory!B:B,"")} -> 37.9 | D640: {=_xlfn.XLOOKUP($A640,[1]MedicHistory!A:A,[1]MedicHistory!C:C,"")} -> 7.76 | E640: =_xlfn.XLOOKUP($A640,[1]MedicHistory!A:A,[1]MedicHistory!D:D,"") -> No | F640: =_xlfn.XLOOKUP($A640,[1]MedicHistory!A:A,[1]MedicHistory!E:E,"") -> No | G640: =_xlfn.XLOOKUP($A640,[1]MedicHistory!A:A,[1]MedicHistory!F:F,"") -> No | H640: =_xlfn.XLOOKUP($A640,[1]MedicHistory!A:A,[1]MedicHistory!G:G,"") -> 0 | I640: =_xlfn.XLOOKUP($A640,[1]MedicHistory!A:A,[1]MedicHistory!H:H,"") -> No | J640: =_xlfn.XLOOKUP($A640,[1]MedicHistory!A:A,[1]MedicHistory!K:K,"") -> Diabetic | K640: =_xlfn.XLOOKUP($A640,[1]MedicHistory!A:A,[1]MedicHistory!I:I,"") -> Obisity | L640: =_xlfn.XLOOKUP($A640,[1]Hospitalisation!A:A,[1]Hospitalisation!C:C,"") -> 15368.22 | M640: =_xlfn.XLOOKUP($A640,[1]Hospitalisation!A:A,[1]Hospitalisation!I:I,"") -> tier - 2 | N640: =_xlfn.XLOOKUP($A640,[1]Hospitalisation!A:A,[1]Hospitalisation!J:J,"") -> tier - 2 | O640: =_xlfn.XLOOKUP($A640,[1]Hospitalisation!A:A,[1]Hospitalisation!K:K,"") -> R1011 | P640: =_xlfn.XLOOKUP($A640,[1]Hospitalisation!A:A,[1]Hospitalisation!L:L,"") -> 58 | Q640: =_xlfn.XLOOKUP($A640,[1]Hospitalisation!A:A,[1]Hospitalisation!M:M,"") -> 23626
A641: Id640 | B641: =_xlfn.XLOOKUP(A641,[1]Customer!A:A,[1]Customer!C:C,"") -> Sandra | C641: {=_xlfn.XLOOKUP($A641,[1]MedicHistory!A:A,[1]MedicHistory!B:B,"")} -> 39.6 | D641: {=_xlfn.XLOOKUP($A641,[1]MedicHistory!A:A,[1]MedicHistory!C:C,"")} -> 9.32 | E641: =_xlfn.XLOOKUP($A641,[1]MedicHistory!A:A,[1]MedicHistory!D:D,"") -> No | F641: =_xlfn.XLOOKUP($A641,[1]MedicHistory!A:A,[1]MedicHistory!E:E,"") -> No | G641: =_xlfn.XLOOKUP($A641,[1]MedicHistory!A:A,[1]MedicHistory!F:F,"") -> No | H641: =_xlfn.XLOOKUP($A641,[1]MedicHistory!A:A,[1]MedicHistory!G:G,"") -> 0 | I641: =_xlfn.XLOOKUP($A641,[1]MedicHistory!A:A,[1]MedicHistory!H:H,"") -> No | J641: =_xlfn.XLOOKUP($A641,[1]MedicHistory!A:A,[1]MedicHistory!K:K,"") -> Diabetic | K641: =_xlfn.XLOOKUP($A641,[1]MedicHistory!A:A,[1]MedicHistory!I:I,"") -> Obisity | L641: =_xlfn.XLOOKUP($A641,[1]Hospitalisation!A:A,[1]Hospitalisation!C:C,"") -> 15363.77 | M641: =_xlfn.XLOOKUP($A641,[1]Hospitalisation!A:A,[1]Hospitalisation!I:I,"") -> tier - 2 | N641: =_xlfn.XLOOKUP($A641,[1]Hospitalisation!A:A,[1]Hospitalisation!J:J,"") -> tier - 1 | O641: =_xlfn.XLOOKUP($A641,[1]Hospitalisation!A:A,[1]Hospitalisation!K:K,"") -> R1026 | P641: =_xlfn.XLOOKUP($A641,[1]Hospitalisation!A:A,[1]Hospitalisation!L:L,"") -> 60 | Q641: =_xlfn.XLOOKUP($A641,[1]Hospitalisation!A:A,[1]Hospitalisation!M:M,"") -> 22845
A642: Id641 | B642: =_xlfn.XLOOKUP(A642,[1]Customer!A:A,[1]Customer!C:C,"") -> Takuo | C642: {=_xlfn.XLOOKUP($A642,[1]MedicHistory!A:A,[1]MedicHistory!B:B,"")} -> 50.92 | D642: {=_xlfn.XLOOKUP($A642,[1]MedicHistory!A:A,[1]MedicHistory!C:C,"")} -> 5.31 | E642: =_xlfn.XLOOKUP($A642,[1]MedicHistory!A:A,[1]MedicHistory!D:D,"") -> yes | F642: =_xlfn.XLOOKUP($A642,[1]MedicHistory!A:A,[1]MedicHistory!E:E,"") -> No | G642: =_xlfn.XLOOKUP($A642,[1]MedicHistory!A:A,[1]MedicHistory!F:F,"") -> No | H642: =_xlfn.XLOOKUP($A642,[1]MedicHistory!A:A,[1]MedicHistory!G:G,"") -> 1 | I642: =_xlfn.XLOOKUP($A642,[1]MedicHistory!A:A,[1]MedicHistory!H:H,"") -> No | J642: =_xlfn.XLOOKUP($A642,[1]MedicHistory!A:A,[1]MedicHistory!K:K,"") -> Normal | K642: =_xlfn.XLOOKUP($A642,[1]MedicHistory!A:A,[1]MedicHistory!I:I,"") -> Obisity | L642: =_xlfn.XLOOKUP($A642,[1]Hospitalisation!A:A,[1]Hospitalisation!C:C,"") -> 15361.5 | M642: =_xlfn.XLOOKUP($A642,[1]Hospitalisation!A:A,[1]Hospitalisation!I:I,"") -> tier - 2 | N642: =_xlfn.XLOOKUP($A642,[1]Hospitalisation!A:A,[1]Hospitalisation!J:J,"") -> tier - 3 | O642: =_xlfn.XLOOKUP($A642,[1]Hospitalisation!A:A,[1]Hospitalisation!K:K,"") -> R1023 | P642: =_xlfn.XLOOKUP($A642,[1]Hospitalisation!A:A,[1]Hospitalisation!L:L,"") -> 54 | Q642: =_xlfn.XLOOKUP($A642,[1]Hospitalisation!A:A,[1]Hospitalisation!M:M,"") -> 25189
A643: Id642 | B643: =_xlfn.XLOOKUP(A643,[1]Customer!A:A,[1]Customer!C:C,"") -> Kelly | C643: {=_xlfn.XLOOKUP($A643,[1]MedicHistory!A:A,[1]MedicHistory!B:B,"")} -> 21.85 | D643: {=_xlfn.XLOOKUP($A643,[1]MedicHistory!A:A,[1]MedicHistory!C:C,"")} -> 5.56 | E643: =_xlfn.XLOOKUP($A643,[1]MedicHistory!A:A,[1]MedicHistory!D:D,"") -> yes | F643: =_xlfn.XLOOKUP($A643,[1]MedicHistory!A:A,[1]MedicHistory!E:E,"") -> No | G643: =_xlfn.XLOOKUP($A643,[1]MedicHistory!A:A,[1]MedicHistory!F:F,"") -> No | H643: =_xlfn.XLOOKUP($A643,[1]MedicHistory!A:A,[1]MedicHistory!G:G,"") -> 0 | I643: =_xlfn.XLOOKUP($A643,[1]MedicHistory!A:A,[1]MedicHistory!H:H,"") -> yes | J643: =_xlfn.XLOOKUP($A643,[1]MedicHistory!A:A,[1]MedicHistory!K:K,"") -> Normal | K643: =_xlfn.XLOOKUP($A643,[1]MedicHistory!A:A,[1]MedicHistory!I:I,"") -> Normal weight | L643: =_xlfn.XLOOKUP($A643,[1]Hospitalisation!A:A,[1]Hospitalisation!C:C,"") -> 15359.1 | M643: =_xlfn.XLOOKUP($A643,[1]Hospitalisation!A:A,[1]Hospitalisation!I:I,"") -> tier - 2 | N643: =_xlfn.XLOOKUP($A643,[1]Hospitalisation!A:A,[1]Hospitalisation!J:J,"") -> tier - 3 | O643: =_xlfn.XLOOKUP($A643,[1]Hospitalisation!A:A,[1]Hospitalisation!K:K,"") -> R1024 | P643: =_xlfn.XLOOKUP($A643,[1]Hospitalisation!A:A,[1]Hospitalisation!L:L,"") -> 34 | Q643: =_xlfn.XLOOKUP($A643,[1]Hospitalisation!A:A,[1]Hospitalisation!M:M,"") -> 32338
A644: Id643 | B644: =_xlfn.XLOOKUP(A644,[1]Customer!A:A,[1]Customer!C:C,"") -> Scott | C644: {=_xlfn.XLOOKUP($A644,[1]MedicHistory!A:A,[1]MedicHistory!B:B,"")} -> 36.08 | D644: {=_xlfn.XLOOKUP($A644,[1]MedicHistory!A:A,[1]MedicHistory!C:C,"")} -> 7.11 | E644: =_xlfn.XLOOKUP($A644,[1]MedicHistory!A:A,[1]MedicHistory!D:D,"") -> yes | F644: =_xlfn.XLOOKUP($A644,[1]MedicHistory!A:A,[1]MedicHistory!E:E,"") -> No | G644: =_xlfn.XLOOKUP($A644,[1]MedicHistory!A:A,[1]MedicHistory!F:F,"") -> Yes | H644: =_xlfn.XLOOKUP($A644,[1]MedicHistory!A:A,[1]MedicHistory!G:G,"") -> 1 | I644: =_xlfn.XLOOKUP($A644,[1]MedicHistory!A:A,[1]MedicHistory!H:H,"") -> No | J644: =_xlfn.XLOOKUP($A644,[1]MedicHistory!A:A,[1]MedicHistory!K:K,"") -> Diabetic | K644: =_xlfn.XLOOKUP($A644,[1]MedicHistory!A:A,[1]MedicHistory!I:I,"") -> Obisity | L644: =_xlfn.XLOOKUP($A644,[1]Hospitalisation!A:A,[1]Hospitalisation!C:C,"") -> 15322.77 | M644: =_xlfn.XLOOKUP($A644,[1]Hospitalisation!A:A,[1]Hospitalisation!I:I,"") -> tier - 2 | N644: =_xlfn.XLOOKUP($A644,[1]Hospitalisation!A:A,[1]Hospitalisation!J:J,"") -> tier - 3 | O644: =_xlfn.XLOOKUP($A644,[1]Hospitalisation!A:A,[1]Hospitalisation!K:K,"") -> R1021 | P644: =_xlfn.XLOOKUP($A644,[1]Hospitalisation!A:A,[1]Hospitalisation!L:L,"") -> 21 | Q644: =_xlfn.XLOOKUP($A644,[1]Hospitalisation!A:A,[1]Hospitalisation!M:M,"") -> 37238
A645: Id644 | B645: =_xlfn.XLOOKUP(A645,[1]Customer!A:A,[1]Customer!C:C,"") -> Benoit | C645: {=_xlfn.XLOOKUP($A645,[1]MedicHistory!A:A,[1]MedicHistory!B:B,"")} -> 40.44 | D645: {=_xlfn.XLOOKUP($A645,[1]MedicHistory!A:A,[1]MedicHistory!C:C,"")} -> 5.13 | E645: =_xlfn.XLOOKUP($A645,[1]MedicHistory!A:A,[1]MedicHistory!D:D,"") -> yes | F645: =_xlfn.XLOOKUP($A645,[1]MedicHistory!A:A,[1]MedicHistory!E:E,"") -> No | G645: =_xlfn.XLOOKUP($A645,[1]MedicHistory!A:A,[1]MedicHistory!F:F,"") -> Yes | H645: =_xlfn.XLOOKUP($A645,[1]MedicHistory!A:A,[1]MedicHistory!G:G,"") -> 1 | I645: =_xlfn.XLOOKUP($A645,[1]MedicHistory!A:A,[1]MedicHistory!H:H,"") -> No | J645: =_xlfn.XLOOKUP($A645,[1]MedicHistory!A:A,[1]MedicHistory!K:K,"") -> Normal | K645: =_xlfn.XLOOKUP($A645,[1]MedicHistory!A:A,[1]MedicHistory!I:I,"") -> Obisity | L645: =_xlfn.XLOOKUP($A645,[1]Hospitalisation!A:A,[1]Hospitalisation!C:C,"") -> 15260.52 | M645: =_xlfn.XLOOKUP($A645,[1]Hospitalisation!A:A,[1]Hospitalisation!I:I,"") -> tier - 2 | N645: =_xlfn.XLOOKUP($A645,[1]Hospitalisation!A:A,[1]Hospitalisation!J:J,"") -> tier - 2 | O645: =_xlfn.XLOOKUP($A645,[1]Hospitalisation!A:A,[1]Hospitalisation!K:K,"") -> R1023 | P645: =_xlfn.XLOOKUP($A645,[1]Hospitalisation!A:A,[1]Hospitalisation!L:L,"") -> 59 | Q645: =_xlfn.XLOOKUP($A645,[1]Hospitalisation!A:A,[1]Hospitalisation!M:M,"") -> 23270
A646: Id645 | B646: =_xlfn.XLOOKUP(A646,[1]Customer!A:A,[1]Customer!C:C,"") -> Elizabeth | C646: {=_xlfn.XLOOKUP($A646,[1]MedicHistory!A:A,[1]MedicHistory!B:B,"")} -> 38.095 | D646: {=_xlfn.XLOOKUP($A646,[1]MedicHistory!A:A,[1]MedicHistory!C:C,"")} -> 10.2 | E646: =_xlfn.XLOOKUP($A646,[1]MedicHistory!A:A,[1]MedicHistory!D:D,"") -> No | F646: =_xlfn.XLOOKUP($A646,[1]MedicHistory!A:A,[1]MedicHistory!E:E,"") -> No | G646: =_xlfn.XLOOKUP($A646,[1]MedicHistory!A:A,[1]MedicHistory!F:F,"") -> No | H646: =_xlfn.XLOOKUP($A646,[1]MedicHistory!A:A,[1]MedicHistory!G:G,"") -> 0 | I646: =_xlfn.XLOOKUP($A646,[1]MedicHistory!A:A,[1]MedicHistory!H:H,"") -> No | J646: =_xlfn.XLOOKUP($A646,[1]MedicHistory!A:A,[1]MedicHistory!K:K,"") -> Diabetic | K646: =_xlfn.XLOOKUP($A646,[1]MedicHistory!A:A,[1]MedicHistory!I:I,"") -> Obisity | L646: =_xlfn.XLOOKUP($A646,[1]Hospitalisation!A:A,[1]Hospitalisation!C:C,"") -> 15230.32 | M646: =_xlfn.XLOOKUP($A646,[1]Hospitalisation!A:A,[1]Hospitalisation!I:I,"") -> tier - 2 | N646: =_xlfn.XLOOKUP($A646,[1]Hospitalisation!A:A,[1]Hospitalisation!J:J,"") -> tier - 2 | O646: =_xlfn.XLOOKUP($A646,[1]Hospitalisation!A:A,[1]Hospitalisation!K:K,"") -> R1024 | P646: =_xlfn.XLOOKUP($A646,[1]Hospitalisation!A:A,[1]Hospitalisation!L:L,"") -> 53 | Q646: =_xlfn.XLOOKUP($A646,[1]Hospitalisation!A:A,[1]Hospitalisation!M:M,"") -> 25409
A647: Id646 | B647: =_xlfn.XLOOKUP(A647,[1]Customer!A:A,[1]Customer!C:C,"") -> Jessica | C647: {=_xlfn.XLOOKUP($A647,[1]MedicHistory!A:A,[1]MedicHistory!B:B,"")} -> 44.95 | D647: {=_xlfn.XLOOKUP($A647,[1]MedicHistory!A:A,[1]MedicHistory!C:C,"")} -> 10.4 | E647: =_xlfn.XLOOKUP($A647,[1]MedicHistory!A:A,[1]MedicHistory!D:D,"") -> No | F647: =_xlfn.XLOOKUP($A647,[1]MedicHistory!A:A,[1]MedicHistory!E:E,"") -> No | G647: =_xlfn.XLOOKUP($A647,[1]MedicHistory!A:A,[1]MedicHistory!F:F,"") -> No | H647: =_xlfn.XLOOKUP($A647,[1]MedicHistory!A:A,[1]MedicHistory!G:G,"") -> 0 | I647: =_xlfn.XLOOKUP($A647,[1]MedicHistory!A:A,[1]MedicHistory!H:H,"") -> No | J647: =_xlfn.XLOOKUP($A647,[1]MedicHistory!A:A,[1]MedicHistory!K:K,"") -> Diabetic | K647: =_xlfn.XLOOKUP($A647,[1]MedicHistory!A:A,[1]MedicHistory!I:I,"") -> Obisity | L647: =_xlfn.XLOOKUP($A647,[1]Hospitalisation!A:A,[1]Hospitalisation!C:C,"") -> 15207.92 | M647: =_xlfn.XLOOKUP($A647,[1]Hospitalisation!A:A,[1]Hospitalisation!I:I,"") -> tier - 2 | N647: =_xlfn.XLOOKUP($A647,[1]Hospitalisation!A:A,[1]Hospitalisation!J:J,"") -> tier - 1 | O647: =_xlfn.XLOOKUP($A647,[1]Hospitalisation!A:A,[1]Hospitalisation!K:K,"") -> R1012 | P647: =_xlfn.XLOOKUP($A647,[1]Hospitalisation!A:A,[1]Hospitalisation!L:L,"") -> 62 | Q647: =_xlfn.XLOOKUP($A647,[1]Hospitalisation!A:A,[1]Hospitalisation!M:M,"") -> 22243
A648: Id647 | B648: =_xlfn.XLOOKUP(A648,[1]Customer!A:A,[1]Customer!C:C,"") -> Monica | C648: {=_xlfn.XLOOKUP($A648,[1]MedicHistory!A:A,[1]MedicHistory!B:B,"")} -> 35.54 | D648: {=_xlfn.XLOOKUP($A648,[1]MedicHistory!A:A,[1]MedicHistory!C:C,"")} -> 10.67 | E648: =_xlfn.XLOOKUP($A648,[1]MedicHistory!A:A,[1]MedicHistory!D:D,"") -> No | F648: =_xlfn.XLOOKUP($A648,[1]MedicHistory!A:A,[1]MedicHistory!E:E,"") -> No | G648: =_xlfn.XLOOKUP($A648,[1]MedicHistory!A:A,[1]MedicHistory!F:F,"") -> No | H648: =_xlfn.XLOOKUP($A648,[1]MedicHistory!A:A,[1]MedicHistory!G:G,"") -> 0 | I648: =_xlfn.XLOOKUP($A648,[1]MedicHistory!A:A,[1]MedicHistory!H:H,"") -> No | J648: =_xlfn.XLOOKUP($A648,[1]MedicHistory!A:A,[1]MedicHistory!K:K,"") -> Diabetic | K648: =_xlfn.XLOOKUP($A648,[1]MedicHistory!A:A,[1]MedicHistory!I:I,"") -> Obisity | L648: =_xlfn.XLOOKUP($A648,[1]Hospitalisation!A:A,[1]Hospitalisation!C:C,"") -> 15174.81 | M648: =_xlfn.XLOOKUP($A648,[1]Hospitalisation!A:A,[1]Hospitalisation!I:I,"") -> tier - 2 | N648: =_xlfn.XLOOKUP($A648,[1]Hospitalisation!A:A,[1]Hospitalisation!J:J,"") -> tier - 1 | O648: =_xlfn.XLOOKUP($A648,[1]Hospitalisation!A:A,[1]Hospitalisation!K:K,"") -> R1012 | P648: =_xlfn.XLOOKUP($A648,[1]Hospitalisation!A:A,[1]Hospitalisation!L:L,"") -> 44 | Q648: =_xlfn.XLOOKUP($A648,[1]Hospitalisation!A:A,[1]Hospitalisation!M:M,"") -> 28658
... A2259: Id2258 | B2259: =_xlfn.XLOOKUP(A2259,[1]Customer!A:A,[1]Customer!C:C,"") -> Blue | C2259: {=_xlfn.XLOOKUP($A2259,[1]MedicHistory!A:A,[1]MedicHistory!B:B,"")} -> 34.1 | D2259: {=_xlfn.XLOOKUP($A2259,[1]MedicHistory!A:A,[1]MedicHistory!C:C,"")} -> 4.13 | E2259: =_xlfn.XLOOKUP($A2259,[1]MedicHistory!A:A,[1]MedicHistory!D:D,"") -> No | F2259: =_xlfn.XLOOKUP($A2259,[1]MedicHistory!A:A,[1]MedicHistory!E:E,"") -> No | G2259: =_xlfn.XLOOKUP($A2259,[1]MedicHistory!A:A,[1]MedicHistory!F:F,"") -> Yes | H2259: =_xlfn.XLOOKUP($A2259,[1]MedicHistory!A:A,[1]MedicHistory!G:G,"") -> 1 | I2259: =_xlfn.XLOOKUP($A2259,[1]MedicHistory!A:A,[1]MedicHistory!H:H,"") -> No | J2259: =_xlfn.XLOOKUP($A2259,[1]MedicHistory!A:A,[1]MedicHistory!K:K,"") -> Normal | K2259: =_xlfn.XLOOKUP($A2259,[1]MedicHistory!A:A,[1]MedicHistory!I:I,"") -> Obisity | L2259: =_xlfn.XLOOKUP($A2259,[1]Hospitalisation!A:A,[1]Hospitalisation!C:C,"") -> 1261.44 | M2259: =_xlfn.XLOOKUP($A2259,[1]Hospitalisation!A:A,[1]Hospitalisation!I:I,"") -> tier - 2 | N2259: =_xlfn.XLOOKUP($A2259,[1]Hospitalisation!A:A,[1]Hospitalisation!J:J,"") -> tier - 3 | O2259: =_xlfn.XLOOKUP($A2259,[1]Hospitalisation!A:A,[1]Hospitalisation!K:K,"") -> R1011 | P2259: =_xlfn.XLOOKUP($A2259,[1]Hospitalisation!A:A,[1]Hospitalisation!L:L,"") -> 19 | Q2259: =_xlfn.XLOOKUP($A2259,[1]Hospitalisation!A:A,[1]Hospitalisation!M:M,"") -> 37924
A2260: Id2259 | B2260: =_xlfn.XLOOKUP(A2260,[1]Customer!A:A,[1]Customer!C:C,"") -> Jeffrey | C2260: {=_xlfn.XLOOKUP($A2260,[1]MedicHistory!A:A,[1]MedicHistory!B:B,"")} -> 30.4 | D2260: {=_xlfn.XLOOKUP($A2260,[1]MedicHistory!A:A,[1]MedicHistory!C:C,"")} -> 4.77 | E2260: =_xlfn.XLOOKUP($A2260,[1]MedicHistory!A:A,[1]MedicHistory!D:D,"") -> No | F2260: =_xlfn.XLOOKUP($A2260,[1]MedicHistory!A:A,[1]MedicHistory!E:E,"") -> No | G2260: =_xlfn.XLOOKUP($A2260,[1]MedicHistory!A:A,[1]MedicHistory!F:F,"") -> Yes | H2260: =_xlfn.XLOOKUP($A2260,[1]MedicHistory!A:A,[1]MedicHistory!G:G,"") -> 1 | I2260: yes | J2260: =_xlfn.XLOOKUP($A2260,[1]MedicHistory!A:A,[1]MedicHistory!K:K,"") -> Normal | K2260: =_xlfn.XLOOKUP($A2260,[1]MedicHistory!A:A,[1]MedicHistory!I:I,"") -> Obisity | L2260: =_xlfn.XLOOKUP($A2260,[1]Hospitalisation!A:A,[1]Hospitalisation!C:C,"") -> 1256.3 | M2260: =_xlfn.XLOOKUP($A2260,[1]Hospitalisation!A:A,[1]Hospitalisation!I:I,"") -> tier - 2 | N2260: =_xlfn.XLOOKUP($A2260,[1]Hospitalisation!A:A,[1]Hospitalisation!J:J,"") -> tier - 3 | O2260: =_xlfn.XLOOKUP($A2260,[1]Hospitalisation!A:A,[1]Hospitalisation!K:K,"") -> R1011 | P2260: =_xlfn.XLOOKUP($A2260,[1]Hospitalisation!A:A,[1]Hospitalisation!L:L,"") -> 19 | Q2260: =_xlfn.XLOOKUP($A2260,[1]Hospitalisation!A:A,[1]Hospitalisation!M:M,"") -> 37907
A2261: Id2260 | B2261: =_xlfn.XLOOKUP(A2261,[1]Customer!A:A,[1]Customer!C:C,"") -> Andrew | C2261: {=_xlfn.XLOOKUP($A2261,[1]MedicHistory!A:A,[1]MedicHistory!B:B,"")} -> 28.7 | D2261: {=_xlfn.XLOOKUP($A2261,[1]MedicHistory!A:A,[1]MedicHistory!C:C,"")} -> 4.99 | E2261: =_xlfn.XLOOKUP($A2261,[1]MedicHistory!A:A,[1]MedicHistory!D:D,"") -> No | F2261: =_xlfn.XLOOKUP($A2261,[1]MedicHistory!A:A,[1]MedicHistory!E:E,"") -> No | G2261: =_xlfn.XLOOKUP($A2261,[1]MedicHistory!A:A,[1]MedicHistory!F:F,"") -> Yes | H2261: =_xlfn.XLOOKUP($A2261,[1]MedicHistory!A:A,[1]MedicHistory!G:G,"") -> 1 | I2261: yes | J2261: =_xlfn.XLOOKUP($A2261,[1]MedicHistory!A:A,[1]MedicHistory!K:K,"") -> Normal | K2261: =_xlfn.XLOOKUP($A2261,[1]MedicHistory!A:A,[1]MedicHistory!I:I,"") -> over weight | L2261: =_xlfn.XLOOKUP($A2261,[1]Hospitalisation!A:A,[1]Hospitalisation!C:C,"") -> 1253.94 | M2261: =_xlfn.XLOOKUP($A2261,[1]Hospitalisation!A:A,[1]Hospitalisation!I:I,"") -> tier - 2 | N2261: =_xlfn.XLOOKUP($A2261,[1]Hospitalisation!A:A,[1]Hospitalisation!J:J,"") -> tier - 2 | O2261: =_xlfn.XLOOKUP($A2261,[1]Hospitalisation!A:A,[1]Hospitalisation!K:K,"") -> R1011 | P2261: =_xlfn.XLOOKUP($A2261,[1]Hospitalisation!A:A,[1]Hospitalisation!L:L,"") -> 19 | Q2261: =_xlfn.XLOOKUP($A2261,[1]Hospitalisation!A:A,[1]Hospitalisation!M:M,"") -> 37965
A2262: Id2261 | B2262: =_xlfn.XLOOKUP(A2262,[1]Customer!A:A,[1]Customer!C:C,"") -> Julia | C2262: {=_xlfn.XLOOKUP($A2262,[1]MedicHistory!A:A,[1]MedicHistory!B:B,"")} -> 17.44 | D2262: {=_xlfn.XLOOKUP($A2262,[1]MedicHistory!A:A,[1]MedicHistory!C:C,"")} -> 4.42 | E2262: =_xlfn.XLOOKUP($A2262,[1]MedicHistory!A:A,[1]MedicHistory!D:D,"") -> yes | F2262: =_xlfn.XLOOKUP($A2262,[1]MedicHistory!A:A,[1]MedicHistory!E:E,"") -> No | G2262: =_xlfn.XLOOKUP($A2262,[1]MedicHistory!A:A,[1]MedicHistory!F:F,"") -> Yes | H2262: =_xlfn.XLOOKUP($A2262,[1]MedicHistory!A:A,[1]MedicHistory!G:G,"") -> 1 | I2262: =_xlfn.XLOOKUP($A2262,[1]MedicHistory!A:A,[1]MedicHistory!H:H,"") -> No | J2262: =_xlfn.XLOOKUP($A2262,[1]MedicHistory!A:A,[1]MedicHistory!K:K,"") -> Normal | K2262: =_xlfn.XLOOKUP($A2262,[1]MedicHistory!A:A,[1]MedicHistory!I:I,"") -> Under weight | L2262: =_xlfn.XLOOKUP($A2262,[1]Hospitalisation!A:A,[1]Hospitalisation!C:C,"") -> 1253 | M2262: =_xlfn.XLOOKUP($A2262,[1]Hospitalisation!A:A,[1]Hospitalisation!I:I,"") -> tier - 2 | N2262: =_xlfn.XLOOKUP($A2262,[1]Hospitalisation!A:A,[1]Hospitalisation!J:J,"") -> tier - 2 | O2262: =_xlfn.XLOOKUP($A2262,[1]Hospitalisation!A:A,[1]Hospitalisation!K:K,"") -> R1013 | P2262: =_xlfn.XLOOKUP($A2262,[1]Hospitalisation!A:A,[1]Hospitalisation!L:L,"") -> 19 | Q2262: =_xlfn.XLOOKUP($A2262,[1]Hospitalisation!A:A,[1]Hospitalisation!M:M,"") -> 37929
A2263: Id2262 | B2263: =_xlfn.XLOOKUP(A2263,[1]Customer!A:A,[1]Customer!C:C,"") -> Daniel | C2263: {=_xlfn.XLOOKUP($A2263,[1]MedicHistory!A:A,[1]MedicHistory!B:B,"")} -> 27.6 | D2263: {=_xlfn.XLOOKUP($A2263,[1]MedicHistory!A:A,[1]MedicHistory!C:C,"")} -> 4.01 | E2263: =_xlfn.XLOOKUP($A2263,[1]MedicHistory!A:A,[1]MedicHistory!D:D,"") -> No | F2263: =_xlfn.XLOOKUP($A2263,[1]MedicHistory!A:A,[1]MedicHistory!E:E,"") -> No | G2263: =_xlfn.XLOOKUP($A2263,[1]MedicHistory!A:A,[1]MedicHistory!F:F,"") -> Yes | H2263: =_xlfn.XLOOKUP($A2263,[1]MedicHistory!A:A,[1]MedicHistory!G:G,"") -> 1 | I2263: =_xlfn.XLOOKUP($A2263,[1]MedicHistory!A:A,[1]MedicHistory!H:H,"") -> No | J2263: =_xlfn.XLOOKUP($A2263,[1]MedicHistory!A:A,[1]MedicHistory!K:K,"") -> Normal | K2263: =_xlfn.XLOOKUP($A2263,[1]MedicHistory!A:A,[1]MedicHistory!I:I,"") -> over weight | L2263: =_xlfn.XLOOKUP($A2263,[1]Hospitalisation!A:A,[1]Hospitalisation!C:C,"") -> 1252.41 | M2263: =_xlfn.XLOOKUP($A2263,[1]Hospitalisation!A:A,[1]Hospitalisation!I:I,"") -> tier - 2 | N2263: =_xlfn.XLOOKUP($A2263,[1]Hospitalisation!A:A,[1]Hospitalisation!J:J,"") -> tier - 3 | O2263: =_xlfn.XLOOKUP($A2263,[1]Hospitalisation!A:A,[1]Hospitalisation!K:K,"") -> R1011 | P2263: =_xlfn.XLOOKUP($A2263,[1]Hospitalisation!A:A,[1]Hospitalisation!L:L,"") -> 25 | Q2263: =_xlfn.XLOOKUP($A2263,[1]Hospitalisation!A:A,[1]Hospitalisation!M:M,"") -> 35688
A2264: Id2263 | B2264: =_xlfn.XLOOKUP(A2264,[1]Customer!A:A,[1]Customer!C:C,"") -> Jaime | C2264: {=_xlfn.XLOOKUP($A2264,[1]MedicHistory!A:A,[1]MedicHistory!B:B,"")} -> 20.7 | D2264: {=_xlfn.XLOOKUP($A2264,[1]MedicHistory!A:A,[1]MedicHistory!C:C,"")} -> 4.49 | E2264: =_xlfn.XLOOKUP($A2264,[1]MedicHistory!A:A,[1]MedicHistory!D:D,"") -> No | F2264: =_xlfn.XLOOKUP($A2264,[1]MedicHistory!A:A,[1]MedicHistory!E:E,"") -> No | G2264: =_xlfn.XLOOKUP($A2264,[1]MedicHistory!A:A,[1]MedicHistory!F:F,"") -> Yes | H2264: =_xlfn.XLOOKUP($A2264,[1]MedicHistory!A:A,[1]MedicHistory!G:G,"") -> 1 | I2264: =_xlfn.XLOOKUP($A2264,[1]MedicHistory!A:A,[1]MedicHistory!H:H,"") -> No | J2264: =_xlfn.XLOOKUP($A2264,[1]MedicHistory!A:A,[1]MedicHistory!K:K,"") -> Normal | K2264: =_xlfn.XLOOKUP($A2264,[1]MedicHistory!A:A,[1]MedicHistory!I:I,"") -> Normal weight | L2264: =_xlfn.XLOOKUP($A2264,[1]Hospitalisation!A:A,[1]Hospitalisation!C:C,"") -> 1242.82 | M2264: =_xlfn.XLOOKUP($A2264,[1]Hospitalisation!A:A,[1]Hospitalisation!I:I,"") -> tier - 2 | N2264: =_xlfn.XLOOKUP($A2264,[1]Hospitalisation!A:A,[1]Hospitalisation!J:J,"") -> tier - 1 | O2264: =_xlfn.XLOOKUP($A2264,[1]Hospitalisation!A:A,[1]Hospitalisation!K:K,"") -> R1011 | P2264: =_xlfn.XLOOKUP($A2264,[1]Hospitalisation!A:A,[1]Hospitalisation!L:L,"") -> 19 | Q2264: =_xlfn.XLOOKUP($A2264,[1]Hospitalisation!A:A,[1]Hospitalisation!M:M,"") -> 37872
A2265: Id2264 | B2265: =_xlfn.XLOOKUP(A2265,[1]Customer!A:A,[1]Customer!C:C,"") -> Mohd | C2265: {=_xlfn.XLOOKUP($A2265,[1]MedicHistory!A:A,[1]MedicHistory!B:B,"")} -> 20.3 | D2265: {=_xlfn.XLOOKUP($A2265,[1]MedicHistory!A:A,[1]MedicHistory!C:C,"")} -> 6.37 | E2265: =_xlfn.XLOOKUP($A2265,[1]MedicHistory!A:A,[1]MedicHistory!D:D,"") -> No | F2265: =_xlfn.XLOOKUP($A2265,[1]MedicHistory!A:A,[1]MedicHistory!E:E,"") -> No | G2265: =_xlfn.XLOOKUP($A2265,[1]MedicHistory!A:A,[1]MedicHistory!F:F,"") -> Yes | H2265: =_xlfn.XLOOKUP($A2265,[1]MedicHistory!A:A,[1]MedicHistory!G:G,"") -> 1 | I2265: =_xlfn.XLOOKUP($A2265,[1]MedicHistory!A:A,[1]MedicHistory!H:H,"") -> No | J2265: =_xlfn.XLOOKUP($A2265,[1]MedicHistory!A:A,[1]MedicHistory!K:K,"") -> Prediabetic | K2265: =_xlfn.XLOOKUP($A2265,[1]MedicHistory!A:A,[1]MedicHistory!I:I,"") -> Normal weight | L2265: =_xlfn.XLOOKUP($A2265,[1]Hospitalisation!A:A,[1]Hospitalisation!C:C,"") -> 1242.26 | M2265: =_xlfn.XLOOKUP($A2265,[1]Hospitalisation!A:A,[1]Hospitalisation!I:I,"") -> tier - 2 | N2265: =_xlfn.XLOOKUP($A2265,[1]Hospitalisation!A:A,[1]Hospitalisation!J:J,"") -> tier - 1 | O2265: =_xlfn.XLOOKUP($A2265,[1]Hospitalisation!A:A,[1]Hospitalisation!K:K,"") -> R1011 | P2265: =_xlfn.XLOOKUP($A2265,[1]Hospitalisation!A:A,[1]Hospitalisation!L:L,"") -> 19 | Q2265: =_xlfn.XLOOKUP($A2265,[1]Hospitalisation!A:A,[1]Hospitalisation!M:M,"") -> 37879
A2266: Id2265 | B2266: =_xlfn.XLOOKUP(A2266,[1]Customer!A:A,[1]Customer!C:C,"") -> Matthew | C2266: {=_xlfn.XLOOKUP($A2266,[1]MedicHistory!A:A,[1]MedicHistory!B:B,"")} -> 19.8 | D2266: {=_xlfn.XLOOKUP($A2266,[1]MedicHistory!A:A,[1]MedicHistory!C:C,"")} -> 5.12 | E2266: =_xlfn.XLOOKUP($A2266,[1]MedicHistory!A:A,[1]MedicHistory!D:D,"") -> No | F2266: =_xlfn.XLOOKUP($A2266,[1]MedicHistory!A:A,[1]MedicHistory!E:E,"") -> No | G2266: =_xlfn.XLOOKUP($A2266,[1]MedicHistory!A:A,[1]MedicHistory!F:F,"") -> Yes | H2266: =_xlfn.XLOOKUP($A2266,[1]MedicHistory!A:A,[1]MedicHistory!G:G,"") -> 1 | I2266: =_xlfn.XLOOKUP($A2266,[1]MedicHistory!A:A,[1]MedicHistory!H:H,"") -> No | J2266: =_xlfn.XLOOKUP($A2266,[1]MedicHistory!A:A,[1]MedicHistory!K:K,"") -> Normal | K2266: =_xlfn.XLOOKUP($A2266,[1]MedicHistory!A:A,[1]MedicHistory!I:I,"") -> Normal weight | L2266: =_xlfn.XLOOKUP($A2266,[1]Hospitalisation!A:A,[1]Hospitalisation!C:C,"") -> 1241.57 | M2266: =_xlfn.XLOOKUP($A2266,[1]Hospitalisation!A:A,[1]Hospitalisation!I:I,"") -> tier - 2 | N2266: =_xlfn.XLOOKUP($A2266,[1]Hospitalisation!A:A,[1]Hospitalisation!J:J,"") -> tier - 2 | O2266: =_xlfn.XLOOKUP($A2266,[1]Hospitalisation!A:A,[1]Hospitalisation!K:K,"") -> R1011 | P2266: =_xlfn.XLOOKUP($A2266,[1]Hospitalisation!A:A,[1]Hospitalisation!L:L,"") -> 19 | Q2266: =_xlfn.XLOOKUP($A2266,[1]Hospitalisation!A:A,[1]Hospitalisation!M:M,"") -> 37835
A2267: Id2266 | B2267: =_xlfn.XLOOKUP(A2267,[1]Customer!A:A,[1]Customer!C:C,"") -> Elizabeth | C2267: {=_xlfn.XLOOKUP($A2267,[1]MedicHistory!A:A,[1]MedicHistory!B:B,"")} -> 21.87 | D2267: {=_xlfn.XLOOKUP($A2267,[1]MedicHistory!A:A,[1]MedicHistory!C:C,"")} -> 8.59 | E2267: =_xlfn.XLOOKUP($A2267,[1]MedicHistory!A:A,[1]MedicHistory!D:D,"") -> No | F2267: =_xlfn.XLOOKUP($A2267,[1]MedicHistory!A:A,[1]MedicHistory!E:E,"") -> No | G2267: =_xlfn.XLOOKUP($A2267,[1]MedicHistory!A:A,[1]MedicHistory!F:F,"") -> No | H2267: =_xlfn.XLOOKUP($A2267,[1]MedicHistory!A:A,[1]MedicHistory!G:G,"") -> 0 | I2267: =_xlfn.XLOOKUP($A2267,[1]MedicHistory!A:A,[1]MedicHistory!H:H,"") -> No | J2267: =_xlfn.XLOOKUP($A2267,[1]MedicHistory!A:A,[1]MedicHistory!K:K,"") -> Diabetic | K2267: =_xlfn.XLOOKUP($A2267,[1]MedicHistory!A:A,[1]MedicHistory!I:I,"") -> Normal weight | L2267: =_xlfn.XLOOKUP($A2267,[1]Hospitalisation!A:A,[1]Hospitalisation!C:C,"") -> 1241 | M2267: =_xlfn.XLOOKUP($A2267,[1]Hospitalisation!A:A,[1]Hospitalisation!I:I,"") -> tier - 2 | N2267: =_xlfn.XLOOKUP($A2267,[1]Hospitalisation!A:A,[1]Hospitalisation!J:J,"") -> tier - 2 | O2267: =_xlfn.XLOOKUP($A2267,[1]Hospitalisation!A:A,[1]Hospitalisation!K:K,"") -> R1013 | P2267: =_xlfn.XLOOKUP($A2267,[1]Hospitalisation!A:A,[1]Hospitalisation!L:L,"") -> 19 | Q2267: =_xlfn.XLOOKUP($A2267,[1]Hospitalisation!A:A,[1]Hospitalisation!M:M,"") -> 37803
A2268: Id2267 | B2268: =_xlfn.XLOOKUP(A2268,[1]Customer!A:A,[1]Customer!C:C,"") -> Katie | C2268: {=_xlfn.XLOOKUP($A2268,[1]MedicHistory!A:A,[1]MedicHistory!B:B,"")} -> 16.6 | D2268: {=_xlfn.XLOOKUP($A2268,[1]MedicHistory!A:A,[1]MedicHistory!C:C,"")} -> 5.87 | E2268: =_xlfn.XLOOKUP($A2268,[1]MedicHistory!A:A,[1]MedicHistory!D:D,"") -> No | F2268: =_xlfn.XLOOKUP($A2268,[1]MedicHistory!A:A,[1]MedicHistory!E:E,"") -> No | G2268: =_xlfn.XLOOKUP($A2268,[1]MedicHistory!A:A,[1]MedicHistory!F:F,"") -> No | H2268: =_xlfn.XLOOKUP($A2268,[1]MedicHistory!A:A,[1]MedicHistory!G:G,"") -> 1 | I2268: =_xlfn.XLOOKUP($A2268,[1]MedicHistory!A:A,[1]MedicHistory!H:H,"") -> No | J2268: =_xlfn.XLOOKUP($A2268,[1]MedicHistory!A:A,[1]MedicHistory!K:K,"") -> Prediabetic | K2268: =_xlfn.XLOOKUP($A2268,[1]MedicHistory!A:A,[1]MedicHistory!I:I,"") -> Under weight | L2268: =_xlfn.XLOOKUP($A2268,[1]Hospitalisation!A:A,[1]Hospitalisation!C:C,"") -> 1240 | M2268: =_xlfn.XLOOKUP($A2268,[1]Hospitalisation!A:A,[1]Hospitalisation!I:I,"") -> tier - 2 | N2268: =_xlfn.XLOOKUP($A2268,[1]Hospitalisation!A:A,[1]Hospitalisation!J:J,"") -> tier - 1 | O2268: =_xlfn.XLOOKUP($A2268,[1]Hospitalisation!A:A,[1]Hospitalisation!K:K,"") -> R1012 | P2268: =_xlfn.XLOOKUP($A2268,[1]Hospitalisation!A:A,[1]Hospitalisation!L:L,"") -> 20 | Q2268: =_xlfn.XLOOKUP($A2268,[1]Hospitalisation!A:A,[1]Hospitalisation!M:M,"") -> 37540
A2269: Id2268 | B2269: =_xlfn.XLOOKUP(A2269,[1]Customer!A:A,[1]Customer!C:C,"") -> Christi | C2269: {=_xlfn.XLOOKUP($A2269,[1]MedicHistory!A:A,[1]MedicHistory!B:B,"")} -> 21.98 | D2269: {=_xlfn.XLOOKUP($A2269,[1]MedicHistory!A:A,[1]MedicHistory!C:C,"")} -> 7.03 | E2269: =_xlfn.XLOOKUP($A2269,[1]MedicHistory!A:A,[1]MedicHistory!D:D,"") -> No | F2269: =_xlfn.XLOOKUP($A2269,[1]MedicHistory!A:A,[1]MedicHistory!E:E,"") -> No | G2269: =_xlfn.XLOOKUP($A2269,[1]MedicHistory!A:A,[1]MedicHistory!F:F,"") -> No | H2269: =_xlfn.XLOOKUP($A2269,[1]MedicHistory!A:A,[1]MedicHistory!G:G,"") -> 0 | I2269: =_xlfn.XLOOKUP($A2269,[1]MedicHistory!A:A,[1]MedicHistory!H:H,"") -> No | J2269: =_xlfn.XLOOKUP($A2269,[1]MedicHistory!A:A,[1]MedicHistory!K:K,"") -> Diabetic | K2269: =_xlfn.XLOOKUP($A2269,[1]MedicHistory!A:A,[1]MedicHistory!I:I,"") -> Normal weight | L2269: =_xlfn.XLOOKUP($A2269,[1]Hospitalisation!A:A,[1]Hospitalisation!C:C,"") -> 1237 | M2269: =_xlfn.XLOOKUP($A2269,[1]Hospitalisation!A:A,[1]Hospitalisation!I:I,"") -> tier - 2 | N2269: =_xlfn.XLOOKUP($A2269,[1]Hospitalisation!A:A,[1]Hospitalisation!J:J,"") -> tier - 2 | O2269: =_xlfn.XLOOKUP($A2269,[1]Hospitalisation!A:A,[1]Hospitalisation!K:K,"") -> R1013 | P2269: =_xlfn.XLOOKUP($A2269,[1]Hospitalisation!A:A,[1]Hospitalisation!L:L,"") -> 24 | Q2269: =_xlfn.XLOOKUP($A2269,[1]Hospitalisation!A:A,[1]Hospitalisation!M:M,"") -> 36141
A2270: Id2269 | B2270: =_xlfn.XLOOKUP(A2270,[1]Customer!A:A,[1]Customer!C:C,"") -> Sandra | C2270: {=_xlfn.XLOOKUP($A2270,[1]MedicHistory!A:A,[1]MedicHistory!B:B,"")} -> 19.7 | D2270: {=_xlfn.XLOOKUP($A2270,[1]MedicHistory!A:A,[1]MedicHistory!C:C,"")} -> 5.51 | E2270: =_xlfn.XLOOKUP($A2270,[1]MedicHistory!A:A,[1]MedicHistory!D:D,"") -> No | F2270: =_xlfn.XLOOKUP($A2270,[1]MedicHistory!A:A,[1]MedicHistory!E:E,"") -> No | G2270: =_xlfn.XLOOKUP($A2270,[1]MedicHistory!A:A,[1]MedicHistory!F:F,"") -> No | H2270: =_xlfn.XLOOKUP($A2270,[1]MedicHistory!A:A,[1]MedicHistory!G:G,"") -> 1 | I2270: =_xlfn.XLOOKUP($A2270,[1]MedicHistory!A:A,[1]MedicHistory!H:H,"") -> No | J2270: =_xlfn.XLOOKUP($A2270,[1]MedicHistory!A:A,[1]MedicHistory!K:K,"") -> Normal | K2270: =_xlfn.XLOOKUP($A2270,[1]MedicHistory!A:A,[1]MedicHistory!I:I,"") -> Normal weight | L2270: =_xlfn.XLOOKUP($A2270,[1]Hospitalisation!A:A,[1]Hospitalisation!C:C,"") -> 1234 | M2270: =_xlfn.XLOOKUP($A2270,[1]Hospitalisation!A:A,[1]Hospitalisation!I:I,"") -> tier - 2 | N2270: =_xlfn.XLOOKUP($A2270,[1]Hospitalisation!A:A,[1]Hospitalisation!J:J,"") -> tier - 1 | O2270: =_xlfn.XLOOKUP($A2270,[1]Hospitalisation!A:A,[1]Hospitalisation!K:K,"") -> R1013 | P2270: =_xlfn.XLOOKUP($A2270,[1]Hospitalisation!A:A,[1]Hospitalisation!L:L,"") -> 20 | Q2270: =_xlfn.XLOOKUP($A2270,[1]Hospitalisation!A:A,[1]Hospitalisation!M:M,"") -> 37450
A2271: Id2270 | B2271: =_xlfn.XLOOKUP(A2271,[1]Customer!A:A,[1]Customer!C:C,"") -> Katharine | C2271: {=_xlfn.XLOOKUP($A2271,[1]MedicHistory!A:A,[1]MedicHistory!B:B,"")} -> 19.21 | D2271: {=_xlfn.XLOOKUP($A2271,[1]MedicHistory!A:A,[1]MedicHistory!C:C,"")} -> 4.76 | E2271: =_xlfn.XLOOKUP($A2271,[1]MedicHistory!A:A,[1]MedicHistory!D:D,"") -> No | F2271: =_xlfn.XLOOKUP($A2271,[1]MedicHistory!A:A,[1]MedicHistory!E:E,"") -> yes | G2271: =_xlfn.XLOOKUP($A2271,[1]MedicHistory!A:A,[1]MedicHistory!F:F,"") -> No | H2271: =_xlfn.XLOOKUP($A2271,[1]MedicHistory!A:A,[1]MedicHistory!G:G,"") -> 1 | I2271: =_xlfn.XLOOKUP($A2271,[1]MedicHistory!A:A,[1]MedicHistory!H:H,"") -> No | J2271: =_xlfn.XLOOKUP($A2271,[1]MedicHistory!A:A,[1]MedicHistory!K:K,"") -> Normal | K2271: =_xlfn.XLOOKUP($A2271,[1]MedicHistory!A:A,[1]MedicHistory!I:I,"") -> Normal weight | L2271: =_xlfn.XLOOKUP($A2271,[1]Hospitalisation!A:A,[1]Hospitalisation!C:C,"") -> 1228 | M2271: =_xlfn.XLOOKUP($A2271,[1]Hospitalisation!A:A,[1]Hospitalisation!I:I,"") -> tier - 2 | N2271: =_xlfn.XLOOKUP($A2271,[1]Hospitalisation!A:A,[1]Hospitalisation!J:J,"") -> tier - 1 | O2271: =_xlfn.XLOOKUP($A2271,[1]Hospitalisation!A:A,[1]Hospitalisation!K:K,"") -> R1012 | P2271: =_xlfn.XLOOKUP($A2271,[1]Hospitalisation!A:A,[1]Hospitalisation!L:L,"") -> 24 | Q2271: =_xlfn.XLOOKUP($A2271,[1]Hospitalisation!A:A,[1]Hospitalisation!M:M,"") -> 36084
A2272: Id2271 | B2272: =_xlfn.XLOOKUP(A2272,[1]Customer!A:A,[1]Customer!C:C,"") -> Jerome | C2272: {=_xlfn.XLOOKUP($A2272,[1]MedicHistory!A:A,[1]MedicHistory!B:B,"")} -> 19.3 | D2272: {=_xlfn.XLOOKUP($A2272,[1]MedicHistory!A:A,[1]MedicHistory!C:C,"")} -> 4.7 | E2272: =_xlfn.XLOOKUP($A2272,[1]MedicHistory!A:A,[1]MedicHistory!D:D,"") -> No | F2272: =_xlfn.XLOOKUP($A2272,[1]MedicHistory!A:A,[1]MedicHistory!E:E,"") -> yes | G2272: =_xlfn.XLOOKUP($A2272,[1]MedicHistory!A:A,[1]MedicHistory!F:F,"") -> No | H2272: =_xlfn.XLOOKUP($A2272,[1]MedicHistory!A:A,[1]MedicHistory!G:G,"") -> 1 | I2272: =_xlfn.XLOOKUP($A2272,[1]MedicHistory!A:A,[1]MedicHistory!H:H,"") -> No | J2272: =_xlfn.XLOOKUP($A2272,[1]MedicHistory!A:A,[1]MedicHistory!K:K,"") -> Normal | K2272: =_xlfn.XLOOKUP($A2272,[1]MedicHistory!A:A,[1]MedicHistory!I:I,"") -> Normal weight | L2272: =_xlfn.XLOOKUP($A2272,[1]Hospitalisation!A:A,[1]Hospitalisation!C:C,"") -> 1224 | M2272: =_xlfn.XLOOKUP($A2272,[1]Hospitalisation!A:A,[1]Hospitalisation!I:I,"") -> tier - 2 | N2272: =_xlfn.XLOOKUP($A2272,[1]Hospitalisation!A:A,[1]Hospitalisation!J:J,"") -> tier - 1 | O2272: =_xlfn.XLOOKUP($A2272,[1]Hospitalisation!A:A,[1]Hospitalisation!K:K,"") -> R1013 | P2272: =_xlfn.XLOOKUP($A2272,[1]Hospitalisation!A:A,[1]Hospitalisation!L:L,"") -> 18 | Q2272: =_xlfn.XLOOKUP($A2272,[1]Hospitalisation!A:A,[1]Hospitalisation!M:M,"") -> 38177
A2273: Id2272 | B2273: =_xlfn.XLOOKUP(A2273,[1]Customer!A:A,[1]Customer!C:C,"") -> Julia | C2273: {=_xlfn.XLOOKUP($A2273,[1]MedicHistory!A:A,[1]MedicHistory!B:B,"")} -> 16.22 | D2273: {=_xlfn.XLOOKUP($A2273,[1]MedicHistory!A:A,[1]MedicHistory!C:C,"")} -> 6.21 | E2273: =_xlfn.XLOOKUP($A2273,[1]MedicHistory!A:A,[1]MedicHistory!D:D,"") -> yes | F2273: =_xlfn.XLOOKUP($A2273,[1]MedicHistory!A:A,[1]MedicHistory!E:E,"") -> No | G2273: =_xlfn.XLOOKUP($A2273,[1]MedicHistory!A:A,[1]MedicHistory!F:F,"") -> No | H2273: =_xlfn.XLOOKUP($A2273,[1]MedicHistory!A:A,[1]MedicHistory!G:G,"") -> 0 | I2273: =_xlfn.XLOOKUP($A2273,[1]MedicHistory!A:A,[1]MedicHistory!H:H,"") -> No | J2273: =_xlfn.XLOOKUP($A2273,[1]MedicHistory!A:A,[1]MedicHistory!K:K,"") -> Prediabetic | K2273: =_xlfn.XLOOKUP($A2273,[1]MedicHistory!A:A,[1]MedicHistory!I:I,"") -> Under weight | L2273: =_xlfn.XLOOKUP($A2273,[1]Hospitalisation!A:A,[1]Hospitalisation!C:C,"") -> 1220 | M2273: =_xlfn.XLOOKUP($A2273,[1]Hospitalisation!A:A,[1]Hospitalisation!I:I,"") -> tier - 2 | N2273: =_xlfn.XLOOKUP($A2273,[1]Hospitalisation!A:A,[1]Hospitalisation!J:J,"") -> tier - 3 | O2273: =_xlfn.XLOOKUP($A2273,[1]Hospitalisation!A:A,[1]Hospitalisation!K:K,"") -> R1012 | P2273: =_xlfn.XLOOKUP($A2273,[1]Hospitalisation!A:A,[1]Hospitalisation!L:L,"") -> 18 | Q2273: =_xlfn.XLOOKUP($A2273,[1]Hospitalisation!A:A,[1]Hospitalisation!M:M,"") -> 38295
... A2336: Id2335 | B2336: =_xlfn.XLOOKUP(A2336,[1]Customer!A:A,[1]Customer!C:C,"") -> Aaron | C2336: {=_xlfn.XLOOKUP($A2336,[1]MedicHistory!A:A,[1]MedicHistory!B:B,"")} -> 17.58 | D2336: {=_xlfn.XLOOKUP($A2336,[1]MedicHistory!A:A,[1]MedicHistory!C:C,"")} -> 4.51 | E2336: =_xlfn.XLOOKUP($A2336,[1]MedicHistory!A:A,[1]MedicHistory!D:D,"") -> No | F2336: =_xlfn.XLOOKUP($A2336,[1]MedicHistory!A:A,[1]MedicHistory!E:E,"") -> No | G2336: =_xlfn.XLOOKUP($A2336,[1]MedicHistory!A:A,[1]MedicHistory!F:F,"") -> No | H2336: =_xlfn.XLOOKUP($A2336,[1]MedicHistory!A:A,[1]MedicHistory!G:G,"") -> 1 | I2336: =_xlfn.XLOOKUP($A2336,[1]MedicHistory!A:A,[1]MedicHistory!H:H,"") -> No | J2336: =_xlfn.XLOOKUP($A2336,[1]MedicHistory!A:A,[1]MedicHistory!K:K,"") -> Normal | K2336: =_xlfn.XLOOKUP($A2336,[1]MedicHistory!A:A,[1]MedicHistory!I:I,"") -> Under weight | L2336: =_xlfn.XLOOKUP($A2336,[1]Hospitalisation!A:A,[1]Hospitalisation!C:C,"") -> 563.84 | M2336: =_xlfn.XLOOKUP($A2336,[1]Hospitalisation!A:A,[1]Hospitalisation!I:I,"") -> tier - 2 | N2336: =_xlfn.XLOOKUP($A2336,[1]Hospitalisation!A:A,[1]Hospitalisation!J:J,"") -> tier - 3 | O2336: =_xlfn.XLOOKUP($A2336,[1]Hospitalisation!A:A,[1]Hospitalisation!K:K,"") -> R1013 | P2336: =_xlfn.XLOOKUP($A2336,[1]Hospitalisation!A:A,[1]Hospitalisation!L:L,"") -> 30 | Q2336: =_xlfn.XLOOKUP($A2336,[1]Hospitalisation!A:A,[1]Hospitalisation!M:M,"") -> 33794
A2337: Toal customer | B2337: =_xlfn.XLOOKUP(A2337,[1]Customer!A:A,[1]Customer!C:C,"") | C2337: Average Bmi | D2337: Average hba1c | E2337: =_xlfn.XLOOKUP($A2337,[1]MedicHistory!A:A,[1]MedicHistory!D:D,"") | F2337: Count | G2337: =_xlfn.XLOOKUP($A2337,[1]MedicHistory!A:A,[1]MedicHistory!F:F,"") | H2337: =_xlfn.XLOOKUP($A2337,[1]MedicHistory!A:A,[1]MedicHistory!G:G,"") | I2337: =_xlfn.XLOOKUP($A2337,[1]MedicHistory!A:A,[1]MedicHistory!H:H,"") | J2337: =_xlfn.XLOOKUP($A2337,[1]MedicHistory!A:A,[1]MedicHistory!K:K,"") | K2337: =_xlfn.XLOOKUP($A2337,[1]MedicHistory!A:A,[1]MedicHistory!I:I,"") | L2337: Average | M2337: =_xlfn.XLOOKUP($A2337,[1]Hospitalisation!A:A,[1]Hospitalisation!I:I,"") | N2337: =_xlfn.XLOOKUP($A2337,[1]Hospitalisation!A:A,[1]Hospitalisation!J:J,"") | O2337: =_xlfn.XLOOKUP($A2337,[1]Hospitalisation!A:A,[1]Hospitalisation!K:K,"") | P2337: Average | Q2337: =_xlfn.XLOOKUP($A2337,[1]Hospitalisation!A:A,[1]Hospitalisation!M:M,"")
A2338: =SUBTOTAL(103,'Healthcare (3)'!$A$2:$A$2336) -> 2335 | C2338: =SUBTOTAL(101,'Healthcare (3)'!$C$2:$C$2336) -> 30.972649 | D2338: =SUBTOTAL(101,'Healthcare (3)'!$D$2:$D$2336) -> 6.5789979 | F2338: =SUBTOTAL(103,'Healthcare (3)'!$F$2:$F$2336) -> 2335 | L2338: =SUBTOTAL(101,'Healthcare (3)'!$L$2:$L$2336) -> 13529.918 | P2338: =SUBTOTAL(101,'Healthcare (3)'!$P$2:$P$2336) -> 39.221842
L2339: =SUM(101,'Healthcare (3)'!$L$2:$L$2336) -> 31592460

Sheet Insights
C2: Quick Analysis o/p: | G2: Manual Dashboard: | Y2: Row Labels | Z2: Average of charges
C3: Total hospitalisation count, | E3: 1579 | Y3: Normal weight | Z3: 9851.9225
C4: Total customers count, | E4: =SUBTOTAL(103,'Healthcare (3)'!$A$2:$A$2336) -> 2335 | Y4: Obisity | Z4: 16661.463
C5: Total healthcare costs, | E5: =SUBTOTAL(109,'Healthcare (3)'!$L$2:$L$2336) -> 31592359 | Y5: over weight | Z5: 11435.413
C6: Average costs:Overall: | E6: 13529.92 | Y6: Under weight | Z6: 6899.3175
C7: Average costs:By group of age: | E7: 39.22 | Y7: Grand Total | Z7: 13529.918
C8: Medical metrics:Based on Heartissuse: | E8: 13529
Y9: Count of Cancer history | Z9: Column Labels
C10: Quick Analysis Charts: | Y10: Smoker | Z10: No | AA10: Yes | AB10: Grand Total
Y11: No | Z11: 1538 | AA11: 307 | AB11: 1845
Y12: yes | Z12: 404 | AA12: 84 | AB12: 488
Y13: Grand Total | Z13: 1942 | AA13: 391 | AB13: 2333
G14: Insights:
H15: Smoker Vs Non Smoker: | Y15: Hsp Tier | Z15: Average of charges | AA15: Average of BMI | AB15: Average of HBA1C | AC15: Average of Age | AD15: Count of MajorSurgeries | AE15: Count of Heart Issues
H16: * | I16: The majority of the population do not smoke. | Y16: tier - 1 | Z16: 30129.199 | AA16: 34.886184 | AB16: 6.6087829 | AC16: 41.105263 | AD16: 304 | AE16: 304
H17: * | I17: Hence Cancer history does not related apperar to be directly linked to smoking in this dataset. | Y17: tier - 2 | Z17: 11865.269 | AA17: 30.201315 | AB17: 6.4259193 | AC17: 37.104634 | AD17: 1338 | AE17: 1338
H18: Distribution of Charges: | Y18: tier - 3 | Z18: 9462.2693 | AA18: 30.74513 | AB18: 6.8614863 | AC18: 42.483405 | AD18: 693 | AE18: 693
H19: * | I19: Medical cost rise as BMI category increases | Y19: Grand Total | Z19: 13529.918 | AA19: 30.972649 | AB19: 6.5789979 | AC19: 39.221842 | AD19: 2335 | AE19: 2335
H20: * | I20: Charges grow progressively from under weight to obese categories. | Y20: Row Labels | Z20: Average of charges
H21: Combined Metrics: | Y21: tier - 1 | Z21: 30129.199
Y22: tier - 2 | Z22: 11865.269
Y23: tier - 3 | Z23: 9462.2693
Y24: Grand Total | Z24: 13529.918
Y25: Heart Issues | Z25: Average of charges
Y26: No | Z26: 13036.026
H27: Disease Burden Distribution: | Y27: yes | Z27: 14281.423
H28: * | I28: Heart Issues appear to be the largest segment | Y28: Grand Total | Z28: 13529.918
H29: * | I29: Cancer history and Major Surgeries form moderate proportions
H30: * | I30: Transplant cases are the smallest, but likely represent high individual costs.
H31: * | I31: Heart issues dominate the disease burden, followed by cancer and major surgeries, indicating a higher prevalence of chronic conditions
H32: Charges Distribution amoung Diabetics:
H33: * | I33: Diabetic patients have the highest total charges at 1,26,418
H34: * | I34: Costs increase as the condition progresses from prediabetic → normal → diabetic.
H35: * | I35: Diabetes is a major factor contributing to higher healthcare charges in your dataset. Preventive care for prediabetics could reduce overall costs

Sheet Dashboard
A1: Healthcare Dashboard -AI Analysis

Sheet Sheet4

Sheet Excersice
H2: Transpalant | I2: Count of Heart Issues
A3: Row Labels | B3: Average of charges | H3: 18 | I3: 1
A4: tier - 1 | B4: 25669.337 | H4: 19 | I4: 4
A5: tier - 2 | B5: 23842.451 | H5: 20 | I5: 1
A6: tier - 3 | B6: 20632.332 | H6: 21 | I6: 1
A7: Grand Total | B7: 24088.08 | H7: 22 | I7: 1
H8: 23 | I8: 1
H9: 24 | I9: 5
H10: 25 | I10: 1
H11: 27 | I11: 4
H12: 28 | I12: 6
H13: 29 | I13: 2
H14: 30 | I14: 1
B15: Count of Customer ID | C15: Column Labels | H15: 31 | I15: 1
B16: Row Labels | C16: Diabetic | D16: Normal | E16: Prediabetic | F16: Grand Total | H16: 32 | I16: 2
B17: 18 | D17: 1 | F17: 1 | H17: 33 | I17: 1
B18: 19 | C18: 1 | D18: 2 | E18: 1 | F18: 4 | H18: 34 | I18: 3
B19: 20 | C19: 1 | F19: 1 | H19: 35 | I19: 4
B20: 21 | D20: 1 | F20: 1 | H20: 36 | I20: 2
B21: 22 | C21: 1 | F21: 1 | H21: 38 | I21: 2
B22: 23 | C22: 1 | F22: 1 | H22: 39 | I22: 1
B23: 24 | C23: 3 | D23: 1 | E23: 1 | F23: 5 | H23: 40 | I23: 4
B24: 25 | E24: 1 | F24: 1 | H24: 43 | I24: 2
B25: 27 | C25: 1 | D25: 1 | E25: 2 | F25: 4 | H25: 44 | I25: 1
B26: 28 | C26: 4 | E26: 2 | F26: 6 | H26: 45 | I26: 2
B27: 29 | E27: 2 | F27: 2 | H27: 47 | I27: 3
B28: 30 | D28: 1 | F28: 1 | H28: 48 | I28: 4
B29: 31 | D29: 1 | F29: 1 | H29: 49 | I29: 1
B30: 32 | C30: 1 | E30: 1 | F30: 2 | H30: 51 | I30: 2
B31: 33 | D31: 1 | F31: 1 | H31: 52 | I31: 4
B32: 34 | C32: 1 | D32: 1 | E32: 1 | F32: 3 | H32: 53 | I32: 3
B33: 35 | D33: 3 | E33: 1 | F33: 4 | H33: 54 | I33: 1
B34: 36 | C34: 1 | E34: 1 | F34: 2 | H34: 55 | I34: 1
B35: 38 | D35: 2 | F35: 2 | H35: 56 | I35: 1
B36: 39 | D36: 1 | F36: 1 | H36: 57 | I36: 1
B37: 40 | C37: 2 | D37: 2 | F37: 4 | H37: 60 | I37: 4
B38: 43 | D38: 2 | F38: 2 | H38: 61 | I38: 1
B39: 44 | D39: 1 | F39: 1 | H39: 62 | I39: 2
B40: 45 | D40: 1 | E40: 1 | F40: 2 | H40: 63 | I40: 3 | K40: Transpalant | L40: Count of Heart Issues
B41: 47 | C41: 1 | D41: 2 | F41: 3 | H41: 64 | I41: 1 | K41: No | L41: 413
B42: 48 | C42: 2 | D42: 2 | F42: 4 | H42: Grand Total | I42: 85 | K42: yes | L42: 24
B43: 49 | C43: 1 | F43: 1 | K43: Grand Total | L43: 437
B44: 51 | C44: 1 | D44: 1 | F44: 2
B45: 52 | C45: 1 | D45: 3 | F45: 4
B46: 53 | C46: 2 | E46: 1 | F46: 3
B47: 54 | D47: 1 | F47: 1
B48: 55 | C48: 1 | F48: 1 | K48: Row Labels | L48: Count of Cancer history
B49: 56 | E49: 1 | F49: 1 | K49: No | L49: 68
B50: 57 | D50: 1 | F50: 1 | K50: Yes | L50: 17
B51: 60 | C51: 1 | D51: 1 | E51: 2 | F51: 4 | K51: Grand Total | L51: 85
B52: 61 | D52: 1 | F52: 1
B53: 62 | C53: 1 | E53: 1 | F53: 2
B54: 63 | D54: 2 | E54: 1 | F54: 3
B55: 64 | E55: 1 | F55: 1
B56: Grand Total | C56: 28 | D56: 36 | E56: 21 | F56: 85
H57: Row Labels | I57: Average of charges | J57: Max of charges2 | K57: Min of charges3
H58: 18 | I58: 21259.38 | J58: 21259.38 | K58: 21259.38
H59: 19 | I59: 19907.615 | J59: 23967.38 | K59: 16420.49
H60: 20 | I60: 26926.51 | J60: 26926.51 | K60: 26926.51
H61: 21 | I61: 16577.78 | J61: 16577.78 | K61: 16577.78
H62: 22 | I62: 33753.32 | J62: 33753.32 | K62: 33753.32
H63: 23 | I63: 30625.65 | J63: 30625.65 | K63: 30625.65
H64: 24 | I64: 28545.862 | J64: 35069.37 | K64: 18608.26
H65: 25 | I65: 19798.05 | J65: 19798.05 | K65: 19798.05
H66: 27 | I66: 23291.685 | J66: 31322.53 | K66: 18259.22
H67: 28 | I67: 25877.155 | J67: 33025.32 | K67: 19594.81
H68: 29 | I68: 25671.445 | J68: 31980.89 | K68: 19362
H69: 30 | I69: 19515.54 | J69: 19515.54 | K69: 19515.54
... H96: 64 | I96: 26912.56 | J96: 26912.56 | K96: 26912.56
H97: Grand Total | I97: 24088.08 | J97: 35069.37 | K97: 13747.87

Sheet Sheet3
G27: Row Labels | H27: Average of charges
G28: Diabetic | H28: 27233.982
G29: Normal | H29: 20990.376
G30: Prediabetic | H30: 25203.895
G31: Grand Total | H31: 24088.08

Sheet Sheet1
A3: Diabetics | B3: Sum of charges
A4: Diabetic | B4: 12638305 | O4: Count of Customer ID
A5: Normal | B5: 13238778 | N5: No
A6: Prediabetic | B6: 5714711.8 | N6: No
N7: No
N8: 0 | O8: 34
N9: 1 | O9: 8
N10: 2 | O10: 3
N11: 3 | O11: 2
N12: yes
N13: 0 | O13: 7
N14: 1 | O14: 8
N15: 2 | O15: 4
N16: Yes
N17: No
N18: 1 | O18: 8
N19: yes
N20: 1 | O20: 9
N21: yes
N22: No
N23: No
N24: 1 | O24: 2
N25: Grand Total | O25: 85
